Workbook
Name _1Excel_BuiltIn_Database_1_1: #REF!
Name _2Excel_BuiltIn_Print_Area_5_1: #REF!
Name _Hlk156713282_5: #REF!
Name Drage: #REF!
Name Drage_14: #REF!
Name Drage_2: #REF!
Name Drage_3: #REF!
Name Drage_6: #REF!
Name Drage_6_14: #REF!
Name Excel_BuiltIn__FilterDatabase_1: #REF!
Name Excel_BuiltIn__FilterDatabase_1_1: #REF!
Name Excel_BuiltIn__FilterDatabase_5: #REF!
Name Excel_BuiltIn__FilterDatabase_5_1: #REF!
Name Excel_BuiltIn__FilterDatabase_5_6: #REF!
Name Excel_BuiltIn_Database: #REF!
Name Excel_BuiltIn_Database_1: #REF!
Name Excel_BuiltIn_Database_2: #REF!
Name Excel_BuiltIn_Database_3: #REF!
Name Excel_BuiltIn_Print_Area_18: #REF!
Name Excel_BuiltIn_Print_Area_5: #REF!
Name Excel_BuiltIn_Print_Area_6: #REF!
Name g: '[1]Karamel Vyr Price'!$R$81:$R$84
Name g_3: '[1]Karamel Vyr Price'!$R$81:$R$84
Name g_5: '[1]Karamel Vyr Price'!$R$81:$R$84
Name Iris: #REF!
Name Iris_14: #REF!
Name Iris_2: #REF!
Name Iris_3: #REF!
Name Iris_6: #REF!
Name Iris_6_14: #REF!
Name Karamel: #REF!
Name Karamel_14: #REF!
Name Karamel_2: #REF!
Name Karamel_3: #REF!
Name Karamel_6: #REF!
Name Karamel_6_14: #REF!
Name KEKSY: '[2]Bisquet Plan Price'!$R$108:$R$110
Name KEKSY_3: #REF!
Name KEKSY_5: '[2]Bisquet Plan Price'!$R$108:$R$110
Name KEKSY_6: '[2]Bisquet Plan Price'!$R$108:$R$110
Name Konditer: '[2]Sweet Plan Price'!$R$66:$R$103
Name Konditer_3: #REF!
Name Konditer_5: '[2]Sweet Plan Price'!$R$66:$R$103
Name Konditer_6: '[2]Sweet Plan Price'!$R$66:$R$103
Name Marmelad: '[2]Sweet Plan Price'!$R$122:$R$127
Name Marmelad_3: #REF!
Name Marmelad_5: '[2]Sweet Plan Price'!$R$122:$R$127
Name Marmelad_6: '[2]Sweet Plan Price'!$R$122:$R$127
Name NEGLAZUR: '[2]Sweet Plan Price'!$R$110:$R$113
Name NEGLAZUR_3: #REF!
Name NEGLAZUR_5: '[2]Sweet Plan Price'!$R$110:$R$113
Name NEGLAZUR_6: '[2]Sweet Plan Price'!$R$110:$R$113
Name Print_Area: 'Солар Вест'!$A$1:$BS$80
Name Pryami: #REF!
Name Pryami_14: #REF!
Name Pryami_2: #REF!
Name Pryami_3: #REF!
Name Pryami_5: #REF!
Name SHIDNI: '[2]Sweet Plan Price'!$R$119:$R$119
Name SHIDNI_3: #REF!

Sheet Заг.
B1: "ЗАТВЕРДЖУЮ"
B2: Генеральний директор
B3: ТзОВ "Волвест Груп"
B4: Корсак В.І. ______________
A5: Звіт про рух грошових коштів (КЕШ-ФЛО), грн
B6: Солар Вест Буд
B7: 2025 | C7: Січень | F7: Січень | I7: Лютий | L7: Лютий | O7: Березень | R7: Березень | U7: Квітень | X7: Квітень | AA7: Травень | AD7: Травень | AG7: Червень | AJ7: Червень | AM7: Липень | AP7: Липень | AS7: Серпень | AV7: Серпень | AY7: Вересень | BB7: Вересень | BE7: Жовтень | BH7: Жовтень | BK7: Листопад | BN7: Листопад | BQ7: Грудень | BT7: Грудень | BW7: Разом 2025 | BZ7: Разом 2025
B8: Залишок на початок | E8: =+D8+C8 -> 0 | F8: 26870.52 | G8: 42072 | H8: =+G8+F8 -> 68942.52 | K8: =+J8+I8 -> 0 | L8: =+F72 -> 6935.15 | M8: =+G72 -> 70184 | N8: =+M8+L8 -> 77119.15 | Q8: =+P8+O8 -> 0 | R8: =+L72 -> 17482.21 | S8: =+M72 -> 68137 | T8: =+S8+R8 -> 85619.21 | W8: =+V8+U8 -> 0 | X8: =+R72 -> 314119.37 | Y8: =+S72 -> 152076 | Z8: =+Y8+X8 -> 466195.37 | AC8: =+AB8+AA8 -> 0 | AD8: =+X72 -> 151289.85 | AE8: =+Y72 -> 341770 | AF8: =+AE8+AD8 -> 493059.85 | AI8: =+AH8+AG8 -> 0 | AJ8: =+AD72 -> 118305.4 | AK8: =+AE72 -> 499081 | AL8: =+AK8+AJ8 -> 617386.4 | AO8: =+AN8+AM8 -> 0 | AP8: =+AJ72 -> 203802.98 | AQ8: =+AK72 -> 445831 | AR8: =+AQ8+AP8 -> 649633.98 | AU8: =+AT8+AS8 -> 0 | AV8: =+AP72 -> 586048.84 | AW8: =+AQ72 -> 175836 | AX8: =+AW8+AV8 -> 761884.84 | BA8: =+AZ8+AY8 -> 0 | BB8: =+AV72 -> 68141.51 | BC8: =+AW72 -> 47388 | BD8: =+BC8+BB8 -> 115529.51 | BG8: =+BF8+BE8 -> 0 | BH8: =+BB72 -> 548793.92 | BI8: =+BC72 -> 61285 | BJ8: =+BI8+BH8 -> 610078.92 | BM8: =+BL8+BK8 -> 0 | BN8: =+BH72 -> 548793.92 | BO8: =+BI72 -> 61285 | BP8: =+BO8+BN8 -> 610078.92 | BS8: =+BR8+BQ8 -> 0 | BT8: =+BN72 -> 548793.92 | BU8: =+BO72 -> 61285 | BV8: =+BU8+BT8 -> 610078.92 | BY8: =+BX8+BW8 -> 0 | BZ8: =+BT72 -> 548793.92 | CA8: =+BU72 -> 61285 | CB8: =+CA8+BZ8 -> 610078.92
B9: 2025 | C9: План | F9: Факт | I9: План | L9: Факт | O9: План | R9: Факт | U9: План | X9: Факт | AA9: План | AD9: Факт | AG9: План | AJ9: Факт | AM9: План | AP9: Факт | AS9: План | AV9: Факт | AY9: План | BB9: Факт | BE9: План | BH9: Факт | BK9: План | BN9: Факт | BQ9: План | BT9: Факт | BW9: План | BZ9: Факт
A10: Код | B10: Стаття | C10: Банк + каса | D10: @ | E10: Разом | F10: Банк + каса | G10: @ | H10: Разом | I10: Банк + каса | J10: @ | K10: Разом | L10: Банк + каса | M10: @ | N10: Разом | O10: Банк + каса | P10: @ | Q10: Разом | R10: Банк + каса | S10: @ | T10: Разом | U10: Банк + каса | V10: @ | W10: Разом | X10: Банк + каса | Y10: @ | Z10: Разом | AA10: Банк + каса | AB10: @ | AC10: Разом | AD10: Банк + каса | AE10: @ | AF10: Разом | AG10: Банк + каса | AH10: @ | AI10: Разом | AJ10: Банк + каса | AK10: @ | AL10: Разом | AM10: Банк + каса | AN10: @ | AO10: Разом | AP10: Банк + каса | AQ10: @ | AR10: Разом | AS10: Банк + каса | AT10: @ | AU10: Разом | AV10: Банк + каса | AW10: @ | AX10: Разом | AY10: Банк + каса | AZ10: @ | BA10: Разом | BB10: Банк + каса | BC10: @ | BD10: Разом | BE10: Банк + каса | BF10: @ | BG10: Разом | BH10: Банк + каса | BI10: @ | BJ10: Разом | BK10: Банк + каса | BL10: @ | BM10: Разом | BN10: Банк + каса | BO10: @ | BP10: Разом | BQ10: Банк + каса | BR10: @ | BS10: Разом | BT10: Банк + каса | BU10: @ | BV10: Разом | BW10: Банк + каса | BX10: @ | BY10: Разом | BZ10: Банк + каса | CA10: @ | CB10: Разом
A11: Надходження
A12: 111 | B12: Дохід від реалізації продукції | C12: ='[5]ПП ВДГ'!C12+'[5]Корсак Л.Р.'!C12+'[5]Корсак В.І.'!C12+[5]Конякіна!C12 -> 0 | D12: ='[5]ПП ВДГ'!D12+'[5]Корсак Л.Р.'!D12+'[5]Корсак В.І.'!D12+[5]Конякіна!D12 -> 0 | E12: =SUM(C12:D12) -> 0 | F12: ='Солар Вест'!F12+Будник!F12 -> 0 | G12: ='Солар Вест'!G12+Будник!G12 -> 0 | H12: =SUM(F12:G12) -> 0 | I12: ='[5]ПП ВДГ'!I12+'[5]Корсак Л.Р.'!I12+'[5]Корсак В.І.'!I12+[5]Конякіна!I12 -> 0 | J12: ='[5]ПП ВДГ'!J12+'[5]Корсак Л.Р.'!J12+'[5]Корсак В.І.'!J12+[5]Конякіна!J12 -> 0 | K12: =SUM(I12:J12) -> 0 | L12: ='Солар Вест'!L12+Будник!L12 -> 0 | M12: ='Солар Вест'!M12+Будник!M12 -> 0 | N12: =SUM(L12:M12) -> 0 | O12: ='[5]ПП ВДГ'!O12+'[5]Корсак Л.Р.'!O12+'[5]Корсак В.І.'!O12+[5]Конякіна!O12 -> 0 | P12: ='[5]ПП ВДГ'!P12+'[5]Корсак Л.Р.'!P12+'[5]Корсак В.І.'!P12+[5]Конякіна!P12 -> 0 | Q12: =SUM(O12:P12) -> 0 | R12: ='Солар Вест'!R12+Будник!R12 -> 0 | S12: ='Солар Вест'!S12+Будник!S12 -> 0 | T12: =SUM(R12:S12) -> 0 | U12: ='[5]ПП ВДГ'!U12+'[5]Корсак Л.Р.'!U12+'[5]Корсак В.І.'!U12+[5]Конякіна!U12 -> 0 | V12: ='[5]ПП ВДГ'!V12+'[5]Корсак Л.Р.'!V12+'[5]Корсак В.І.'!V12+[5]Конякіна!V12 -> 0 | W12: =SUM(U12:V12) -> 0 | X12: ='Солар Вест'!X12+Будник!X12 -> 0 | Y12: ='Солар Вест'!Y12+Будник!Y12 -> 0 | Z12: =SUM(X12:Y12) -> 0 | AA12: ='[5]ПП ВДГ'!AA12+'[5]Корсак Л.Р.'!AA12+'[5]Корсак В.І.'!AA12+[5]Конякіна!AA12 -> 0 | AB12: ='[5]ПП ВДГ'!AB12+'[5]Корсак Л.Р.'!AB12+'[5]Корсак В.І.'!AB12+[5]Конякіна!AB12 -> 0 | AC12: =SUM(AA12:AB12) -> 0 | AD12: ='Солар Вест'!AD12+Будник!AD12 -> 0 | AE12: ='Солар Вест'!AE12+Будник!AE12 -> 0 | AF12: =SUM(AD12:AE12) -> 0 | AG12: ='[5]ПП ВДГ'!AG12+'[5]Корсак Л.Р.'!AG12+'[5]Корсак В.І.'!AG12+[5]Конякіна!AG12 -> 0 | AH12: ='[5]ПП ВДГ'!AH12+'[5]Корсак Л.Р.'!AH12+'[5]Корсак В.І.'!AH12+[5]Конякіна!AH12 -> 0 | AI12: =SUM(AG12:AH12) -> 0 | AJ12: ='Солар Вест'!AJ12+Будник!AJ12 -> 0 | AK12: ='Солар Вест'!AK12+Будник!AK12 -> 0 | AL12: =SUM(AJ12:AK12) -> 0 | AM12: ='[5]ПП ВДГ'!AM12+'[5]Корсак Л.Р.'!AM12+'[5]Корсак В.І.'!AM12+[5]Конякіна!AM12 -> 0 | AN12: ='[5]ПП ВДГ'!AN12+'[5]Корсак Л.Р.'!AN12+'[5]Корсак В.І.'!AN12+[5]Конякіна!AN12 -> 0 | AO12: =SUM(AM12:AN12) -> 0 | AP12: ='Солар Вест'!AP12+Будник!AP12 -> 0 | AQ12: ='Солар Вест'!AQ12+Будник!AQ12 -> 0 | AR12: =SUM(AP12:AQ12) -> 0 | AS12: ='[5]ПП ВДГ'!AS12+'[5]Корсак Л.Р.'!AS12+'[5]Корсак В.І.'!AS12+[5]Конякіна!AS12 -> 0 | AT12: ='[5]ПП ВДГ'!AT12+'[5]Корсак Л.Р.'!AT12+'[5]Корсак В.І.'!AT12+[5]Конякіна!AT12 -> 0 | AU12: =SUM(AS12:AT12) -> 0 | AV12: ='Солар Вест'!AV12+Будник!AV12 -> 0 | AW12: ='Солар Вест'!AW12+Будник!AW12 -> 0 | AX12: =SUM(AV12:AW12) -> 0 | AY12: ='[5]ПП ВДГ'!AY12+'[5]Корсак Л.Р.'!AY12+'[5]Корсак В.І.'!AY12+[5]Конякіна!AY12 -> 0 | AZ12: ='[5]ПП ВДГ'!AZ12+'[5]Корсак Л.Р.'!AZ12+'[5]Корсак В.І.'!AZ12+[5]Конякіна!AZ12 -> 0 | BA12: =SUM(AY12:AZ12) -> 0 | BB12: ='Солар Вест'!BB12+Будник!BB12 -> 0 | BC12: ='Солар Вест'!BC12+Будник!BC12 -> 0 | BD12: =SUM(BB12:BC12) -> 0 | BE12: ='Солар Вест'!BE12+Будник!BE12 -> 0 | BF12: ='Солар Вест'!BF12+Будник!BF12 -> 0 | BG12: =SUM(BE12:BF12) -> 0 | BH12: ='Солар Вест'!BH12+Будник!BH12 -> 0 | BI12: ='Солар Вест'!BI12+Будник!BI12 -> 0 | BJ12: =SUM(BH12:BI12) -> 0 | BK12: ='[5]ПП ВДГ'!BK12+'[5]Корсак Л.Р.'!BK12+'[5]Корсак В.І.'!BK12+[5]Конякіна!BK12 -> 0 | BL12: ='[5]ПП ВДГ'!BL12+'[5]Корсак Л.Р.'!BL12+'[5]Корсак В.І.'!BL12+[5]Конякіна!BL12 -> 0 | BM12: =SUM(BK12:BL12) -> 0 | BN12: ='Солар Вест'!BN12+Будник!BN12 -> 0 | BO12: ='Солар Вест'!BO12+Будник!BO12 -> 0 | BP12: =SUM(BN12:BO12) -> 0 | BQ12: ='[5]ПП ВДГ'!BQ12+'[5]Корсак Л.Р.'!BQ12+'[5]Корсак В.І.'!BQ12+[5]Конякіна!BQ12 -> 0 | BR12: ='[5]ПП ВДГ'!BR12+'[5]Корсак Л.Р.'!BR12+'[5]Корсак В.І.'!BR12+[5]Конякіна!BR12 -> 0 | BS12: =SUM(BQ12:BR12) -> 0 | BT12: ='Солар Вест'!BT12+Будник!BT12 -> 0 | BU12: ='Солар Вест'!BU12+Будник!BU12 -> 0 | BV12: =SUM(BT12:BU12) -> 0 | BW12: =+C12+I12+O12+AA12+AG12+U12+AM12+AS12+AY12+BE12+BK12+BQ12 -> 0 | BX12: =+D12+J12+P12+AB12+AH12+V12+AN12+AT12+AZ12+BF12+BL12+BR12 -> 0 | BY12: =SUM(BW12:BX12) -> 0 | BZ12: =+F12+L12+R12+AD12+AJ12+X12+AP12+AV12+BB12+BH12+BN12+BT12 -> 0 | CA12: =+G12+M12+S12+AE12+AK12+Y12+AQ12+AW12+BC12+BI12+BO12+BU12 -> 0 | CB12: =SUM(BZ12:CA12) -> 0
B13: в т.ч. внутрішньогрупові доходи від реалізації продукції | C13: ='[5]ПП ВДГ'!C13+'[5]Корсак Л.Р.'!C13+'[5]Корсак В.І.'!C13+[5]Конякіна!C13 -> 0 | D13: ='[5]ПП ВДГ'!D13+'[5]Корсак Л.Р.'!D13+'[5]Корсак В.І.'!D13+[5]Конякіна!D13 -> 0 | E13: =SUM(C13:D13) -> 0 | F13: ='Солар Вест'!F13+Будник!F13 -> 0 | G13: ='Солар Вест'!G13+Будник!G13 -> 0 | H13: =SUM(F13:G13) -> 0 | I13: ='[5]ПП ВДГ'!I13+'[5]Корсак Л.Р.'!I13+'[5]Корсак В.І.'!I13+[5]Конякіна!I13 -> 0 | J13: ='[5]ПП ВДГ'!J13+'[5]Корсак Л.Р.'!J13+'[5]Корсак В.І.'!J13+[5]Конякіна!J13 -> 0 | K13: =SUM(I13:J13) -> 0 | L13: ='Солар Вест'!L13+Будник!L13 -> 0 | M13: ='Солар Вест'!M13+Будник!M13 -> 0 | N13: =SUM(L13:M13) -> 0 | O13: ='[5]ПП ВДГ'!O13+'[5]Корсак Л.Р.'!O13+'[5]Корсак В.І.'!O13+[5]Конякіна!O13 -> 0 | P13: ='[5]ПП ВДГ'!P13+'[5]Корсак Л.Р.'!P13+'[5]Корсак В.І.'!P13+[5]Конякіна!P13 -> 0 | Q13: =SUM(O13:P13) -> 0 | R13: ='Солар Вест'!R13+Будник!R13 -> 0 | S13: ='Солар Вест'!S13+Будник!S13 -> 0 | T13: =SUM(R13:S13) -> 0 | U13: ='[5]ПП ВДГ'!U13+'[5]Корсак Л.Р.'!U13+'[5]Корсак В.І.'!U13+[5]Конякіна!U13 -> 0 | V13: ='[5]ПП ВДГ'!V13+'[5]Корсак Л.Р.'!V13+'[5]Корсак В.І.'!V13+[5]Конякіна!V13 -> 0 | W13: =SUM(U13:V13) -> 0 | X13: ='Солар Вест'!X13+Будник!X13 -> 0 | Y13: ='Солар Вест'!Y13+Будник!Y13 -> 0 | Z13: =SUM(X13:Y13) -> 0 | AA13: ='[5]ПП ВДГ'!AA13+'[5]Корсак Л.Р.'!AA13+'[5]Корсак В.І.'!AA13+[5]Конякіна!AA13 -> 0 | AB13: ='[5]ПП ВДГ'!AB13+'[5]Корсак Л.Р.'!AB13+'[5]Корсак В.І.'!AB13+[5]Конякіна!AB13 -> 0 | AC13: =SUM(AA13:AB13) -> 0 | AD13: ='Солар Вест'!AD13+Будник!AD13 -> 0 | AE13: ='Солар Вест'!AE13+Будник!AE13 -> 0 | AF13: =SUM(AD13:AE13) -> 0 | AG13: ='[5]ПП ВДГ'!AG13+'[5]Корсак Л.Р.'!AG13+'[5]Корсак В.І.'!AG13+[5]Конякіна!AG13 -> 0 | AH13: ='[5]ПП ВДГ'!AH13+'[5]Корсак Л.Р.'!AH13+'[5]Корсак В.І.'!AH13+[5]Конякіна!AH13 -> 0 | AI13: =SUM(AG13:AH13) -> 0 | AJ13: ='Солар Вест'!AJ13+Будник!AJ13 -> 0 | AK13: ='Солар Вест'!AK13+Будник!AK13 -> 0 | AL13: =SUM(AJ13:AK13) -> 0 | AM13: ='[5]ПП ВДГ'!AM13+'[5]Корсак Л.Р.'!AM13+'[5]Корсак В.І.'!AM13+[5]Конякіна!AM13 -> 0 | AN13: ='[5]ПП ВДГ'!AN13+'[5]Корсак Л.Р.'!AN13+'[5]Корсак В.І.'!AN13+[5]Конякіна!AN13 -> 0 | AO13: =SUM(AM13:AN13) -> 0 | AP13: ='Солар Вест'!AP13+Будник!AP13 -> 0 | AQ13: ='Солар Вест'!AQ13+Будник!AQ13 -> 0 | AR13: =SUM(AP13:AQ13) -> 0 | AS13: ='[5]ПП ВДГ'!AS13+'[5]Корсак Л.Р.'!AS13+'[5]Корсак В.І.'!AS13+[5]Конякіна!AS13 -> 0 | AT13: ='[5]ПП ВДГ'!AT13+'[5]Корсак Л.Р.'!AT13+'[5]Корсак В.І.'!AT13+[5]Конякіна!AT13 -> 0 | AU13: =SUM(AS13:AT13) -> 0 | AV13: ='Солар Вест'!AV13+Будник!AV13 -> 0 | AW13: ='Солар Вест'!AW13+Будник!AW13 -> 0 | AX13: =SUM(AV13:AW13) -> 0 | AY13: ='[5]ПП ВДГ'!AY13+'[5]Корсак Л.Р.'!AY13+'[5]Корсак В.І.'!AY13+[5]Конякіна!AY13 -> 0 | AZ13: ='[5]ПП ВДГ'!AZ13+'[5]Корсак Л.Р.'!AZ13+'[5]Корсак В.І.'!AZ13+[5]Конякіна!AZ13 -> 0 | BA13: =SUM(AY13:AZ13) -> 0 | BB13: ='Солар Вест'!BB13+Будник!BB13 -> 0 | BC13: ='Солар Вест'!BC13+Будник!BC13 -> 0 | BD13: =SUM(BB13:BC13) -> 0 | BE13: ='Солар Вест'!BE13+Будник!BE13 -> 0 | BF13: ='Солар Вест'!BF13+Будник!BF13 -> 0 | BG13: =SUM(BE13:BF13) -> 0 | BH13: ='Солар Вест'!BH13+Будник!BH13 -> 0 | BI13: ='Солар Вест'!BI13+Будник!BI13 -> 0 | BJ13: =SUM(BH13:BI13) -> 0 | BK13: ='[5]ПП ВДГ'!BK13+'[5]Корсак Л.Р.'!BK13+'[5]Корсак В.І.'!BK13+[5]Конякіна!BK13 -> 0 | BL13: ='[5]ПП ВДГ'!BL13+'[5]Корсак Л.Р.'!BL13+'[5]Корсак В.І.'!BL13+[5]Конякіна!BL13 -> 0 | BM13: =SUM(BK13:BL13) -> 0 | BN13: ='Солар Вест'!BN13+Будник!BN13 -> 0 | BO13: ='Солар Вест'!BO13+Будник!BO13 -> 0 | BP13: =SUM(BN13:BO13) -> 0 | BQ13: ='[5]ПП ВДГ'!BQ13+'[5]Корсак Л.Р.'!BQ13+'[5]Корсак В.І.'!BQ13+[5]Конякіна!BQ13 -> 0 | BR13: ='[5]ПП ВДГ'!BR13+'[5]Корсак Л.Р.'!BR13+'[5]Корсак В.І.'!BR13+[5]Конякіна!BR13 -> 0 | BS13: =SUM(BQ13:BR13) -> 0 | BT13: ='Солар Вест'!BT13+Будник!BT13 -> 0 | BU13: ='Солар Вест'!BU13+Будник!BU13 -> 0 | BV13: =SUM(BT13:BU13) -> 0 | BW13: =+C13+I13+O13+AA13+AG13+U13+AM13+AS13+AY13+BE13+BK13+BQ13 -> 0 | BX13: =+D13+J13+P13+AB13+AH13+V13+AN13+AT13+AZ13+BF13+BL13+BR13 -> 0 | BY13: =SUM(BW13:BX13) -> 0 | BZ13: =+F13+L13+R13+AD13+AJ13+X13+AP13+AV13+BB13+BH13+BN13+BT13 -> 0 | CA13: =+G13+M13+S13+AE13+AK13+Y13+AQ13+AW13+BC13+BI13+BO13+BU13 -> 0 | CB13: =SUM(BZ13:CA13) -> 0
A14: 112 | B14: Дохід від реалізації товарів | C14: ='[5]ПП ВДГ'!C14+'[5]Корсак Л.Р.'!C14+'[5]Корсак В.І.'!C14+[5]Конякіна!C14 -> 0 | D14: ='[5]ПП ВДГ'!D14+'[5]Корсак Л.Р.'!D14+'[5]Корсак В.І.'!D14+[5]Конякіна!D14 -> 0 | E14: =SUM(C14:D14) -> 0 | F14: ='Солар Вест'!F14+Будник!F14 -> 125791.1 | G14: ='Солар Вест'!G14+Будник!G14 -> 2810 | H14: =SUM(F14:G14) -> 128601.1 | I14: ='[5]ПП ВДГ'!I14+'[5]Корсак Л.Р.'!I14+'[5]Корсак В.І.'!I14+[5]Конякіна!I14 -> 0 | J14: ='[5]ПП ВДГ'!J14+'[5]Корсак Л.Р.'!J14+'[5]Корсак В.І.'!J14+[5]Конякіна!J14 -> 0 | K14: =SUM(I14:J14) -> 0 | L14: ='Солар Вест'!L14+Будник!L14 -> 157034.6 | M14: ='Солар Вест'!M14+Будник!M14 -> 3300 | N14: =SUM(L14:M14) -> 160334.6 | O14: ='[5]ПП ВДГ'!O14+'[5]Корсак Л.Р.'!O14+'[5]Корсак В.І.'!O14+[5]Конякіна!O14 -> 0 | P14: ='[5]ПП ВДГ'!P14+'[5]Корсак Л.Р.'!P14+'[5]Корсак В.І.'!P14+[5]Конякіна!P14 -> 0 | Q14: =SUM(O14:P14) -> 0 | R14: ='Солар Вест'!R14+Будник!R14 -> 2086265.6 | S14: ='Солар Вест'!S14+Будник!S14 -> 79400 | T14: =SUM(R14:S14) -> 2165665.5 | U14: ='[5]ПП ВДГ'!U14+'[5]Корсак Л.Р.'!U14+'[5]Корсак В.І.'!U14+[5]Конякіна!U14 -> 0 | V14: ='[5]ПП ВДГ'!V14+'[5]Корсак Л.Р.'!V14+'[5]Корсак В.І.'!V14+[5]Конякіна!V14 -> 0 | W14: =SUM(U14:V14) -> 0 | X14: ='Солар Вест'!X14+Будник!X14 -> 2535318.4 | Y14: ='Солар Вест'!Y14+Будник!Y14 -> 135358 | Z14: =SUM(X14:Y14) -> 2670676.4 | AA14: ='[5]ПП ВДГ'!AA14+'[5]Корсак Л.Р.'!AA14+'[5]Корсак В.І.'!AA14+[5]Конякіна!AA14 -> 0 | AB14: ='[5]ПП ВДГ'!AB14+'[5]Корсак Л.Р.'!AB14+'[5]Корсак В.І.'!AB14+[5]Конякіна!AB14 -> 0 | AC14: =SUM(AA14:AB14) -> 0 | AD14: ='Солар Вест'!AD14+Будник!AD14 -> 1074727.5 | AE14: ='Солар Вест'!AE14+Будник!AE14 -> 29910 | AF14: =SUM(AD14:AE14) -> 1104637.5 | AG14: ='[5]ПП ВДГ'!AG14+'[5]Корсак Л.Р.'!AG14+'[5]Корсак В.І.'!AG14+[5]Конякіна!AG14 -> 0 | AH14: ='[5]ПП ВДГ'!AH14+'[5]Корсак Л.Р.'!AH14+'[5]Корсак В.І.'!AH14+[5]Конякіна!AH14 -> 0 | AI14: =SUM(AG14:AH14) -> 0 | AJ14: ='Солар Вест'!AJ14+Будник!AJ14 -> 4236033.3 | AK14: ='Солар Вест'!AK14+Будник!AK14 -> 19150 | AL14: =SUM(AJ14:AK14) -> 4255183.3 | AM14: ='[5]ПП ВДГ'!AM14+'[5]Корсак Л.Р.'!AM14+'[5]Корсак В.І.'!AM14+[5]Конякіна!AM14 -> 0 | AN14: ='[5]ПП ВДГ'!AN14+'[5]Корсак Л.Р.'!AN14+'[5]Корсак В.І.'!AN14+[5]Конякіна!AN14 -> 0 | AO14: =SUM(AM14:AN14) -> 0 | AP14: ='Солар Вест'!AP14+Будник!AP14 -> 948545.59 | AQ14: ='Солар Вест'!AQ14+Будник!AQ14 -> 9375 | AR14: =SUM(AP14:AQ14) -> 957920.59 | AS14: ='[5]ПП ВДГ'!AS14+'[5]Корсак Л.Р.'!AS14+'[5]Корсак В.І.'!AS14+[5]Конякіна!AS14 -> 0 | AT14: ='[5]ПП ВДГ'!AT14+'[5]Корсак Л.Р.'!AT14+'[5]Корсак В.І.'!AT14+[5]Конякіна!AT14 -> 0 | AU14: =SUM(AS14:AT14) -> 0 | AV14: ='Солар Вест'!AV14+Будник!AV14 -> 264408.5 | AW14: ='Солар Вест'!AW14+Будник!AW14 -> 17302 | AX14: =SUM(AV14:AW14) -> 281710.5 | AY14: ='[5]ПП ВДГ'!AY14+'[5]Корсак Л.Р.'!AY14+'[5]Корсак В.І.'!AY14+[5]Конякіна!AY14 -> 0 | AZ14: ='[5]ПП ВДГ'!AZ14+'[5]Корсак Л.Р.'!AZ14+'[5]Корсак В.І.'!AZ14+[5]Конякіна!AZ14 -> 0 | BA14: =SUM(AY14:AZ14) -> 0 | BB14: ='Солар Вест'!BB14+Будник!BB14 -> 1162866.5 | BC14: ='Солар Вест'!BC14+Будник!BC14 -> 1920 | BD14: =SUM(BB14:BC14) -> 1164786.5 | BE14: ='Солар Вест'!BE14+Будник!BE14 -> 583567.42 | BF14: ='Солар Вест'!BF14+Будник!BF14 -> 140808 | BG14: =SUM(BE14:BF14) -> 724375.42 | BH14: ='Солар Вест'!BH14+Будник!BH14 -> 0 | BI14: ='Солар Вест'!BI14+Будник!BI14 -> 0 | BJ14: =SUM(BH14:BI14) -> 0 | BK14: ='[5]ПП ВДГ'!BK14+'[5]Корсак Л.Р.'!BK14+'[5]Корсак В.І.'!BK14+[5]Конякіна!BK14 -> 0 | BL14: ='[5]ПП ВДГ'!BL14+'[5]Корсак Л.Р.'!BL14+'[5]Корсак В.І.'!BL14+[5]Конякіна!BL14 -> 0 | BM14: =SUM(BK14:BL14) -> 0 | BN14: ='Солар Вест'!BN14+Будник!BN14 -> 0 | BO14: ='Солар Вест'!BO14+Будник!BO14 -> 0 | BP14: =SUM(BN14:BO14) -> 0 | BQ14: ='[5]ПП ВДГ'!BQ14+'[5]Корсак Л.Р.'!BQ14+'[5]Корсак В.І.'!BQ14+[5]Конякіна!BQ14 -> 0 | BR14: ='[5]ПП ВДГ'!BR14+'[5]Корсак Л.Р.'!BR14+'[5]Корсак В.І.'!BR14+[5]Конякіна!BR14 -> 0 | BS14: =SUM(BQ14:BR14) -> 0 | BT14: ='Солар Вест'!BT14+Будник!BT14 -> 0 | BU14: ='Солар Вест'!BU14+Будник!BU14 -> 0 | BV14: =SUM(BT14:BU14) -> 0 | BW14: =+C14+I14+O14+AA14+AG14+U14+AM14+AS14+AY14+BE14+BK14+BQ14 -> 583567.42 | BX14: =+D14+J14+P14+AB14+AH14+V14+AN14+AT14+AZ14+BF14+BL14+BR14 -> 140808 | BY14: =SUM(BW14:BX14) -> 724375.42 | BZ14: =+F14+L14+R14+AD14+AJ14+X14+AP14+AV14+BB14+BH14+BN14+BT14 -> 12590991 | CA14: =+G14+M14+S14+AE14+AK14+Y14+AQ14+AW14+BC14+BI14+BO14+BU14 -> 298525 | CB14: =SUM(BZ14:CA14) -> 12889516
B15: в т.ч. внутрішньогрупові доходи від реалізації товарів | C15: ='[5]ПП ВДГ'!C15+'[5]Корсак Л.Р.'!C15+'[5]Корсак В.І.'!C15+[5]Конякіна!C15 -> 0 | D15: ='[5]ПП ВДГ'!D15+'[5]Корсак Л.Р.'!D15+'[5]Корсак В.І.'!D15+[5]Конякіна!D15 -> 0 | E15: =SUM(C15:D15) -> 0 | F15: ='Солар Вест'!F15+Будник!F15 -> 0 | G15: ='Солар Вест'!G15+Будник!G15 -> 0 | H15: =SUM(F15:G15) -> 0 | I15: ='[5]ПП ВДГ'!I15+'[5]Корсак Л.Р.'!I15+'[5]Корсак В.І.'!I15+[5]Конякіна!I15 -> 0 | J15: ='[5]ПП ВДГ'!J15+'[5]Корсак Л.Р.'!J15+'[5]Корсак В.І.'!J15+[5]Конякіна!J15 -> 0 | K15: =SUM(I15:J15) -> 0 | L15: ='Солар Вест'!L15+Будник!L15 -> 0 | M15: ='Солар Вест'!M15+Будник!M15 -> 0 | N15: =SUM(L15:M15) -> 0 | O15: ='[5]ПП ВДГ'!O15+'[5]Корсак Л.Р.'!O15+'[5]Корсак В.І.'!O15+[5]Конякіна!O15 -> 0 | P15: ='[5]ПП ВДГ'!P15+'[5]Корсак Л.Р.'!P15+'[5]Корсак В.І.'!P15+[5]Конякіна!P15 -> 0 | Q15: =SUM(O15:P15) -> 0 | R15: ='Солар Вест'!R15+Будник!R15 -> 0 | S15: ='Солар Вест'!S15+Будник!S15 -> 0 | T15: =SUM(R15:S15) -> 0 | U15: ='[5]ПП ВДГ'!U15+'[5]Корсак Л.Р.'!U15+'[5]Корсак В.І.'!U15+[5]Конякіна!U15 -> 0 | V15: ='[5]ПП ВДГ'!V15+'[5]Корсак Л.Р.'!V15+'[5]Корсак В.І.'!V15+[5]Конякіна!V15 -> 0 | W15: =SUM(U15:V15) -> 0 | X15: ='Солар Вест'!X15+Будник!X15 -> 0 | Y15: ='Солар Вест'!Y15+Будник!Y15 -> 0 | Z15: =SUM(X15:Y15) -> 0 | AA15: ='[5]ПП ВДГ'!AA15+'[5]Корсак Л.Р.'!AA15+'[5]Корсак В.І.'!AA15+[5]Конякіна!AA15 -> 0 | AB15: ='[5]ПП ВДГ'!AB15+'[5]Корсак Л.Р.'!AB15+'[5]Корсак В.І.'!AB15+[5]Конякіна!AB15 -> 0 | AC15: =SUM(AA15:AB15) -> 0 | AD15: ='Солар Вест'!AD15+Будник!AD15 -> 0 | AE15: ='Солар Вест'!AE15+Будник!AE15 -> 0 | AF15: =SUM(AD15:AE15) -> 0 | AG15: ='[5]ПП ВДГ'!AG15+'[5]Корсак Л.Р.'!AG15+'[5]Корсак В.І.'!AG15+[5]Конякіна!AG15 -> 0 | AH15: ='[5]ПП ВДГ'!AH15+'[5]Корсак Л.Р.'!AH15+'[5]Корсак В.І.'!AH15+[5]Конякіна!AH15 -> 0 | AI15: =SUM(AG15:AH15) -> 0 | AJ15: ='Солар Вест'!AJ15+Будник!AJ15 -> 0 | AK15: ='Солар Вест'!AK15+Будник!AK15 -> 0 | AL15: =SUM(AJ15:AK15) -> 0 | AM15: ='[5]ПП ВДГ'!AM15+'[5]Корсак Л.Р.'!AM15+'[5]Корсак В.І.'!AM15+[5]Конякіна!AM15 -> 0 | AN15: ='[5]ПП ВДГ'!AN15+'[5]Корсак Л.Р.'!AN15+'[5]Корсак В.І.'!AN15+[5]Конякіна!AN15 -> 0 | AO15: =SUM(AM15:AN15) -> 0 | AP15: ='Солар Вест'!AP15+Будник!AP15 -> 0 | AQ15: ='Солар Вест'!AQ15+Будник!AQ15 -> 0 | AR15: =SUM(AP15:AQ15) -> 0 | AS15: ='[5]ПП ВДГ'!AS15+'[5]Корсак Л.Р.'!AS15+'[5]Корсак В.І.'!AS15+[5]Конякіна!AS15 -> 0 | AT15: ='[5]ПП ВДГ'!AT15+'[5]Корсак Л.Р.'!AT15+'[5]Корсак В.І.'!AT15+[5]Конякіна!AT15 -> 0 | AU15: =SUM(AS15:AT15) -> 0 | AV15: ='Солар Вест'!AV15+Будник!AV15 -> 0 | AW15: ='Солар Вест'!AW15+Будник!AW15 -> 0 | AX15: =SUM(AV15:AW15) -> 0 | AY15: ='[5]ПП ВДГ'!AY15+'[5]Корсак Л.Р.'!AY15+'[5]Корсак В.І.'!AY15+[5]Конякіна!AY15 -> 0 | AZ15: ='[5]ПП ВДГ'!AZ15+'[5]Корсак Л.Р.'!AZ15+'[5]Корсак В.І.'!AZ15+[5]Конякіна!AZ15 -> 0 | BA15: =SUM(AY15:AZ15) -> 0 | BB15: ='Солар Вест'!BB15+Будник!BB15 -> 0 | BC15: ='Солар Вест'!BC15+Будник!BC15 -> 0 | BD15: =SUM(BB15:BC15) -> 0 | BE15: ='Солар Вест'!BE15+Будник!BE15 -> 0 | BF15: ='Солар Вест'!BF15+Будник!BF15 -> 0 | BG15: =SUM(BE15:BF15) -> 0 | BH15: ='Солар Вест'!BH15+Будник!BH15 -> 0 | BI15: ='Солар Вест'!BI15+Будник!BI15 -> 0 | BJ15: =SUM(BH15:BI15) -> 0 | BK15: ='[5]ПП ВДГ'!BK15+'[5]Корсак Л.Р.'!BK15+'[5]Корсак В.І.'!BK15+[5]Конякіна!BK15 -> 0 | BL15: ='[5]ПП ВДГ'!BL15+'[5]Корсак Л.Р.'!BL15+'[5]Корсак В.І.'!BL15+[5]Конякіна!BL15 -> 0 | BM15: =SUM(BK15:BL15) -> 0 | BN15: ='Солар Вест'!BN15+Будник!BN15 -> 0 | BO15: ='Солар Вест'!BO15+Будник!BO15 -> 0 | BP15: =SUM(BN15:BO15) -> 0 | BQ15: ='[5]ПП ВДГ'!BQ15+'[5]Корсак Л.Р.'!BQ15+'[5]Корсак В.І.'!BQ15+[5]Конякіна!BQ15 -> 0 | BR15: ='[5]ПП ВДГ'!BR15+'[5]Корсак Л.Р.'!BR15+'[5]Корсак В.І.'!BR15+[5]Конякіна!BR15 -> 0 | BS15: =SUM(BQ15:BR15) -> 0 | BT15: ='Солар Вест'!BT15+Будник!BT15 -> 0 | BU15: ='Солар Вест'!BU15+Будник!BU15 -> 0 | BV15: =SUM(BT15:BU15) -> 0 | BW15: =+C15+I15+O15+AA15+AG15+U15+AM15+AS15+AY15+BE15+BK15+BQ15 -> 0 | BX15: =+D15+J15+P15+AB15+AH15+V15+AN15+AT15+AZ15+BF15+BL15+BR15 -> 0 | BY15: =SUM(BW15:BX15) -> 0 | BZ15: =+F15+L15+R15+AD15+AJ15+X15+AP15+AV15+BB15+BH15+BN15+BT15 -> 0 | CA15: =+G15+M15+S15+AE15+AK15+Y15+AQ15+AW15+BC15+BI15+BO15+BU15 -> 0 | CB15: =SUM(BZ15:CA15) -> 0
A16: 113 | B16: Дохід від реалізації послуг | C16: ='[5]ПП ВДГ'!C16+'[5]Корсак Л.Р.'!C16+'[5]Корсак В.І.'!C16+[5]Конякіна!C16 -> 0 | D16: ='[5]ПП ВДГ'!D16+'[5]Корсак Л.Р.'!D16+'[5]Корсак В.І.'!D16+[5]Конякіна!D16 -> 0 | E16: =SUM(C16:D16) -> 0 | F16: ='Солар Вест'!F16+Будник!F16 -> 0 | G16: ='Солар Вест'!G16+Будник!G16 -> 229400 | H16: =SUM(F16:G16) -> 229400 | I16: ='[5]ПП ВДГ'!I16+'[5]Корсак Л.Р.'!I16+'[5]Корсак В.І.'!I16+[5]Конякіна!I16 -> 0 | J16: ='[5]ПП ВДГ'!J16+'[5]Корсак Л.Р.'!J16+'[5]Корсак В.І.'!J16+[5]Конякіна!J16 -> 0 | K16: =SUM(I16:J16) -> 0 | L16: ='Солар Вест'!L16+Будник!L16 -> 0 | M16: ='Солар Вест'!M16+Будник!M16 -> 169100 | N16: =SUM(L16:M16) -> 169100 | O16: ='[5]ПП ВДГ'!O16+'[5]Корсак Л.Р.'!O16+'[5]Корсак В.І.'!O16+[5]Конякіна!O16 -> 0 | P16: ='[5]ПП ВДГ'!P16+'[5]Корсак Л.Р.'!P16+'[5]Корсак В.І.'!P16+[5]Конякіна!P16 -> 0 | Q16: =SUM(O16:P16) -> 0 | R16: ='Солар Вест'!R16+Будник!R16 -> 0 | S16: ='Солар Вест'!S16+Будник!S16 -> 188610 | T16: =SUM(R16:S16) -> 188610 | U16: ='[5]ПП ВДГ'!U16+'[5]Корсак Л.Р.'!U16+'[5]Корсак В.І.'!U16+[5]Конякіна!U16 -> 0 | V16: ='[5]ПП ВДГ'!V16+'[5]Корсак Л.Р.'!V16+'[5]Корсак В.І.'!V16+[5]Конякіна!V16 -> 0 | W16: =SUM(U16:V16) -> 0 | X16: ='Солар Вест'!X16+Будник!X16 -> 0 | Y16: ='Солар Вест'!Y16+Будник!Y16 -> 410000 | Z16: =SUM(X16:Y16) -> 410000 | AA16: ='[5]ПП ВДГ'!AA16+'[5]Корсак Л.Р.'!AA16+'[5]Корсак В.І.'!AA16+[5]Конякіна!AA16 -> 0 | AB16: ='[5]ПП ВДГ'!AB16+'[5]Корсак Л.Р.'!AB16+'[5]Корсак В.І.'!AB16+[5]Конякіна!AB16 -> 0 | AC16: =SUM(AA16:AB16) -> 0 | AD16: ='Солар Вест'!AD16+Будник!AD16 -> 0 | AE16: ='Солар Вест'!AE16+Будник!AE16 -> 687620 | AF16: =SUM(AD16:AE16) -> 687620 | AG16: ='[5]ПП ВДГ'!AG16+'[5]Корсак Л.Р.'!AG16+'[5]Корсак В.І.'!AG16+[5]Конякіна!AG16 -> 0 | AH16: ='[5]ПП ВДГ'!AH16+'[5]Корсак Л.Р.'!AH16+'[5]Корсак В.І.'!AH16+[5]Конякіна!AH16 -> 0 | AI16: =SUM(AG16:AH16) -> 0 | AJ16: ='Солар Вест'!AJ16+Будник!AJ16 -> 62000 | AK16: ='Солар Вест'!AK16+Будник!AK16 -> 643228 | AL16: =SUM(AJ16:AK16) -> 705228 | AM16: ='[5]ПП ВДГ'!AM16+'[5]Корсак Л.Р.'!AM16+'[5]Корсак В.І.'!AM16+[5]Конякіна!AM16 -> 0 | AN16: ='[5]ПП ВДГ'!AN16+'[5]Корсак Л.Р.'!AN16+'[5]Корсак В.І.'!AN16+[5]Конякіна!AN16 -> 0 | AO16: =SUM(AM16:AN16) -> 0 | AP16: ='Солар Вест'!AP16+Будник!AP16 -> 56600 | AQ16: ='Солар Вест'!AQ16+Будник!AQ16 -> 222000 | AR16: =SUM(AP16:AQ16) -> 278600 | AS16: ='[5]ПП ВДГ'!AS16+'[5]Корсак Л.Р.'!AS16+'[5]Корсак В.І.'!AS16+[5]Конякіна!AS16 -> 0 | AT16: ='[5]ПП ВДГ'!AT16+'[5]Корсак Л.Р.'!AT16+'[5]Корсак В.І.'!AT16+[5]Конякіна!AT16 -> 0 | AU16: =SUM(AS16:AT16) -> 0 | AV16: ='Солар Вест'!AV16+Будник!AV16 -> 528700 | AW16: ='Солар Вест'!AW16+Будник!AW16 -> 282290 | AX16: =SUM(AV16:AW16) -> 810990 | AY16: ='[5]ПП ВДГ'!AY16+'[5]Корсак Л.Р.'!AY16+'[5]Корсак В.І.'!AY16+[5]Конякіна!AY16 -> 0 | AZ16: ='[5]ПП ВДГ'!AZ16+'[5]Корсак Л.Р.'!AZ16+'[5]Корсак В.І.'!AZ16+[5]Конякіна!AZ16 -> 0 | BA16: =SUM(AY16:AZ16) -> 0 | BB16: ='Солар Вест'!BB16+Будник!BB16 -> 216700 | BC16: ='Солар Вест'!BC16+Будник!BC16 -> 283290 | BD16: =SUM(BB16:BC16) -> 499990 | BE16: ='Солар Вест'!BE16+Будник!BE16 -> 0 | BF16: ='Солар Вест'!BF16+Будник!BF16 -> 268985 | BG16: =SUM(BE16:BF16) -> 268985 | BH16: ='Солар Вест'!BH16+Будник!BH16 -> 0 | BI16: ='Солар Вест'!BI16+Будник!BI16 -> 0 | BJ16: =SUM(BH16:BI16) -> 0 | BK16: ='[5]ПП ВДГ'!BK16+'[5]Корсак Л.Р.'!BK16+'[5]Корсак В.І.'!BK16+[5]Конякіна!BK16 -> 0 | BL16: ='[5]ПП ВДГ'!BL16+'[5]Корсак Л.Р.'!BL16+'[5]Корсак В.І.'!BL16+[5]Конякіна!BL16 -> 0 | BM16: =SUM(BK16:BL16) -> 0 | BN16: ='Солар Вест'!BN16+Будник!BN16 -> 0 | BO16: ='Солар Вест'!BO16+Будник!BO16 -> 0 | BP16: =SUM(BN16:BO16) -> 0 | BQ16: ='[5]ПП ВДГ'!BQ16+'[5]Корсак Л.Р.'!BQ16+'[5]Корсак В.І.'!BQ16+[5]Конякіна!BQ16 -> 0 | BR16: ='[5]ПП ВДГ'!BR16+'[5]Корсак Л.Р.'!BR16+'[5]Корсак В.І.'!BR16+[5]Конякіна!BR16 -> 0 | BS16: =SUM(BQ16:BR16) -> 0 | BT16: ='Солар Вест'!BT16+Будник!BT16 -> 0 | BU16: ='Солар Вест'!BU16+Будник!BU16 -> 0 | BV16: =SUM(BT16:BU16) -> 0 | BW16: =+C16+I16+O16+AA16+AG16+U16+AM16+AS16+AY16+BE16+BK16+BQ16 -> 0 | BX16: =+D16+J16+P16+AB16+AH16+V16+AN16+AT16+AZ16+BF16+BL16+BR16 -> 268985 | BY16: =SUM(BW16:BX16) -> 268985 | BZ16: =+F16+L16+R16+AD16+AJ16+X16+AP16+AV16+BB16+BH16+BN16+BT16 -> 864000 | CA16: =+G16+M16+S16+AE16+AK16+Y16+AQ16+AW16+BC16+BI16+BO16+BU16 -> 3115538 | CB16: =SUM(BZ16:CA16) -> 3979538
B17: в т.ч. внутрішньогрупові доходи від реалізації послуг | C17: ='[5]ПП ВДГ'!C17+'[5]Корсак Л.Р.'!C17+'[5]Корсак В.І.'!C17+[5]Конякіна!C17 -> 0 | D17: ='[5]ПП ВДГ'!D17+'[5]Корсак Л.Р.'!D17+'[5]Корсак В.І.'!D17+[5]Конякіна!D17 -> 0 | E17: =SUM(C17:D17) -> 0 | F17: ='Солар Вест'!F17+Будник!F17 -> 0 | G17: ='Солар Вест'!G17+Будник!G17 -> 0 | H17: =SUM(F17:G17) -> 0 | I17: ='[5]ПП ВДГ'!I17+'[5]Корсак Л.Р.'!I17+'[5]Корсак В.І.'!I17+[5]Конякіна!I17 -> 0 | J17: ='[5]ПП ВДГ'!J17+'[5]Корсак Л.Р.'!J17+'[5]Корсак В.І.'!J17+[5]Конякіна!J17 -> 0 | K17: =SUM(I17:J17) -> 0 | L17: ='Солар Вест'!L17+Будник!L17 -> 0 | M17: ='Солар Вест'!M17+Будник!M17 -> 0 | N17: =SUM(L17:M17) -> 0 | O17: ='[5]ПП ВДГ'!O17+'[5]Корсак Л.Р.'!O17+'[5]Корсак В.І.'!O17+[5]Конякіна!O17 -> 0 | P17: ='[5]ПП ВДГ'!P17+'[5]Корсак Л.Р.'!P17+'[5]Корсак В.І.'!P17+[5]Конякіна!P17 -> 0 | Q17: =SUM(O17:P17) -> 0 | R17: ='Солар Вест'!R17+Будник!R17 -> 0 | S17: ='Солар Вест'!S17+Будник!S17 -> 0 | T17: =SUM(R17:S17) -> 0 | U17: ='[5]ПП ВДГ'!U17+'[5]Корсак Л.Р.'!U17+'[5]Корсак В.І.'!U17+[5]Конякіна!U17 -> 0 | V17: ='[5]ПП ВДГ'!V17+'[5]Корсак Л.Р.'!V17+'[5]Корсак В.І.'!V17+[5]Конякіна!V17 -> 0 | W17: =SUM(U17:V17) -> 0 | X17: ='Солар Вест'!X17+Будник!X17 -> 0 | Y17: ='Солар Вест'!Y17+Будник!Y17 -> 0 | Z17: =SUM(X17:Y17) -> 0 | AA17: ='[5]ПП ВДГ'!AA17+'[5]Корсак Л.Р.'!AA17+'[5]Корсак В.І.'!AA17+[5]Конякіна!AA17 -> 0 | AB17: ='[5]ПП ВДГ'!AB17+'[5]Корсак Л.Р.'!AB17+'[5]Корсак В.І.'!AB17+[5]Конякіна!AB17 -> 0 | AC17: =SUM(AA17:AB17) -> 0 | AD17: ='Солар Вест'!AD17+Будник!AD17 -> 0 | AE17: ='Солар Вест'!AE17+Будник!AE17 -> 0 | AF17: =SUM(AD17:AE17) -> 0 | AG17: ='[5]ПП ВДГ'!AG17+'[5]Корсак Л.Р.'!AG17+'[5]Корсак В.І.'!AG17+[5]Конякіна!AG17 -> 0 | AH17: ='[5]ПП ВДГ'!AH17+'[5]Корсак Л.Р.'!AH17+'[5]Корсак В.І.'!AH17+[5]Конякіна!AH17 -> 0 | AI17: =SUM(AG17:AH17) -> 0 | AJ17: ='Солар Вест'!AJ17+Будник!AJ17 -> 0 | AK17: ='Солар Вест'!AK17+Будник!AK17 -> 0 | AL17: =SUM(AJ17:AK17) -> 0 | AM17: ='[5]ПП ВДГ'!AM17+'[5]Корсак Л.Р.'!AM17+'[5]Корсак В.І.'!AM17+[5]Конякіна!AM17 -> 0 | AN17: ='[5]ПП ВДГ'!AN17+'[5]Корсак Л.Р.'!AN17+'[5]Корсак В.І.'!AN17+[5]Конякіна!AN17 -> 0 | AO17: =SUM(AM17:AN17) -> 0 | AP17: ='Солар Вест'!AP17+Будник!AP17 -> 0 | AQ17: ='Солар Вест'!AQ17+Будник!AQ17 -> 0 | AR17: =SUM(AP17:AQ17) -> 0 | AS17: ='[5]ПП ВДГ'!AS17+'[5]Корсак Л.Р.'!AS17+'[5]Корсак В.І.'!AS17+[5]Конякіна!AS17 -> 0 | AT17: ='[5]ПП ВДГ'!AT17+'[5]Корсак Л.Р.'!AT17+'[5]Корсак В.І.'!AT17+[5]Конякіна!AT17 -> 0 | AU17: =SUM(AS17:AT17) -> 0 | AV17: ='Солар Вест'!AV17+Будник!AV17 -> 0 | AW17: ='Солар Вест'!AW17+Будник!AW17 -> 0 | AX17: =SUM(AV17:AW17) -> 0 | AY17: ='[5]ПП ВДГ'!AY17+'[5]Корсак Л.Р.'!AY17+'[5]Корсак В.І.'!AY17+[5]Конякіна!AY17 -> 0 | AZ17: ='[5]ПП ВДГ'!AZ17+'[5]Корсак Л.Р.'!AZ17+'[5]Корсак В.І.'!AZ17+[5]Конякіна!AZ17 -> 0 | BA17: =SUM(AY17:AZ17) -> 0 | BB17: ='Солар Вест'!BB17+Будник!BB17 -> 0 | BC17: ='Солар Вест'!BC17+Будник!BC17 -> 0 | BD17: =SUM(BB17:BC17) -> 0 | BE17: ='Солар Вест'!BE17+Будник!BE17 -> 0 | BF17: ='Солар Вест'!BF17+Будник!BF17 -> 0 | BG17: =SUM(BE17:BF17) -> 0 | BH17: ='Солар Вест'!BH17+Будник!BH17 -> 0 | BI17: ='Солар Вест'!BI17+Будник!BI17 -> 0 | BJ17: =SUM(BH17:BI17) -> 0 | BK17: ='[5]ПП ВДГ'!BK17+'[5]Корсак Л.Р.'!BK17+'[5]Корсак В.І.'!BK17+[5]Конякіна!BK17 -> 0 | BL17: ='[5]ПП ВДГ'!BL17+'[5]Корсак Л.Р.'!BL17+'[5]Корсак В.І.'!BL17+[5]Конякіна!BL17 -> 0 | BM17: =SUM(BK17:BL17) -> 0 | BN17: ='Солар Вест'!BN17+Будник!BN17 -> 0 | BO17: ='Солар Вест'!BO17+Будник!BO17 -> 0 | BP17: =SUM(BN17:BO17) -> 0 | BQ17: ='[5]ПП ВДГ'!BQ17+'[5]Корсак Л.Р.'!BQ17+'[5]Корсак В.І.'!BQ17+[5]Конякіна!BQ17 -> 0 | BR17: ='[5]ПП ВДГ'!BR17+'[5]Корсак Л.Р.'!BR17+'[5]Корсак В.І.'!BR17+[5]Конякіна!BR17 -> 0 | BS17: =SUM(BQ17:BR17) -> 0 | BT17: ='Солар Вест'!BT17+Будник!BT17 -> 0 | BU17: ='Солар Вест'!BU17+Будник!BU17 -> 0 | BV17: =SUM(BT17:BU17) -> 0 | BW17: =+C17+I17+O17+AA17+AG17+U17+AM17+AS17+AY17+BE17+BK17+BQ17 -> 0 | BX17: =+D17+J17+P17+AB17+AH17+V17+AN17+AT17+AZ17+BF17+BL17+BR17 -> 0 | BY17: =SUM(BW17:BX17) -> 0 | BZ17: =+F17+L17+R17+AD17+AJ17+X17+AP17+AV17+BB17+BH17+BN17+BT17 -> 0 | CA17: =+G17+M17+S17+AE17+AK17+Y17+AQ17+AW17+BC17+BI17+BO17+BU17 -> 0 | CB17: =SUM(BZ17:CA17) -> 0
A18: 114 | B18: Дохід від оренди зовнішнім контрагентам | C18: ='[5]ПП ВДГ'!C18+'[5]Корсак Л.Р.'!C18+'[5]Корсак В.І.'!C18+[5]Конякіна!C18 -> 175000 | D18: ='[5]ПП ВДГ'!D18+'[5]Корсак Л.Р.'!D18+'[5]Корсак В.І.'!D18+[5]Конякіна!D18 -> 191000 | E18: =SUM(C18:D18) -> 366000 | F18: ='Солар Вест'!F18+Будник!F18 -> 0 | G18: ='Солар Вест'!G18+Будник!G18 -> 0 | H18: =SUM(F18:G18) -> 0 | I18: ='[5]ПП ВДГ'!I18+'[5]Корсак Л.Р.'!I18+'[5]Корсак В.І.'!I18+[5]Конякіна!I18 -> 175000 | J18: ='[5]ПП ВДГ'!J18+'[5]Корсак Л.Р.'!J18+'[5]Корсак В.І.'!J18+[5]Конякіна!J18 -> 191000 | K18: =SUM(I18:J18) -> 366000 | L18: ='Солар Вест'!L18+Будник!L18 -> 0 | M18: ='Солар Вест'!M18+Будник!M18 -> 0 | N18: =SUM(L18:M18) -> 0 | O18: ='[5]ПП ВДГ'!O18+'[5]Корсак Л.Р.'!O18+'[5]Корсак В.І.'!O18+[5]Конякіна!O18 -> 175000 | P18: ='[5]ПП ВДГ'!P18+'[5]Корсак Л.Р.'!P18+'[5]Корсак В.І.'!P18+[5]Конякіна!P18 -> 191000 | Q18: =SUM(O18:P18) -> 366000 | R18: ='Солар Вест'!R18+Будник!R18 -> 0 | S18: ='Солар Вест'!S18+Будник!S18 -> 0 | T18: =SUM(R18:S18) -> 0 | U18: ='[5]ПП ВДГ'!U18+'[5]Корсак Л.Р.'!U18+'[5]Корсак В.І.'!U18+[5]Конякіна!U18 -> 270000 | V18: ='[5]ПП ВДГ'!V18+'[5]Корсак Л.Р.'!V18+'[5]Корсак В.І.'!V18+[5]Конякіна!V18 -> 97000 | W18: =SUM(U18:V18) -> 367000 | X18: ='Солар Вест'!X18+Будник!X18 -> 0 | Y18: ='Солар Вест'!Y18+Будник!Y18 -> 0 | Z18: =SUM(X18:Y18) -> 0 | AA18: ='[5]ПП ВДГ'!AA18+'[5]Корсак Л.Р.'!AA18+'[5]Корсак В.І.'!AA18+[5]Конякіна!AA18 -> 175000 | AB18: ='[5]ПП ВДГ'!AB18+'[5]Корсак Л.Р.'!AB18+'[5]Корсак В.І.'!AB18+[5]Конякіна!AB18 -> 191000 | AC18: =SUM(AA18:AB18) -> 366000 | AD18: ='Солар Вест'!AD18+Будник!AD18 -> 0 | AE18: ='Солар Вест'!AE18+Будник!AE18 -> 0 | AF18: =SUM(AD18:AE18) -> 0 | AG18: ='[5]ПП ВДГ'!AG18+'[5]Корсак Л.Р.'!AG18+'[5]Корсак В.І.'!AG18+[5]Конякіна!AG18 -> 180000 | AH18: ='[5]ПП ВДГ'!AH18+'[5]Корсак Л.Р.'!AH18+'[5]Корсак В.І.'!AH18+[5]Конякіна!AH18 -> 199000 | AI18: =SUM(AG18:AH18) -> 379000 | AJ18: ='Солар Вест'!AJ18+Будник!AJ18 -> 0 | AK18: ='Солар Вест'!AK18+Будник!AK18 -> 0 | AL18: =SUM(AJ18:AK18) -> 0 | AM18: ='[5]ПП ВДГ'!AM18+'[5]Корсак Л.Р.'!AM18+'[5]Корсак В.І.'!AM18+[5]Конякіна!AM18 -> 175000 | AN18: ='[5]ПП ВДГ'!AN18+'[5]Корсак Л.Р.'!AN18+'[5]Корсак В.І.'!AN18+[5]Конякіна!AN18 -> 194000 | AO18: =SUM(AM18:AN18) -> 369000 | AP18: ='Солар Вест'!AP18+Будник!AP18 -> 0 | AQ18: ='Солар Вест'!AQ18+Будник!AQ18 -> 0 | AR18: =SUM(AP18:AQ18) -> 0 | AS18: ='[5]ПП ВДГ'!AS18+'[5]Корсак Л.Р.'!AS18+'[5]Корсак В.І.'!AS18+[5]Конякіна!AS18 -> 175000 | AT18: ='[5]ПП ВДГ'!AT18+'[5]Корсак Л.Р.'!AT18+'[5]Корсак В.І.'!AT18+[5]Конякіна!AT18 -> 191000 | AU18: =SUM(AS18:AT18) -> 366000 | AV18: ='Солар Вест'!AV18+Будник!AV18 -> 0 | AW18: ='Солар Вест'!AW18+Будник!AW18 -> 0 | AX18: =SUM(AV18:AW18) -> 0 | AY18: ='[5]ПП ВДГ'!AY18+'[5]Корсак Л.Р.'!AY18+'[5]Корсак В.І.'!AY18+[5]Конякіна!AY18 -> 175000 | AZ18: ='[5]ПП ВДГ'!AZ18+'[5]Корсак Л.Р.'!AZ18+'[5]Корсак В.І.'!AZ18+[5]Конякіна!AZ18 -> 191000 | BA18: =SUM(AY18:AZ18) -> 366000 | BB18: ='Солар Вест'!BB18+Будник!BB18 -> 0 | BC18: ='Солар Вест'!BC18+Будник!BC18 -> 0 | BD18: =SUM(BB18:BC18) -> 0 | BE18: ='Солар Вест'!BE18+Будник!BE18 -> 0 | BF18: ='Солар Вест'!BF18+Будник!BF18 -> 0 | BG18: =SUM(BE18:BF18) -> 0 | BH18: ='Солар Вест'!BH18+Будник!BH18 -> 0 | BI18: ='Солар Вест'!BI18+Будник!BI18 -> 0 | BJ18: =SUM(BH18:BI18) -> 0 | BK18: ='[5]ПП ВДГ'!BK18+'[5]Корсак Л.Р.'!BK18+'[5]Корсак В.І.'!BK18+[5]Конякіна!BK18 -> 175000 | BL18: ='[5]ПП ВДГ'!BL18+'[5]Корсак Л.Р.'!BL18+'[5]Корсак В.І.'!BL18+[5]Конякіна!BL18 -> 183000 | BM18: =SUM(BK18:BL18) -> 358000 | BN18: ='Солар Вест'!BN18+Будник!BN18 -> 0 | BO18: ='Солар Вест'!BO18+Будник!BO18 -> 0 | BP18: =SUM(BN18:BO18) -> 0 | BQ18: ='[5]ПП ВДГ'!BQ18+'[5]Корсак Л.Р.'!BQ18+'[5]Корсак В.І.'!BQ18+[5]Конякіна!BQ18 -> 235000 | BR18: ='[5]ПП ВДГ'!BR18+'[5]Корсак Л.Р.'!BR18+'[5]Корсак В.І.'!BR18+[5]Конякіна!BR18 -> 135000 | BS18: =SUM(BQ18:BR18) -> 370000 | BT18: ='Солар Вест'!BT18+Будник!BT18 -> 0 | BU18: ='Солар Вест'!BU18+Будник!BU18 -> 0 | BV18: =SUM(BT18:BU18) -> 0 | BW18: =+C18+I18+O18+AA18+AG18+U18+AM18+AS18+AY18+BE18+BK18+BQ18 -> 2085000 | BX18: =+D18+J18+P18+AB18+AH18+V18+AN18+AT18+AZ18+BF18+BL18+BR18 -> 1954000 | BY18: =SUM(BW18:BX18) -> 4039000 | BZ18: =+F18+L18+R18+AD18+AJ18+X18+AP18+AV18+BB18+BH18+BN18+BT18 -> 0 | CA18: =+G18+M18+S18+AE18+AK18+Y18+AQ18+AW18+BC18+BI18+BO18+BU18 -> 0 | CB18: =SUM(BZ18:CA18) -> 0
B19: в т.ч. внутрішньогруповий дохід від оренди | C19: ='[5]ПП ВДГ'!C19+'[5]Корсак Л.Р.'!C19+'[5]Корсак В.І.'!C19+[5]Конякіна!C19 -> 115000 | D19: ='[5]ПП ВДГ'!D19+'[5]Корсак Л.Р.'!D19+'[5]Корсак В.І.'!D19+[5]Конякіна!D19 -> 190000 | E19: =SUM(C19:D19) -> 305000 | F19: ='Солар Вест'!F19+Будник!F19 -> 0 | G19: ='Солар Вест'!G19+Будник!G19 -> 0 | H19: =SUM(F19:G19) -> 0 | I19: ='[5]ПП ВДГ'!I19+'[5]Корсак Л.Р.'!I19+'[5]Корсак В.І.'!I19+[5]Конякіна!I19 -> 115000 | J19: ='[5]ПП ВДГ'!J19+'[5]Корсак Л.Р.'!J19+'[5]Корсак В.І.'!J19+[5]Конякіна!J19 -> 190000 | K19: =SUM(I19:J19) -> 305000 | L19: ='Солар Вест'!L19+Будник!L19 -> 0 | M19: ='Солар Вест'!M19+Будник!M19 -> 0 | N19: =SUM(L19:M19) -> 0 | O19: ='[5]ПП ВДГ'!O19+'[5]Корсак Л.Р.'!O19+'[5]Корсак В.І.'!O19+[5]Конякіна!O19 -> 115000 | P19: ='[5]ПП ВДГ'!P19+'[5]Корсак Л.Р.'!P19+'[5]Корсак В.І.'!P19+[5]Конякіна!P19 -> 190000 | Q19: =SUM(O19:P19) -> 305000 | R19: ='Солар Вест'!R19+Будник!R19 -> 0 | S19: ='Солар Вест'!S19+Будник!S19 -> 0 | T19: =SUM(R19:S19) -> 0 | U19: ='[5]ПП ВДГ'!U19+'[5]Корсак Л.Р.'!U19+'[5]Корсак В.І.'!U19+[5]Конякіна!U19 -> 120000 | V19: ='[5]ПП ВДГ'!V19+'[5]Корсак Л.Р.'!V19+'[5]Корсак В.І.'!V19+[5]Конякіна!V19 -> 97000 | W19: =SUM(U19:V19) -> 217000 | X19: ='Солар Вест'!X19+Будник!X19 -> 0 | Y19: ='Солар Вест'!Y19+Будник!Y19 -> 0 | Z19: =SUM(X19:Y19) -> 0 | AA19: ='[5]ПП ВДГ'!AA19+'[5]Корсак Л.Р.'!AA19+'[5]Корсак В.І.'!AA19+[5]Конякіна!AA19 -> 115000 | AB19: ='[5]ПП ВДГ'!AB19+'[5]Корсак Л.Р.'!AB19+'[5]Корсак В.І.'!AB19+[5]Конякіна!AB19 -> 190000 | AC19: =SUM(AA19:AB19) -> 305000 | AD19: ='Солар Вест'!AD19+Будник!AD19 -> 0 | AE19: ='Солар Вест'!AE19+Будник!AE19 -> 0 | AF19: =SUM(AD19:AE19) -> 0 | AG19: ='[5]ПП ВДГ'!AG19+'[5]Корсак Л.Р.'!AG19+'[5]Корсак В.І.'!AG19+[5]Конякіна!AG19 -> 70000 | AH19: ='[5]ПП ВДГ'!AH19+'[5]Корсак Л.Р.'!AH19+'[5]Корсак В.І.'!AH19+[5]Конякіна!AH19 -> 197000 | AI19: =SUM(AG19:AH19) -> 267000 | AJ19: ='Солар Вест'!AJ19+Будник!AJ19 -> 0 | AK19: ='Солар Вест'!AK19+Будник!AK19 -> 0 | AL19: =SUM(AJ19:AK19) -> 0 | AM19: ='[5]ПП ВДГ'!AM19+'[5]Корсак Л.Р.'!AM19+'[5]Корсак В.І.'!AM19+[5]Конякіна!AM19 -> 65000 | AN19: ='[5]ПП ВДГ'!AN19+'[5]Корсак Л.Р.'!AN19+'[5]Корсак В.І.'!AN19+[5]Конякіна!AN19 -> 194000 | AO19: =SUM(AM19:AN19) -> 259000 | AP19: ='Солар Вест'!AP19+Будник!AP19 -> 0 | AQ19: ='Солар Вест'!AQ19+Будник!AQ19 -> 0 | AR19: =SUM(AP19:AQ19) -> 0 | AS19: ='[5]ПП ВДГ'!AS19+'[5]Корсак Л.Р.'!AS19+'[5]Корсак В.І.'!AS19+[5]Конякіна!AS19 -> 115000 | AT19: ='[5]ПП ВДГ'!AT19+'[5]Корсак Л.Р.'!AT19+'[5]Корсак В.І.'!AT19+[5]Конякіна!AT19 -> 190000 | AU19: =SUM(AS19:AT19) -> 305000 | AV19: ='Солар Вест'!AV19+Будник!AV19 -> 0 | AW19: ='Солар Вест'!AW19+Будник!AW19 -> 0 | AX19: =SUM(AV19:AW19) -> 0 | AY19: ='[5]ПП ВДГ'!AY19+'[5]Корсак Л.Р.'!AY19+'[5]Корсак В.І.'!AY19+[5]Конякіна!AY19 -> 115000 | AZ19: ='[5]ПП ВДГ'!AZ19+'[5]Корсак Л.Р.'!AZ19+'[5]Корсак В.І.'!AZ19+[5]Конякіна!AZ19 -> 190000 | BA19: =SUM(AY19:AZ19) -> 305000 | BB19: ='Солар Вест'!BB19+Будник!BB19 -> 0 | BC19: ='Солар Вест'!BC19+Будник!BC19 -> 0 | BD19: =SUM(BB19:BC19) -> 0 | BE19: ='Солар Вест'!BE19+Будник!BE19 -> 0 | BF19: ='Солар Вест'!BF19+Будник!BF19 -> 0 | BG19: =SUM(BE19:BF19) -> 0 | BH19: ='Солар Вест'!BH19+Будник!BH19 -> 0 | BI19: ='Солар Вест'!BI19+Будник!BI19 -> 0 | BJ19: =SUM(BH19:BI19) -> 0 | BK19: ='[5]ПП ВДГ'!BK19+'[5]Корсак Л.Р.'!BK19+'[5]Корсак В.І.'!BK19+[5]Конякіна!BK19 -> 66000 | BL19: ='[5]ПП ВДГ'!BL19+'[5]Корсак Л.Р.'!BL19+'[5]Корсак В.І.'!BL19+[5]Конякіна!BL19 -> 183000 | BM19: =SUM(BK19:BL19) -> 249000 | BN19: ='Солар Вест'!BN19+Будник!BN19 -> 0 | BO19: ='Солар Вест'!BO19+Будник!BO19 -> 0 | BP19: =SUM(BN19:BO19) -> 0 | BQ19: ='[5]ПП ВДГ'!BQ19+'[5]Корсак Л.Р.'!BQ19+'[5]Корсак В.І.'!BQ19+[5]Конякіна!BQ19 -> 135000 | BR19: ='[5]ПП ВДГ'!BR19+'[5]Корсак Л.Р.'!BR19+'[5]Корсак В.І.'!BR19+[5]Конякіна!BR19 -> 133000 | BS19: =SUM(BQ19:BR19) -> 268000 | BT19: ='Солар Вест'!BT19+Будник!BT19 -> 0 | BU19: ='Солар Вест'!BU19+Будник!BU19 -> 0 | BV19: =SUM(BT19:BU19) -> 0 | BW19: =+C19+I19+O19+AA19+AG19+U19+AM19+AS19+AY19+BE19+BK19+BQ19 -> 1146000 | BX19: =+D19+J19+P19+AB19+AH19+V19+AN19+AT19+AZ19+BF19+BL19+BR19 -> 1944000 | BY19: =SUM(BW19:BX19) -> 3090000 | BZ19: =+F19+L19+R19+AD19+AJ19+X19+AP19+AV19+BB19+BH19+BN19+BT19 -> 0 | CA19: =+G19+M19+S19+AE19+AK19+Y19+AQ19+AW19+BC19+BI19+BO19+BU19 -> 0 | CB19: =SUM(BZ19:CA19) -> 0
A20: 115 | B20: Інший дохід | C20: ='[5]ПП ВДГ'!C20+'[5]Корсак Л.Р.'!C20+'[5]Корсак В.І.'!C20+[5]Конякіна!C20 -> 0 | D20: ='[5]ПП ВДГ'!D20+'[5]Корсак Л.Р.'!D20+'[5]Корсак В.І.'!D20+[5]Конякіна!D20 -> 0 | E20: =SUM(C20:D20) -> 0 | F20: ='Солар Вест'!F20+Будник!F20 -> 0 | G20: ='Солар Вест'!G20+Будник!G20 -> 0 | H20: =SUM(F20:G20) -> 0 | I20: ='[5]ПП ВДГ'!I20+'[5]Корсак Л.Р.'!I20+'[5]Корсак В.І.'!I20+[5]Конякіна!I20 -> 0 | J20: ='[5]ПП ВДГ'!J20+'[5]Корсак Л.Р.'!J20+'[5]Корсак В.І.'!J20+[5]Конякіна!J20 -> 0 | K20: =SUM(I20:J20) -> 0 | L20: ='Солар Вест'!L20+Будник!L20 -> 0 | M20: ='Солар Вест'!M20+Будник!M20 -> 0 | N20: =SUM(L20:M20) -> 0 | O20: ='[5]ПП ВДГ'!O20+'[5]Корсак Л.Р.'!O20+'[5]Корсак В.І.'!O20+[5]Конякіна!O20 -> 0 | P20: ='[5]ПП ВДГ'!P20+'[5]Корсак Л.Р.'!P20+'[5]Корсак В.І.'!P20+[5]Конякіна!P20 -> 0 | Q20: =SUM(O20:P20) -> 0 | R20: ='Солар Вест'!R20+Будник!R20 -> 0 | S20: ='Солар Вест'!S20+Будник!S20 -> 0 | T20: =SUM(R20:S20) -> 0 | U20: ='[5]ПП ВДГ'!U20+'[5]Корсак Л.Р.'!U20+'[5]Корсак В.І.'!U20+[5]Конякіна!U20 -> 0 | V20: ='[5]ПП ВДГ'!V20+'[5]Корсак Л.Р.'!V20+'[5]Корсак В.І.'!V20+[5]Конякіна!V20 -> 0 | W20: =SUM(U20:V20) -> 0 | X20: ='Солар Вест'!X20+Будник!X20 -> 0 | Y20: ='Солар Вест'!Y20+Будник!Y20 -> 0 | Z20: =SUM(X20:Y20) -> 0 | AA20: ='[5]ПП ВДГ'!AA20+'[5]Корсак Л.Р.'!AA20+'[5]Корсак В.І.'!AA20+[5]Конякіна!AA20 -> 0 | AB20: ='[5]ПП ВДГ'!AB20+'[5]Корсак Л.Р.'!AB20+'[5]Корсак В.І.'!AB20+[5]Конякіна!AB20 -> 3200 | AC20: =SUM(AA20:AB20) -> 3200 | AD20: ='Солар Вест'!AD20+Будник!AD20 -> 0 | AE20: ='Солар Вест'!AE20+Будник!AE20 -> 0 | AF20: =SUM(AD20:AE20) -> 0 | AG20: ='[5]ПП ВДГ'!AG20+'[5]Корсак Л.Р.'!AG20+'[5]Корсак В.І.'!AG20+[5]Конякіна!AG20 -> 0 | AH20: ='[5]ПП ВДГ'!AH20+'[5]Корсак Л.Р.'!AH20+'[5]Корсак В.І.'!AH20+[5]Конякіна!AH20 -> 3500 | AI20: =SUM(AG20:AH20) -> 3500 | AJ20: ='Солар Вест'!AJ20+Будник!AJ20 -> 0 | AK20: ='Солар Вест'!AK20+Будник!AK20 -> 0 | AL20: =SUM(AJ20:AK20) -> 0 | AM20: ='[5]ПП ВДГ'!AM20+'[5]Корсак Л.Р.'!AM20+'[5]Корсак В.І.'!AM20+[5]Конякіна!AM20 -> 0 | AN20: ='[5]ПП ВДГ'!AN20+'[5]Корсак Л.Р.'!AN20+'[5]Корсак В.І.'!AN20+[5]Конякіна!AN20 -> 3700 | AO20: =SUM(AM20:AN20) -> 3700 | AP20: ='Солар Вест'!AP20+Будник!AP20 -> 0 | AQ20: ='Солар Вест'!AQ20+Будник!AQ20 -> 0 | AR20: =SUM(AP20:AQ20) -> 0 | AS20: ='[5]ПП ВДГ'!AS20+'[5]Корсак Л.Р.'!AS20+'[5]Корсак В.І.'!AS20+[5]Конякіна!AS20 -> 0 | AT20: ='[5]ПП ВДГ'!AT20+'[5]Корсак Л.Р.'!AT20+'[5]Корсак В.І.'!AT20+[5]Конякіна!AT20 -> 3700 | AU20: =SUM(AS20:AT20) -> 3700 | AV20: ='Солар Вест'!AV20+Будник!AV20 -> 0 | AW20: ='Солар Вест'!AW20+Будник!AW20 -> 0 | AX20: =SUM(AV20:AW20) -> 0 | AY20: ='[5]ПП ВДГ'!AY20+'[5]Корсак Л.Р.'!AY20+'[5]Корсак В.І.'!AY20+[5]Конякіна!AY20 -> 0 | AZ20: ='[5]ПП ВДГ'!AZ20+'[5]Корсак Л.Р.'!AZ20+'[5]Корсак В.І.'!AZ20+[5]Конякіна!AZ20 -> 0 | BA20: =SUM(AY20:AZ20) -> 0 | BB20: ='Солар Вест'!BB20+Будник!BB20 -> 0 | BC20: ='Солар Вест'!BC20+Будник!BC20 -> 0 | BD20: =SUM(BB20:BC20) -> 0 | BE20: ='Солар Вест'!BE20+Будник!BE20 -> 0 | BF20: ='Солар Вест'!BF20+Будник!BF20 -> 0 | BG20: =SUM(BE20:BF20) -> 0 | BH20: ='Солар Вест'!BH20+Будник!BH20 -> 0 | BI20: ='Солар Вест'!BI20+Будник!BI20 -> 0 | BJ20: =SUM(BH20:BI20) -> 0 | BK20: ='[5]ПП ВДГ'!BK20+'[5]Корсак Л.Р.'!BK20+'[5]Корсак В.І.'!BK20+[5]Конякіна!BK20 -> 0 | BL20: ='[5]ПП ВДГ'!BL20+'[5]Корсак Л.Р.'!BL20+'[5]Корсак В.І.'!BL20+[5]Конякіна!BL20 -> 0 | BM20: =SUM(BK20:BL20) -> 0 | BN20: ='Солар Вест'!BN20+Будник!BN20 -> 0 | BO20: ='Солар Вест'!BO20+Будник!BO20 -> 0 | BP20: =SUM(BN20:BO20) -> 0 | BQ20: ='[5]ПП ВДГ'!BQ20+'[5]Корсак Л.Р.'!BQ20+'[5]Корсак В.І.'!BQ20+[5]Конякіна!BQ20 -> 0 | BR20: ='[5]ПП ВДГ'!BR20+'[5]Корсак Л.Р.'!BR20+'[5]Корсак В.І.'!BR20+[5]Конякіна!BR20 -> 0 | BS20: =SUM(BQ20:BR20) -> 0 | BT20: ='Солар Вест'!BT20+Будник!BT20 -> 0 | BU20: ='Солар Вест'!BU20+Будник!BU20 -> 0 | BV20: =SUM(BT20:BU20) -> 0 | BW20: =+C20+I20+O20+AA20+AG20+U20+AM20+AS20+AY20+BE20+BK20+BQ20 -> 0 | BX20: =+D20+J20+P20+AB20+AH20+V20+AN20+AT20+AZ20+BF20+BL20+BR20 -> 14100 | BY20: =SUM(BW20:BX20) -> 14100 | BZ20: =+F20+L20+R20+AD20+AJ20+X20+AP20+AV20+BB20+BH20+BN20+BT20 -> 0 | CA20: =+G20+M20+S20+AE20+AK20+Y20+AQ20+AW20+BC20+BI20+BO20+BU20 -> 0 | CB20: =SUM(BZ20:CA20) -> 0
A21: 211 | B21: Отримання кредитів та позик | C21: ='[5]ПП ВДГ'!C21+'[5]Корсак Л.Р.'!C21+'[5]Корсак В.І.'!C21+[5]Конякіна!C21 -> 0 | D21: ='[5]ПП ВДГ'!D21+'[5]Корсак Л.Р.'!D21+'[5]Корсак В.І.'!D21+[5]Конякіна!D21 -> 0 | E21: =SUM(C21:D21) -> 0 | F21: ='Солар Вест'!F21+Будник!F21 -> 0 | G21: ='Солар Вест'!G21+Будник!G21 -> 0 | H21: =SUM(F21:G21) -> 0 | I21: ='[5]ПП ВДГ'!I21+'[5]Корсак Л.Р.'!I21+'[5]Корсак В.І.'!I21+[5]Конякіна!I21 -> 0 | J21: ='[5]ПП ВДГ'!J21+'[5]Корсак Л.Р.'!J21+'[5]Корсак В.І.'!J21+[5]Конякіна!J21 -> 0 | K21: =SUM(I21:J21) -> 0 | L21: ='Солар Вест'!L21+Будник!L21 -> 0 | M21: ='Солар Вест'!M21+Будник!M21 -> 0 | N21: =SUM(L21:M21) -> 0 | O21: ='[5]ПП ВДГ'!O21+'[5]Корсак Л.Р.'!O21+'[5]Корсак В.І.'!O21+[5]Конякіна!O21 -> 0 | P21: ='[5]ПП ВДГ'!P21+'[5]Корсак Л.Р.'!P21+'[5]Корсак В.І.'!P21+[5]Конякіна!P21 -> 0 | Q21: =SUM(O21:P21) -> 0 | R21: ='Солар Вест'!R21+Будник!R21 -> 0 | S21: ='Солар Вест'!S21+Будник!S21 -> 0 | T21: =SUM(R21:S21) -> 0 | U21: ='[5]ПП ВДГ'!U21+'[5]Корсак Л.Р.'!U21+'[5]Корсак В.І.'!U21+[5]Конякіна!U21 -> 0 | V21: ='[5]ПП ВДГ'!V21+'[5]Корсак Л.Р.'!V21+'[5]Корсак В.І.'!V21+[5]Конякіна!V21 -> 0 | W21: =SUM(U21:V21) -> 0 | X21: ='Солар Вест'!X21+Будник!X21 -> 0 | Y21: ='Солар Вест'!Y21+Будник!Y21 -> 0 | Z21: =SUM(X21:Y21) -> 0 | AA21: ='[5]ПП ВДГ'!AA21+'[5]Корсак Л.Р.'!AA21+'[5]Корсак В.І.'!AA21+[5]Конякіна!AA21 -> 0 | AB21: ='[5]ПП ВДГ'!AB21+'[5]Корсак Л.Р.'!AB21+'[5]Корсак В.І.'!AB21+[5]Конякіна!AB21 -> 0 | AC21: =SUM(AA21:AB21) -> 0 | AD21: ='Солар Вест'!AD21+Будник!AD21 -> 0 | AE21: ='Солар Вест'!AE21+Будник!AE21 -> 0 | AF21: =SUM(AD21:AE21) -> 0 | AG21: ='[5]ПП ВДГ'!AG21+'[5]Корсак Л.Р.'!AG21+'[5]Корсак В.І.'!AG21+[5]Конякіна!AG21 -> 0 | AH21: ='[5]ПП ВДГ'!AH21+'[5]Корсак Л.Р.'!AH21+'[5]Корсак В.І.'!AH21+[5]Конякіна!AH21 -> 0 | AI21: =SUM(AG21:AH21) -> 0 | AJ21: ='Солар Вест'!AJ21+Будник!AJ21 -> 0 | AK21: ='Солар Вест'!AK21+Будник!AK21 -> 0 | AL21: =SUM(AJ21:AK21) -> 0 | AM21: ='[5]ПП ВДГ'!AM21+'[5]Корсак Л.Р.'!AM21+'[5]Корсак В.І.'!AM21+[5]Конякіна!AM21 -> 0 | AN21: ='[5]ПП ВДГ'!AN21+'[5]Корсак Л.Р.'!AN21+'[5]Корсак В.І.'!AN21+[5]Конякіна!AN21 -> 0 | AO21: =SUM(AM21:AN21) -> 0 | AP21: ='Солар Вест'!AP21+Будник!AP21 -> 0 | AQ21: ='Солар Вест'!AQ21+Будник!AQ21 -> 0 | AR21: =SUM(AP21:AQ21) -> 0 | AS21: ='[5]ПП ВДГ'!AS21+'[5]Корсак Л.Р.'!AS21+'[5]Корсак В.І.'!AS21+[5]Конякіна!AS21 -> 0 | AT21: ='[5]ПП ВДГ'!AT21+'[5]Корсак Л.Р.'!AT21+'[5]Корсак В.І.'!AT21+[5]Конякіна!AT21 -> 0 | AU21: =SUM(AS21:AT21) -> 0 | AV21: ='Солар Вест'!AV21+Будник!AV21 -> 0 | AW21: ='Солар Вест'!AW21+Будник!AW21 -> 0 | AX21: =SUM(AV21:AW21) -> 0 | AY21: ='[5]ПП ВДГ'!AY21+'[5]Корсак Л.Р.'!AY21+'[5]Корсак В.І.'!AY21+[5]Конякіна!AY21 -> 0 | AZ21: ='[5]ПП ВДГ'!AZ21+'[5]Корсак Л.Р.'!AZ21+'[5]Корсак В.І.'!AZ21+[5]Конякіна!AZ21 -> 0 | BA21: =SUM(AY21:AZ21) -> 0 | BB21: ='Солар Вест'!BB21+Будник!BB21 -> 0 | BC21: ='Солар Вест'!BC21+Будник!BC21 -> 0 | BD21: =SUM(BB21:BC21) -> 0 | BE21: ='Солар Вест'!BE21+Будник!BE21 -> 0 | BF21: ='Солар Вест'!BF21+Будник!BF21 -> 0 | BG21: =SUM(BE21:BF21) -> 0 | BH21: ='Солар Вест'!BH21+Будник!BH21 -> 0 | BI21: ='Солар Вест'!BI21+Будник!BI21 -> 0 | BJ21: =SUM(BH21:BI21) -> 0 | BK21: ='[5]ПП ВДГ'!BK21+'[5]Корсак Л.Р.'!BK21+'[5]Корсак В.І.'!BK21+[5]Конякіна!BK21 -> 0 | BL21: ='[5]ПП ВДГ'!BL21+'[5]Корсак Л.Р.'!BL21+'[5]Корсак В.І.'!BL21+[5]Конякіна!BL21 -> 0 | BM21: =SUM(BK21:BL21) -> 0 | BN21: ='Солар Вест'!BN21+Будник!BN21 -> 0 | BO21: ='Солар Вест'!BO21+Будник!BO21 -> 0 | BP21: =SUM(BN21:BO21) -> 0 | BQ21: ='[5]ПП ВДГ'!BQ21+'[5]Корсак Л.Р.'!BQ21+'[5]Корсак В.І.'!BQ21+[5]Конякіна!BQ21 -> 0 | BR21: ='[5]ПП ВДГ'!BR21+'[5]Корсак Л.Р.'!BR21+'[5]Корсак В.І.'!BR21+[5]Конякіна!BR21 -> 0 | BS21: =SUM(BQ21:BR21) -> 0 | BT21: ='Солар Вест'!BT21+Будник!BT21 -> 0 | BU21: ='Солар Вест'!BU21+Будник!BU21 -> 0 | BV21: =SUM(BT21:BU21) -> 0 | BW21: =+C21+I21+O21+AA21+AG21+U21+AM21+AS21+AY21+BE21+BK21+BQ21 -> 0 | BX21: =+D21+J21+P21+AB21+AH21+V21+AN21+AT21+AZ21+BF21+BL21+BR21 -> 0 | BY21: =SUM(BW21:BX21) -> 0 | BZ21: =+F21+L21+R21+AD21+AJ21+X21+AP21+AV21+BB21+BH21+BN21+BT21 -> 0 | CA21: =+G21+M21+S21+AE21+AK21+Y21+AQ21+AW21+BC21+BI21+BO21+BU21 -> 0 | CB21: =SUM(BZ21:CA21) -> 0
A22: 212 | B22: Отримання фінансових позик | C22: ='[5]ПП ВДГ'!C22+'[5]Корсак Л.Р.'!C22+'[5]Корсак В.І.'!C22+[5]Конякіна!C22 -> 0 | D22: ='[5]ПП ВДГ'!D22+'[5]Корсак Л.Р.'!D22+'[5]Корсак В.І.'!D22+[5]Конякіна!D22 -> 0 | E22: =SUM(C22:D22) -> 0 | F22: ='Солар Вест'!F22+Будник!F22 -> 292000 | G22: ='Солар Вест'!G22+Будник!G22 -> 0 | H22: =SUM(F22:G22) -> 292000 | I22: ='[5]ПП ВДГ'!I22+'[5]Корсак Л.Р.'!I22+'[5]Корсак В.І.'!I22+[5]Конякіна!I22 -> 0 | J22: ='[5]ПП ВДГ'!J22+'[5]Корсак Л.Р.'!J22+'[5]Корсак В.І.'!J22+[5]Конякіна!J22 -> 0 | K22: =SUM(I22:J22) -> 0 | L22: ='Солар Вест'!L22+Будник!L22 -> 141000 | M22: ='Солар Вест'!M22+Будник!M22 -> 0 | N22: =SUM(L22:M22) -> 141000 | O22: ='[5]ПП ВДГ'!O22+'[5]Корсак Л.Р.'!O22+'[5]Корсак В.І.'!O22+[5]Конякіна!O22 -> 1700 | P22: ='[5]ПП ВДГ'!P22+'[5]Корсак Л.Р.'!P22+'[5]Корсак В.І.'!P22+[5]Конякіна!P22 -> 0 | Q22: =SUM(O22:P22) -> 1700 | R22: ='Солар Вест'!R22+Будник!R22 -> 2060000 | S22: ='Солар Вест'!S22+Будник!S22 -> 0 | T22: =SUM(R22:S22) -> 2060000 | U22: ='[5]ПП ВДГ'!U22+'[5]Корсак Л.Р.'!U22+'[5]Корсак В.І.'!U22+[5]Конякіна!U22 -> 0 | V22: ='[5]ПП ВДГ'!V22+'[5]Корсак Л.Р.'!V22+'[5]Корсак В.І.'!V22+[5]Конякіна!V22 -> 0 | W22: =SUM(U22:V22) -> 0 | X22: ='Солар Вест'!X22+Будник!X22 -> 0 | Y22: ='Солар Вест'!Y22+Будник!Y22 -> 0 | Z22: =SUM(X22:Y22) -> 0 | AA22: ='[5]ПП ВДГ'!AA22+'[5]Корсак Л.Р.'!AA22+'[5]Корсак В.І.'!AA22+[5]Конякіна!AA22 -> 1800 | AB22: ='[5]ПП ВДГ'!AB22+'[5]Корсак Л.Р.'!AB22+'[5]Корсак В.І.'!AB22+[5]Конякіна!AB22 -> 0 | AC22: =SUM(AA22:AB22) -> 1800 | AD22: ='Солар Вест'!AD22+Будник!AD22 -> 72000 | AE22: ='Солар Вест'!AE22+Будник!AE22 -> 0 | AF22: =SUM(AD22:AE22) -> 72000 | AG22: ='[5]ПП ВДГ'!AG22+'[5]Корсак Л.Р.'!AG22+'[5]Корсак В.І.'!AG22+[5]Конякіна!AG22 -> 1800 | AH22: ='[5]ПП ВДГ'!AH22+'[5]Корсак Л.Р.'!AH22+'[5]Корсак В.І.'!AH22+[5]Конякіна!AH22 -> 0 | AI22: =SUM(AG22:AH22) -> 1800 | AJ22: ='Солар Вест'!AJ22+Будник!AJ22 -> 458000 | AK22: ='Солар Вест'!AK22+Будник!AK22 -> 0 | AL22: =SUM(AJ22:AK22) -> 458000 | AM22: ='[5]ПП ВДГ'!AM22+'[5]Корсак Л.Р.'!AM22+'[5]Корсак В.І.'!AM22+[5]Конякіна!AM22 -> 1750 | AN22: ='[5]ПП ВДГ'!AN22+'[5]Корсак Л.Р.'!AN22+'[5]Корсак В.І.'!AN22+[5]Конякіна!AN22 -> 0 | AO22: =SUM(AM22:AN22) -> 1750 | AP22: ='Солар Вест'!AP22+Будник!AP22 -> 241100 | AQ22: ='Солар Вест'!AQ22+Будник!AQ22 -> 0 | AR22: =SUM(AP22:AQ22) -> 241100 | AS22: ='[5]ПП ВДГ'!AS22+'[5]Корсак Л.Р.'!AS22+'[5]Корсак В.І.'!AS22+[5]Конякіна!AS22 -> 1800 | AT22: ='[5]ПП ВДГ'!AT22+'[5]Корсак Л.Р.'!AT22+'[5]Корсак В.І.'!AT22+[5]Конякіна!AT22 -> 0 | AU22: =SUM(AS22:AT22) -> 1800 | AV22: ='Солар Вест'!AV22+Будник!AV22 -> 0 | AW22: ='Солар Вест'!AW22+Будник!AW22 -> 0 | AX22: =SUM(AV22:AW22) -> 0 | AY22: ='[5]ПП ВДГ'!AY22+'[5]Корсак Л.Р.'!AY22+'[5]Корсак В.І.'!AY22+[5]Конякіна!AY22 -> 1700 | AZ22: ='[5]ПП ВДГ'!AZ22+'[5]Корсак Л.Р.'!AZ22+'[5]Корсак В.І.'!AZ22+[5]Конякіна!AZ22 -> 0 | BA22: =SUM(AY22:AZ22) -> 1700 | BB22: ='Солар Вест'!BB22+Будник!BB22 -> 0 | BC22: ='Солар Вест'!BC22+Будник!BC22 -> 0 | BD22: =SUM(BB22:BC22) -> 0 | BE22: ='Солар Вест'!BE22+Будник!BE22 -> 0 | BF22: ='Солар Вест'!BF22+Будник!BF22 -> 0 | BG22: =SUM(BE22:BF22) -> 0 | BH22: ='Солар Вест'!BH22+Будник!BH22 -> 0 | BI22: ='Солар Вест'!BI22+Будник!BI22 -> 0 | BJ22: =SUM(BH22:BI22) -> 0 | BK22: ='[5]ПП ВДГ'!BK22+'[5]Корсак Л.Р.'!BK22+'[5]Корсак В.І.'!BK22+[5]Конякіна!BK22 -> 1850 | BL22: ='[5]ПП ВДГ'!BL22+'[5]Корсак Л.Р.'!BL22+'[5]Корсак В.І.'!BL22+[5]Конякіна!BL22 -> 0 | BM22: =SUM(BK22:BL22) -> 1850 | BN22: ='Солар Вест'!BN22+Будник!BN22 -> 0 | BO22: ='Солар Вест'!BO22+Будник!BO22 -> 0 | BP22: =SUM(BN22:BO22) -> 0 | BQ22: ='[5]ПП ВДГ'!BQ22+'[5]Корсак Л.Р.'!BQ22+'[5]Корсак В.І.'!BQ22+[5]Конякіна!BQ22 -> 1900 | BR22: ='[5]ПП ВДГ'!BR22+'[5]Корсак Л.Р.'!BR22+'[5]Корсак В.І.'!BR22+[5]Конякіна!BR22 -> 0 | BS22: =SUM(BQ22:BR22) -> 1900 | BT22: ='Солар Вест'!BT22+Будник!BT22 -> 0 | BU22: ='Солар Вест'!BU22+Будник!BU22 -> 0 | BV22: =SUM(BT22:BU22) -> 0 | BW22: =+C22+I22+O22+AA22+AG22+U22+AM22+AS22+AY22+BE22+BK22+BQ22 -> 14300 | BX22: =+D22+J22+P22+AB22+AH22+V22+AN22+AT22+AZ22+BF22+BL22+BR22 -> 0 | BY22: =SUM(BW22:BX22) -> 14300 | BZ22: =+F22+L22+R22+AD22+AJ22+X22+AP22+AV22+BB22+BH22+BN22+BT22 -> 3264100 | CA22: =+G22+M22+S22+AE22+AK22+Y22+AQ22+AW22+BC22+BI22+BO22+BU22 -> 0 | CB22: =SUM(BZ22:CA22) -> 3264100
B23: в т.ч. внутрішньогрупове отримання фінансових позик | C23: ='[5]ПП ВДГ'!C23+'[5]Корсак Л.Р.'!C23+'[5]Корсак В.І.'!C23+[5]Конякіна!C23 -> 0 | D23: ='[5]ПП ВДГ'!D23+'[5]Корсак Л.Р.'!D23+'[5]Корсак В.І.'!D23+[5]Конякіна!D23 -> 0 | E23: =SUM(C23:D23) -> 0 | F23: ='Солар Вест'!F23+Будник!F23 -> 0 | G23: ='Солар Вест'!G23+Будник!G23 -> 0 | H23: =SUM(F23:G23) -> 0 | I23: ='[5]ПП ВДГ'!I23+'[5]Корсак Л.Р.'!I23+'[5]Корсак В.І.'!I23+[5]Конякіна!I23 -> 0 | J23: ='[5]ПП ВДГ'!J23+'[5]Корсак Л.Р.'!J23+'[5]Корсак В.І.'!J23+[5]Конякіна!J23 -> 0 | K23: =SUM(I23:J23) -> 0 | L23: ='Солар Вест'!L23+Будник!L23 -> 0 | M23: ='Солар Вест'!M23+Будник!M23 -> 0 | N23: =SUM(L23:M23) -> 0 | O23: ='[5]ПП ВДГ'!O23+'[5]Корсак Л.Р.'!O23+'[5]Корсак В.І.'!O23+[5]Конякіна!O23 -> 1700 | P23: ='[5]ПП ВДГ'!P23+'[5]Корсак Л.Р.'!P23+'[5]Корсак В.І.'!P23+[5]Конякіна!P23 -> 0 | Q23: =SUM(O23:P23) -> 1700 | R23: ='Солар Вест'!R23+Будник!R23 -> 0 | S23: ='Солар Вест'!S23+Будник!S23 -> 0 | T23: =SUM(R23:S23) -> 0 | U23: ='[5]ПП ВДГ'!U23+'[5]Корсак Л.Р.'!U23+'[5]Корсак В.І.'!U23+[5]Конякіна!U23 -> 0 | V23: ='[5]ПП ВДГ'!V23+'[5]Корсак Л.Р.'!V23+'[5]Корсак В.І.'!V23+[5]Конякіна!V23 -> 0 | W23: =SUM(U23:V23) -> 0 | X23: ='Солар Вест'!X23+Будник!X23 -> 0 | Y23: ='Солар Вест'!Y23+Будник!Y23 -> 0 | Z23: =SUM(X23:Y23) -> 0 | AA23: ='[5]ПП ВДГ'!AA23+'[5]Корсак Л.Р.'!AA23+'[5]Корсак В.І.'!AA23+[5]Конякіна!AA23 -> 1800 | AB23: ='[5]ПП ВДГ'!AB23+'[5]Корсак Л.Р.'!AB23+'[5]Корсак В.І.'!AB23+[5]Конякіна!AB23 -> 0 | AC23: =SUM(AA23:AB23) -> 1800 | AD23: ='Солар Вест'!AD23+Будник!AD23 -> 0 | AE23: ='Солар Вест'!AE23+Будник!AE23 -> 0 | AF23: =SUM(AD23:AE23) -> 0 | AG23: ='[5]ПП ВДГ'!AG23+'[5]Корсак Л.Р.'!AG23+'[5]Корсак В.І.'!AG23+[5]Конякіна!AG23 -> 1800 | AH23: ='[5]ПП ВДГ'!AH23+'[5]Корсак Л.Р.'!AH23+'[5]Корсак В.І.'!AH23+[5]Конякіна!AH23 -> 0 | AI23: =SUM(AG23:AH23) -> 1800 | AJ23: ='Солар Вест'!AJ23+Будник!AJ23 -> 0 | AK23: ='Солар Вест'!AK23+Будник!AK23 -> 0 | AL23: =SUM(AJ23:AK23) -> 0 | AM23: ='[5]ПП ВДГ'!AM23+'[5]Корсак Л.Р.'!AM23+'[5]Корсак В.І.'!AM23+[5]Конякіна!AM23 -> 1750 | AN23: ='[5]ПП ВДГ'!AN23+'[5]Корсак Л.Р.'!AN23+'[5]Корсак В.І.'!AN23+[5]Конякіна!AN23 -> 0 | AO23: =SUM(AM23:AN23) -> 1750 | AP23: ='Солар Вест'!AP23+Будник!AP23 -> 0 | AQ23: ='Солар Вест'!AQ23+Будник!AQ23 -> 0 | AR23: =SUM(AP23:AQ23) -> 0 | AS23: ='[5]ПП ВДГ'!AS23+'[5]Корсак Л.Р.'!AS23+'[5]Корсак В.І.'!AS23+[5]Конякіна!AS23 -> 1800 | AT23: ='[5]ПП ВДГ'!AT23+'[5]Корсак Л.Р.'!AT23+'[5]Корсак В.І.'!AT23+[5]Конякіна!AT23 -> 0 | AU23: =SUM(AS23:AT23) -> 1800 | AV23: ='Солар Вест'!AV23+Будник!AV23 -> 0 | AW23: ='Солар Вест'!AW23+Будник!AW23 -> 0 | AX23: =SUM(AV23:AW23) -> 0 | AY23: ='[5]ПП ВДГ'!AY23+'[5]Корсак Л.Р.'!AY23+'[5]Корсак В.І.'!AY23+[5]Конякіна!AY23 -> 1700 | AZ23: ='[5]ПП ВДГ'!AZ23+'[5]Корсак Л.Р.'!AZ23+'[5]Корсак В.І.'!AZ23+[5]Конякіна!AZ23 -> 0 | BA23: =SUM(AY23:AZ23) -> 1700 | BB23: ='Солар Вест'!BB23+Будник!BB23 -> 0 | BC23: ='Солар Вест'!BC23+Будник!BC23 -> 0 | BD23: =SUM(BB23:BC23) -> 0 | BE23: ='Солар Вест'!BE23+Будник!BE23 -> 0 | BF23: ='Солар Вест'!BF23+Будник!BF23 -> 0 | BG23: =SUM(BE23:BF23) -> 0 | BH23: ='Солар Вест'!BH23+Будник!BH23 -> 0 | BI23: ='Солар Вест'!BI23+Будник!BI23 -> 0 | BJ23: =SUM(BH23:BI23) -> 0 | BK23: ='[5]ПП ВДГ'!BK23+'[5]Корсак Л.Р.'!BK23+'[5]Корсак В.І.'!BK23+[5]Конякіна!BK23 -> 1850 | BL23: ='[5]ПП ВДГ'!BL23+'[5]Корсак Л.Р.'!BL23+'[5]Корсак В.І.'!BL23+[5]Конякіна!BL23 -> 0 | BM23: =SUM(BK23:BL23) -> 1850 | BN23: ='Солар Вест'!BN23+Будник!BN23 -> 0 | BO23: ='Солар Вест'!BO23+Будник!BO23 -> 0 | BP23: =SUM(BN23:BO23) -> 0 | BQ23: ='[5]ПП ВДГ'!BQ23+'[5]Корсак Л.Р.'!BQ23+'[5]Корсак В.І.'!BQ23+[5]Конякіна!BQ23 -> 1900 | BR23: ='[5]ПП ВДГ'!BR23+'[5]Корсак Л.Р.'!BR23+'[5]Корсак В.І.'!BR23+[5]Конякіна!BR23 -> 0 | BS23: =SUM(BQ23:BR23) -> 1900 | BT23: ='Солар Вест'!BT23+Будник!BT23 -> 0 | BU23: ='Солар Вест'!BU23+Будник!BU23 -> 0 | BV23: =SUM(BT23:BU23) -> 0 | BW23: =+C23+I23+O23+AA23+AG23+U23+AM23+AS23+AY23+BE23+BK23+BQ23 -> 14300 | BX23: =+D23+J23+P23+AB23+AH23+V23+AN23+AT23+AZ23+BF23+BL23+BR23 -> 0 | BY23: =SUM(BW23:BX23) -> 14300 | BZ23: =+F23+L23+R23+AD23+AJ23+X23+AP23+AV23+BB23+BH23+BN23+BT23 -> 0 | CA23: =+G23+M23+S23+AE23+AK23+Y23+AQ23+AW23+BC23+BI23+BO23+BU23 -> 0 | CB23: =SUM(BZ23:CA23) -> 0
A24: 213 | B24: Повернення фінансових позик | C24: ='[5]ПП ВДГ'!C24+'[5]Корсак Л.Р.'!C24+'[5]Корсак В.І.'!C24+[5]Конякіна!C24 -> 0 | D24: ='[5]ПП ВДГ'!D24+'[5]Корсак Л.Р.'!D24+'[5]Корсак В.І.'!D24+[5]Конякіна!D24 -> 0 | E24: =SUM(C24:D24) -> 0 | F24: ='Солар Вест'!F24+Будник!F24 -> 0 | G24: ='Солар Вест'!G24+Будник!G24 -> 0 | H24: =SUM(F24:G24) -> 0 | I24: ='[5]ПП ВДГ'!I24+'[5]Корсак Л.Р.'!I24+'[5]Корсак В.І.'!I24+[5]Конякіна!I24 -> 0 | J24: ='[5]ПП ВДГ'!J24+'[5]Корсак Л.Р.'!J24+'[5]Корсак В.І.'!J24+[5]Конякіна!J24 -> 0 | K24: =SUM(I24:J24) -> 0 | L24: ='Солар Вест'!L24+Будник!L24 -> 0 | M24: ='Солар Вест'!M24+Будник!M24 -> 0 | N24: =SUM(L24:M24) -> 0 | O24: ='[5]ПП ВДГ'!O24+'[5]Корсак Л.Р.'!O24+'[5]Корсак В.І.'!O24+[5]Конякіна!O24 -> 0 | P24: ='[5]ПП ВДГ'!P24+'[5]Корсак Л.Р.'!P24+'[5]Корсак В.І.'!P24+[5]Конякіна!P24 -> 0 | Q24: =SUM(O24:P24) -> 0 | R24: ='Солар Вест'!R24+Будник!R24 -> 0 | S24: ='Солар Вест'!S24+Будник!S24 -> 0 | T24: =SUM(R24:S24) -> 0 | U24: ='[5]ПП ВДГ'!U24+'[5]Корсак Л.Р.'!U24+'[5]Корсак В.І.'!U24+[5]Конякіна!U24 -> 0 | V24: ='[5]ПП ВДГ'!V24+'[5]Корсак Л.Р.'!V24+'[5]Корсак В.І.'!V24+[5]Конякіна!V24 -> 0 | W24: =SUM(U24:V24) -> 0 | X24: ='Солар Вест'!X24+Будник!X24 -> 0 | Y24: ='Солар Вест'!Y24+Будник!Y24 -> 0 | Z24: =SUM(X24:Y24) -> 0 | AA24: ='[5]ПП ВДГ'!AA24+'[5]Корсак Л.Р.'!AA24+'[5]Корсак В.І.'!AA24+[5]Конякіна!AA24 -> 0 | AB24: ='[5]ПП ВДГ'!AB24+'[5]Корсак Л.Р.'!AB24+'[5]Корсак В.І.'!AB24+[5]Конякіна!AB24 -> 0 | AC24: =SUM(AA24:AB24) -> 0 | AD24: ='Солар Вест'!AD24+Будник!AD24 -> 0 | AE24: ='Солар Вест'!AE24+Будник!AE24 -> 0 | AF24: =SUM(AD24:AE24) -> 0 | AG24: ='[5]ПП ВДГ'!AG24+'[5]Корсак Л.Р.'!AG24+'[5]Корсак В.І.'!AG24+[5]Конякіна!AG24 -> 0 | AH24: ='[5]ПП ВДГ'!AH24+'[5]Корсак Л.Р.'!AH24+'[5]Корсак В.І.'!AH24+[5]Конякіна!AH24 -> 0 | AI24: =SUM(AG24:AH24) -> 0 | AJ24: ='Солар Вест'!AJ24+Будник!AJ24 -> 0 | AK24: ='Солар Вест'!AK24+Будник!AK24 -> 0 | AL24: =SUM(AJ24:AK24) -> 0 | AM24: ='[5]ПП ВДГ'!AM24+'[5]Корсак Л.Р.'!AM24+'[5]Корсак В.І.'!AM24+[5]Конякіна!AM24 -> 0 | AN24: ='[5]ПП ВДГ'!AN24+'[5]Корсак Л.Р.'!AN24+'[5]Корсак В.І.'!AN24+[5]Конякіна!AN24 -> 0 | AO24: =SUM(AM24:AN24) -> 0 | AP24: ='Солар Вест'!AP24+Будник!AP24 -> 0 | AQ24: ='Солар Вест'!AQ24+Будник!AQ24 -> 0 | AR24: =SUM(AP24:AQ24) -> 0 | AS24: ='[5]ПП ВДГ'!AS24+'[5]Корсак Л.Р.'!AS24+'[5]Корсак В.І.'!AS24+[5]Конякіна!AS24 -> 0 | AT24: ='[5]ПП ВДГ'!AT24+'[5]Корсак Л.Р.'!AT24+'[5]Корсак В.І.'!AT24+[5]Конякіна!AT24 -> 0 | AU24: =SUM(AS24:AT24) -> 0 | AV24: ='Солар Вест'!AV24+Будник!AV24 -> 0 | AW24: ='Солар Вест'!AW24+Будник!AW24 -> 2500 | AX24: =SUM(AV24:AW24) -> 2500 | AY24: ='[5]ПП ВДГ'!AY24+'[5]Корсак Л.Р.'!AY24+'[5]Корсак В.І.'!AY24+[5]Конякіна!AY24 -> 0 | AZ24: ='[5]ПП ВДГ'!AZ24+'[5]Корсак Л.Р.'!AZ24+'[5]Корсак В.І.'!AZ24+[5]Конякіна!AZ24 -> 0 | BA24: =SUM(AY24:AZ24) -> 0 | BB24: ='Солар Вест'!BB24+Будник!BB24 -> 0 | BC24: ='Солар Вест'!BC24+Будник!BC24 -> 500 | BD24: =SUM(BB24:BC24) -> 500 | BE24: ='Солар Вест'!BE24+Будник!BE24 -> 0 | BF24: ='Солар Вест'!BF24+Будник!BF24 -> 0 | BG24: =SUM(BE24:BF24) -> 0 | BH24: ='Солар Вест'!BH24+Будник!BH24 -> 0 | BI24: ='Солар Вест'!BI24+Будник!BI24 -> 0 | BJ24: =SUM(BH24:BI24) -> 0 | BK24: ='[5]ПП ВДГ'!BK24+'[5]Корсак Л.Р.'!BK24+'[5]Корсак В.І.'!BK24+[5]Конякіна!BK24 -> 0 | BL24: ='[5]ПП ВДГ'!BL24+'[5]Корсак Л.Р.'!BL24+'[5]Корсак В.І.'!BL24+[5]Конякіна!BL24 -> 0 | BM24: =SUM(BK24:BL24) -> 0 | BN24: ='Солар Вест'!BN24+Будник!BN24 -> 0 | BO24: ='Солар Вест'!BO24+Будник!BO24 -> 0 | BP24: =SUM(BN24:BO24) -> 0 | BQ24: ='[5]ПП ВДГ'!BQ24+'[5]Корсак Л.Р.'!BQ24+'[5]Корсак В.І.'!BQ24+[5]Конякіна!BQ24 -> 0 | BR24: ='[5]ПП ВДГ'!BR24+'[5]Корсак Л.Р.'!BR24+'[5]Корсак В.І.'!BR24+[5]Конякіна!BR24 -> 0 | BS24: =SUM(BQ24:BR24) -> 0 | BT24: ='Солар Вест'!BT24+Будник!BT24 -> 0 | BU24: ='Солар Вест'!BU24+Будник!BU24 -> 0 | BV24: =SUM(BT24:BU24) -> 0 | BW24: =+C24+I24+O24+AA24+AG24+U24+AM24+AS24+AY24+BE24+BK24+BQ24 -> 0 | BX24: =+D24+J24+P24+AB24+AH24+V24+AN24+AT24+AZ24+BF24+BL24+BR24 -> 0 | BY24: =SUM(BW24:BX24) -> 0 | BZ24: =+F24+L24+R24+AD24+AJ24+X24+AP24+AV24+BB24+BH24+BN24+BT24 -> 0 | CA24: =+G24+M24+S24+AE24+AK24+Y24+AQ24+AW24+BC24+BI24+BO24+BU24 -> 3000 | CB24: =SUM(BZ24:CA24) -> 3000
B25: в т.ч. внутрішньогрупове повернення фінансових позик | C25: ='[5]ПП ВДГ'!C25+'[5]Корсак Л.Р.'!C25+'[5]Корсак В.І.'!C25+[5]Конякіна!C25 -> 0 | D25: ='[5]ПП ВДГ'!D25+'[5]Корсак Л.Р.'!D25+'[5]Корсак В.І.'!D25+[5]Конякіна!D25 -> 0 | E25: =SUM(C25:D25) -> 0 | F25: ='Солар Вест'!F25+Будник!F25 -> 0 | G25: ='Солар Вест'!G25+Будник!G25 -> 0 | H25: =SUM(F25:G25) -> 0 | I25: ='[5]ПП ВДГ'!I25+'[5]Корсак Л.Р.'!I25+'[5]Корсак В.І.'!I25+[5]Конякіна!I25 -> 0 | J25: ='[5]ПП ВДГ'!J25+'[5]Корсак Л.Р.'!J25+'[5]Корсак В.І.'!J25+[5]Конякіна!J25 -> 0 | K25: =SUM(I25:J25) -> 0 | L25: ='Солар Вест'!L25+Будник!L25 -> 0 | M25: ='Солар Вест'!M25+Будник!M25 -> 0 | N25: =SUM(L25:M25) -> 0 | O25: ='[5]ПП ВДГ'!O25+'[5]Корсак Л.Р.'!O25+'[5]Корсак В.І.'!O25+[5]Конякіна!O25 -> 0 | P25: ='[5]ПП ВДГ'!P25+'[5]Корсак Л.Р.'!P25+'[5]Корсак В.І.'!P25+[5]Конякіна!P25 -> 0 | Q25: =SUM(O25:P25) -> 0 | R25: ='Солар Вест'!R25+Будник!R25 -> 0 | S25: ='Солар Вест'!S25+Будник!S25 -> 0 | T25: =SUM(R25:S25) -> 0 | U25: ='[5]ПП ВДГ'!U25+'[5]Корсак Л.Р.'!U25+'[5]Корсак В.І.'!U25+[5]Конякіна!U25 -> 0 | V25: ='[5]ПП ВДГ'!V25+'[5]Корсак Л.Р.'!V25+'[5]Корсак В.І.'!V25+[5]Конякіна!V25 -> 0 | W25: =SUM(U25:V25) -> 0 | X25: ='Солар Вест'!X25+Будник!X25 -> 0 | Y25: ='Солар Вест'!Y25+Будник!Y25 -> 0 | Z25: =SUM(X25:Y25) -> 0 | AA25: ='[5]ПП ВДГ'!AA25+'[5]Корсак Л.Р.'!AA25+'[5]Корсак В.І.'!AA25+[5]Конякіна!AA25 -> 0 | AB25: ='[5]ПП ВДГ'!AB25+'[5]Корсак Л.Р.'!AB25+'[5]Корсак В.І.'!AB25+[5]Конякіна!AB25 -> 0 | AC25: =SUM(AA25:AB25) -> 0 | AD25: ='Солар Вест'!AD25+Будник!AD25 -> 0 | AE25: ='Солар Вест'!AE25+Будник!AE25 -> 0 | AF25: =SUM(AD25:AE25) -> 0 | AG25: ='[5]ПП ВДГ'!AG25+'[5]Корсак Л.Р.'!AG25+'[5]Корсак В.І.'!AG25+[5]Конякіна!AG25 -> 0 | AH25: ='[5]ПП ВДГ'!AH25+'[5]Корсак Л.Р.'!AH25+'[5]Корсак В.І.'!AH25+[5]Конякіна!AH25 -> 0 | AI25: =SUM(AG25:AH25) -> 0 | AJ25: ='Солар Вест'!AJ25+Будник!AJ25 -> 0 | AK25: ='Солар Вест'!AK25+Будник!AK25 -> 0 | AL25: =SUM(AJ25:AK25) -> 0 | AM25: ='[5]ПП ВДГ'!AM25+'[5]Корсак Л.Р.'!AM25+'[5]Корсак В.І.'!AM25+[5]Конякіна!AM25 -> 0 | AN25: ='[5]ПП ВДГ'!AN25+'[5]Корсак Л.Р.'!AN25+'[5]Корсак В.І.'!AN25+[5]Конякіна!AN25 -> 0 | AO25: =SUM(AM25:AN25) -> 0 | AP25: ='Солар Вест'!AP25+Будник!AP25 -> 0 | AQ25: ='Солар Вест'!AQ25+Будник!AQ25 -> 0 | AR25: =SUM(AP25:AQ25) -> 0 | AS25: ='[5]ПП ВДГ'!AS25+'[5]Корсак Л.Р.'!AS25+'[5]Корсак В.І.'!AS25+[5]Конякіна!AS25 -> 0 | AT25: ='[5]ПП ВДГ'!AT25+'[5]Корсак Л.Р.'!AT25+'[5]Корсак В.І.'!AT25+[5]Конякіна!AT25 -> 0 | AU25: =SUM(AS25:AT25) -> 0 | AV25: ='Солар Вест'!AV25+Будник!AV25 -> 0 | AW25: ='Солар Вест'!AW25+Будник!AW25 -> 0 | AX25: =SUM(AV25:AW25) -> 0 | AY25: ='[5]ПП ВДГ'!AY25+'[5]Корсак Л.Р.'!AY25+'[5]Корсак В.І.'!AY25+[5]Конякіна!AY25 -> 0 | AZ25: ='[5]ПП ВДГ'!AZ25+'[5]Корсак Л.Р.'!AZ25+'[5]Корсак В.І.'!AZ25+[5]Конякіна!AZ25 -> 0 | BA25: =SUM(AY25:AZ25) -> 0 | BB25: ='Солар Вест'!BB25+Будник!BB25 -> 0 | BC25: ='Солар Вест'!BC25+Будник!BC25 -> 0 | BD25: =SUM(BB25:BC25) -> 0 | BE25: ='Солар Вест'!BE25+Будник!BE25 -> 0 | BF25: ='Солар Вест'!BF25+Будник!BF25 -> 0 | BG25: =SUM(BE25:BF25) -> 0 | BH25: ='Солар Вест'!BH25+Будник!BH25 -> 0 | BI25: ='Солар Вест'!BI25+Будник!BI25 -> 0 | BJ25: =SUM(BH25:BI25) -> 0 | BK25: ='[5]ПП ВДГ'!BK25+'[5]Корсак Л.Р.'!BK25+'[5]Корсак В.І.'!BK25+[5]Конякіна!BK25 -> 0 | BL25: ='[5]ПП ВДГ'!BL25+'[5]Корсак Л.Р.'!BL25+'[5]Корсак В.І.'!BL25+[5]Конякіна!BL25 -> 0 | BM25: =SUM(BK25:BL25) -> 0 | BN25: ='Солар Вест'!BN25+Будник!BN25 -> 0 | BO25: ='Солар Вест'!BO25+Будник!BO25 -> 0 | BP25: =SUM(BN25:BO25) -> 0 | BQ25: ='[5]ПП ВДГ'!BQ25+'[5]Корсак Л.Р.'!BQ25+'[5]Корсак В.І.'!BQ25+[5]Конякіна!BQ25 -> 0 | BR25: ='[5]ПП ВДГ'!BR25+'[5]Корсак Л.Р.'!BR25+'[5]Корсак В.І.'!BR25+[5]Конякіна!BR25 -> 0 | BS25: =SUM(BQ25:BR25) -> 0 | BT25: ='Солар Вест'!BT25+Будник!BT25 -> 0 | BU25: ='Солар Вест'!BU25+Будник!BU25 -> 0 | BV25: =SUM(BT25:BU25) -> 0 | BW25: =+C25+I25+O25+AA25+AG25+U25+AM25+AS25+AY25+BE25+BK25+BQ25 -> 0 | BX25: =+D25+J25+P25+AB25+AH25+V25+AN25+AT25+AZ25+BF25+BL25+BR25 -> 0 | BY25: =SUM(BW25:BX25) -> 0 | BZ25: =+F25+L25+R25+AD25+AJ25+X25+AP25+AV25+BB25+BH25+BN25+BT25 -> 0 | CA25: =+G25+M25+S25+AE25+AK25+Y25+AQ25+AW25+BC25+BI25+BO25+BU25 -> 0 | CB25: =SUM(BZ25:CA25) -> 0
A26: 214 | B26: Інші фінасові доходи (по ЦП, депозитах, дивідендах, внески) | C26: ='[5]ПП ВДГ'!C26+'[5]Корсак Л.Р.'!C26+'[5]Корсак В.І.'!C26+[5]Конякіна!C26 -> 0 | D26: ='[5]ПП ВДГ'!D26+'[5]Корсак Л.Р.'!D26+'[5]Корсак В.І.'!D26+[5]Конякіна!D26 -> 0 | E26: =SUM(C26:D26) -> 0 | F26: ='Солар Вест'!F26+Будник!F26 -> 0 | G26: ='Солар Вест'!G26+Будник!G26 -> 0 | H26: =SUM(F26:G26) -> 0 | I26: ='[5]ПП ВДГ'!I26+'[5]Корсак Л.Р.'!I26+'[5]Корсак В.І.'!I26+[5]Конякіна!I26 -> 0 | J26: ='[5]ПП ВДГ'!J26+'[5]Корсак Л.Р.'!J26+'[5]Корсак В.І.'!J26+[5]Конякіна!J26 -> 0 | K26: =SUM(I26:J26) -> 0 | L26: ='Солар Вест'!L26+Будник!L26 -> 0 | M26: ='Солар Вест'!M26+Будник!M26 -> 0 | N26: =SUM(L26:M26) -> 0 | O26: ='[5]ПП ВДГ'!O26+'[5]Корсак Л.Р.'!O26+'[5]Корсак В.І.'!O26+[5]Конякіна!O26 -> 0 | P26: ='[5]ПП ВДГ'!P26+'[5]Корсак Л.Р.'!P26+'[5]Корсак В.І.'!P26+[5]Конякіна!P26 -> 0 | Q26: =SUM(O26:P26) -> 0 | R26: ='Солар Вест'!R26+Будник!R26 -> 250000 | S26: ='Солар Вест'!S26+Будник!S26 -> 0 | T26: =SUM(R26:S26) -> 250000 | U26: ='[5]ПП ВДГ'!U26+'[5]Корсак Л.Р.'!U26+'[5]Корсак В.І.'!U26+[5]Конякіна!U26 -> 0 | V26: ='[5]ПП ВДГ'!V26+'[5]Корсак Л.Р.'!V26+'[5]Корсак В.І.'!V26+[5]Конякіна!V26 -> 0 | W26: =SUM(U26:V26) -> 0 | X26: ='Солар Вест'!X26+Будник!X26 -> 0 | Y26: ='Солар Вест'!Y26+Будник!Y26 -> 0 | Z26: =SUM(X26:Y26) -> 0 | AA26: ='[5]ПП ВДГ'!AA26+'[5]Корсак Л.Р.'!AA26+'[5]Корсак В.І.'!AA26+[5]Конякіна!AA26 -> 0 | AB26: ='[5]ПП ВДГ'!AB26+'[5]Корсак Л.Р.'!AB26+'[5]Корсак В.І.'!AB26+[5]Конякіна!AB26 -> 0 | AC26: =SUM(AA26:AB26) -> 0 | AD26: ='Солар Вест'!AD26+Будник!AD26 -> 1093.33 | AE26: ='Солар Вест'!AE26+Будник!AE26 -> 0 | AF26: =SUM(AD26:AE26) -> 1093.33 | AG26: ='[5]ПП ВДГ'!AG26+'[5]Корсак Л.Р.'!AG26+'[5]Корсак В.І.'!AG26+[5]Конякіна!AG26 -> 0 | AH26: ='[5]ПП ВДГ'!AH26+'[5]Корсак Л.Р.'!AH26+'[5]Корсак В.І.'!AH26+[5]Конякіна!AH26 -> 0 | AI26: =SUM(AG26:AH26) -> 0 | AJ26: ='Солар Вест'!AJ26+Будник!AJ26 -> 0 | AK26: ='Солар Вест'!AK26+Будник!AK26 -> 0 | AL26: =SUM(AJ26:AK26) -> 0 | AM26: ='[5]ПП ВДГ'!AM26+'[5]Корсак Л.Р.'!AM26+'[5]Корсак В.І.'!AM26+[5]Конякіна!AM26 -> 0 | AN26: ='[5]ПП ВДГ'!AN26+'[5]Корсак Л.Р.'!AN26+'[5]Корсак В.І.'!AN26+[5]Конякіна!AN26 -> 0 | AO26: =SUM(AM26:AN26) -> 0 | AP26: ='Солар Вест'!AP26+Будник!AP26 -> 0 | AQ26: ='Солар Вест'!AQ26+Будник!AQ26 -> 0 | AR26: =SUM(AP26:AQ26) -> 0 | AS26: ='[5]ПП ВДГ'!AS26+'[5]Корсак Л.Р.'!AS26+'[5]Корсак В.І.'!AS26+[5]Конякіна!AS26 -> 0 | AT26: ='[5]ПП ВДГ'!AT26+'[5]Корсак Л.Р.'!AT26+'[5]Корсак В.І.'!AT26+[5]Конякіна!AT26 -> 0 | AU26: =SUM(AS26:AT26) -> 0 | AV26: ='Солар Вест'!AV26+Будник!AV26 -> 0 | AW26: ='Солар Вест'!AW26+Будник!AW26 -> 0 | AX26: =SUM(AV26:AW26) -> 0 | AY26: ='[5]ПП ВДГ'!AY26+'[5]Корсак Л.Р.'!AY26+'[5]Корсак В.І.'!AY26+[5]Конякіна!AY26 -> 0 | AZ26: ='[5]ПП ВДГ'!AZ26+'[5]Корсак Л.Р.'!AZ26+'[5]Корсак В.І.'!AZ26+[5]Конякіна!AZ26 -> 0 | BA26: =SUM(AY26:AZ26) -> 0 | BB26: ='Солар Вест'!BB26+Будник!BB26 -> 0 | BC26: ='Солар Вест'!BC26+Будник!BC26 -> 0 | BD26: =SUM(BB26:BC26) -> 0 | BE26: ='Солар Вест'!BE26+Будник!BE26 -> 0 | BF26: ='Солар Вест'!BF26+Будник!BF26 -> 0 | BG26: =SUM(BE26:BF26) -> 0 | BH26: ='Солар Вест'!BH26+Будник!BH26 -> 0 | BI26: ='Солар Вест'!BI26+Будник!BI26 -> 0 | BJ26: =SUM(BH26:BI26) -> 0 | BK26: ='[5]ПП ВДГ'!BK26+'[5]Корсак Л.Р.'!BK26+'[5]Корсак В.І.'!BK26+[5]Конякіна!BK26 -> 0 | BL26: ='[5]ПП ВДГ'!BL26+'[5]Корсак Л.Р.'!BL26+'[5]Корсак В.І.'!BL26+[5]Конякіна!BL26 -> 0 | BM26: =SUM(BK26:BL26) -> 0 | BN26: ='Солар Вест'!BN26+Будник!BN26 -> 0 | BO26: ='Солар Вест'!BO26+Будник!BO26 -> 0 | BP26: =SUM(BN26:BO26) -> 0 | BQ26: ='[5]ПП ВДГ'!BQ26+'[5]Корсак Л.Р.'!BQ26+'[5]Корсак В.І.'!BQ26+[5]Конякіна!BQ26 -> 0 | BR26: ='[5]ПП ВДГ'!BR26+'[5]Корсак Л.Р.'!BR26+'[5]Корсак В.І.'!BR26+[5]Конякіна!BR26 -> 0 | BS26: =SUM(BQ26:BR26) -> 0 | BT26: ='Солар Вест'!BT26+Будник!BT26 -> 0 | BU26: ='Солар Вест'!BU26+Будник!BU26 -> 0 | BV26: =SUM(BT26:BU26) -> 0 | BW26: =+C26+I26+O26+AA26+AG26+U26+AM26+AS26+AY26+BE26+BK26+BQ26 -> 0 | BX26: =+D26+J26+P26+AB26+AH26+V26+AN26+AT26+AZ26+BF26+BL26+BR26 -> 0 | BY26: =SUM(BW26:BX26) -> 0 | BZ26: =+F26+L26+R26+AD26+AJ26+X26+AP26+AV26+BB26+BH26+BN26+BT26 -> 251093.33 | CA26: =+G26+M26+S26+AE26+AK26+Y26+AQ26+AW26+BC26+BI26+BO26+BU26 -> 0 | CB26: =SUM(BZ26:CA26) -> 251093.33
A27: 311 | B27: Реалізація необоротних активів | C27: ='[5]ПП ВДГ'!C27+'[5]Корсак Л.Р.'!C27+'[5]Корсак В.І.'!C27+[5]Конякіна!C27 -> 0 | D27: ='[5]ПП ВДГ'!D27+'[5]Корсак Л.Р.'!D27+'[5]Корсак В.І.'!D27+[5]Конякіна!D27 -> 0 | E27: =SUM(C27:D27) -> 0 | F27: ='Солар Вест'!F27+Будник!F27 -> 0 | G27: ='Солар Вест'!G27+Будник!G27 -> 0 | H27: =SUM(F27:G27) -> 0 | I27: ='[5]ПП ВДГ'!I27+'[5]Корсак Л.Р.'!I27+'[5]Корсак В.І.'!I27+[5]Конякіна!I27 -> 0 | J27: ='[5]ПП ВДГ'!J27+'[5]Корсак Л.Р.'!J27+'[5]Корсак В.І.'!J27+[5]Конякіна!J27 -> 0 | K27: =SUM(I27:J27) -> 0 | L27: ='Солар Вест'!L27+Будник!L27 -> 0 | M27: ='Солар Вест'!M27+Будник!M27 -> 0 | N27: =SUM(L27:M27) -> 0 | O27: ='[5]ПП ВДГ'!O27+'[5]Корсак Л.Р.'!O27+'[5]Корсак В.І.'!O27+[5]Конякіна!O27 -> 0 | P27: ='[5]ПП ВДГ'!P27+'[5]Корсак Л.Р.'!P27+'[5]Корсак В.І.'!P27+[5]Конякіна!P27 -> 0 | Q27: =SUM(O27:P27) -> 0 | R27: ='Солар Вест'!R27+Будник!R27 -> 0 | S27: ='Солар Вест'!S27+Будник!S27 -> 0 | T27: =SUM(R27:S27) -> 0 | U27: ='[5]ПП ВДГ'!U27+'[5]Корсак Л.Р.'!U27+'[5]Корсак В.І.'!U27+[5]Конякіна!U27 -> 0 | V27: ='[5]ПП ВДГ'!V27+'[5]Корсак Л.Р.'!V27+'[5]Корсак В.І.'!V27+[5]Конякіна!V27 -> 0 | W27: =SUM(U27:V27) -> 0 | X27: ='Солар Вест'!X27+Будник!X27 -> 0 | Y27: ='Солар Вест'!Y27+Будник!Y27 -> 0 | Z27: =SUM(X27:Y27) -> 0 | AA27: ='[5]ПП ВДГ'!AA27+'[5]Корсак Л.Р.'!AA27+'[5]Корсак В.І.'!AA27+[5]Конякіна!AA27 -> 0 | AB27: ='[5]ПП ВДГ'!AB27+'[5]Корсак Л.Р.'!AB27+'[5]Корсак В.І.'!AB27+[5]Конякіна!AB27 -> 0 | AC27: =SUM(AA27:AB27) -> 0 | AD27: ='Солар Вест'!AD27+Будник!AD27 -> 0 | AE27: ='Солар Вест'!AE27+Будник!AE27 -> 0 | AF27: =SUM(AD27:AE27) -> 0 | AG27: ='[5]ПП ВДГ'!AG27+'[5]Корсак Л.Р.'!AG27+'[5]Корсак В.І.'!AG27+[5]Конякіна!AG27 -> 0 | AH27: ='[5]ПП ВДГ'!AH27+'[5]Корсак Л.Р.'!AH27+'[5]Корсак В.І.'!AH27+[5]Конякіна!AH27 -> 0 | AI27: =SUM(AG27:AH27) -> 0 | AJ27: ='Солар Вест'!AJ27+Будник!AJ27 -> 0 | AK27: ='Солар Вест'!AK27+Будник!AK27 -> 0 | AL27: =SUM(AJ27:AK27) -> 0 | AM27: ='[5]ПП ВДГ'!AM27+'[5]Корсак Л.Р.'!AM27+'[5]Корсак В.І.'!AM27+[5]Конякіна!AM27 -> 0 | AN27: ='[5]ПП ВДГ'!AN27+'[5]Корсак Л.Р.'!AN27+'[5]Корсак В.І.'!AN27+[5]Конякіна!AN27 -> 0 | AO27: =SUM(AM27:AN27) -> 0 | AP27: ='Солар Вест'!AP27+Будник!AP27 -> 0 | AQ27: ='Солар Вест'!AQ27+Будник!AQ27 -> 0 | AR27: =SUM(AP27:AQ27) -> 0 | AS27: ='[5]ПП ВДГ'!AS27+'[5]Корсак Л.Р.'!AS27+'[5]Корсак В.І.'!AS27+[5]Конякіна!AS27 -> 0 | AT27: ='[5]ПП ВДГ'!AT27+'[5]Корсак Л.Р.'!AT27+'[5]Корсак В.І.'!AT27+[5]Конякіна!AT27 -> 0 | AU27: =SUM(AS27:AT27) -> 0 | AV27: ='Солар Вест'!AV27+Будник!AV27 -> 0 | AW27: ='Солар Вест'!AW27+Будник!AW27 -> 0 | AX27: =SUM(AV27:AW27) -> 0 | AY27: ='[5]ПП ВДГ'!AY27+'[5]Корсак Л.Р.'!AY27+'[5]Корсак В.І.'!AY27+[5]Конякіна!AY27 -> 0 | AZ27: ='[5]ПП ВДГ'!AZ27+'[5]Корсак Л.Р.'!AZ27+'[5]Корсак В.І.'!AZ27+[5]Конякіна!AZ27 -> 0 | BA27: =SUM(AY27:AZ27) -> 0 | BB27: ='Солар Вест'!BB27+Будник!BB27 -> 0 | BC27: ='Солар Вест'!BC27+Будник!BC27 -> 0 | BD27: =SUM(BB27:BC27) -> 0 | BE27: ='Солар Вест'!BE27+Будник!BE27 -> 0 | BF27: ='Солар Вест'!BF27+Будник!BF27 -> 0 | BG27: =SUM(BE27:BF27) -> 0 | BH27: ='Солар Вест'!BH27+Будник!BH27 -> 0 | BI27: ='Солар Вест'!BI27+Будник!BI27 -> 0 | BJ27: =SUM(BH27:BI27) -> 0 | BK27: ='[5]ПП ВДГ'!BK27+'[5]Корсак Л.Р.'!BK27+'[5]Корсак В.І.'!BK27+[5]Конякіна!BK27 -> 0 | BL27: ='[5]ПП ВДГ'!BL27+'[5]Корсак Л.Р.'!BL27+'[5]Корсак В.І.'!BL27+[5]Конякіна!BL27 -> 0 | BM27: =SUM(BK27:BL27) -> 0 | BN27: ='Солар Вест'!BN27+Будник!BN27 -> 0 | BO27: ='Солар Вест'!BO27+Будник!BO27 -> 0 | BP27: =SUM(BN27:BO27) -> 0 | BQ27: ='[5]ПП ВДГ'!BQ27+'[5]Корсак Л.Р.'!BQ27+'[5]Корсак В.І.'!BQ27+[5]Конякіна!BQ27 -> 0 | BR27: ='[5]ПП ВДГ'!BR27+'[5]Корсак Л.Р.'!BR27+'[5]Корсак В.І.'!BR27+[5]Конякіна!BR27 -> 0 | BS27: =SUM(BQ27:BR27) -> 0 | BT27: ='Солар Вест'!BT27+Будник!BT27 -> 0 | BU27: ='Солар Вест'!BU27+Будник!BU27 -> 0 | BV27: =SUM(BT27:BU27) -> 0 | BW27: =+C27+I27+O27+AA27+AG27+U27+AM27+AS27+AY27+BE27+BK27+BQ27 -> 0 | BX27: =+D27+J27+P27+AB27+AH27+V27+AN27+AT27+AZ27+BF27+BL27+BR27 -> 0 | BY27: =SUM(BW27:BX27) -> 0 | BZ27: =+F27+L27+R27+AD27+AJ27+X27+AP27+AV27+BB27+BH27+BN27+BT27 -> 0 | CA27: =+G27+M27+S27+AE27+AK27+Y27+AQ27+AW27+BC27+BI27+BO27+BU27 -> 0 | CB27: =SUM(BZ27:CA27) -> 0
A28: 318 | B28: Доходи від фінансових інвестицій | C28: ='[5]ПП ВДГ'!C28+'[5]Корсак Л.Р.'!C28+'[5]Корсак В.І.'!C28+[5]Конякіна!C28 -> 0 | D28: ='[5]ПП ВДГ'!D28+'[5]Корсак Л.Р.'!D28+'[5]Корсак В.І.'!D28+[5]Конякіна!D28 -> 0 | E28: =SUM(C28:D28) -> 0 | F28: ='Солар Вест'!F28+Будник!F28 -> 0 | G28: ='Солар Вест'!G28+Будник!G28 -> 0 | H28: =SUM(F28:G28) -> 0 | I28: ='[5]ПП ВДГ'!I28+'[5]Корсак Л.Р.'!I28+'[5]Корсак В.І.'!I28+[5]Конякіна!I28 -> 0 | J28: ='[5]ПП ВДГ'!J28+'[5]Корсак Л.Р.'!J28+'[5]Корсак В.І.'!J28+[5]Конякіна!J28 -> 0 | K28: =SUM(I28:J28) -> 0 | L28: ='Солар Вест'!L28+Будник!L28 -> 0 | M28: ='Солар Вест'!M28+Будник!M28 -> 0 | N28: =SUM(L28:M28) -> 0 | O28: ='[5]ПП ВДГ'!O28+'[5]Корсак Л.Р.'!O28+'[5]Корсак В.І.'!O28+[5]Конякіна!O28 -> 0 | P28: ='[5]ПП ВДГ'!P28+'[5]Корсак Л.Р.'!P28+'[5]Корсак В.І.'!P28+[5]Конякіна!P28 -> 0 | Q28: =SUM(O28:P28) -> 0 | R28: ='Солар Вест'!R28+Будник!R28 -> 0 | S28: ='Солар Вест'!S28+Будник!S28 -> 0 | T28: =SUM(R28:S28) -> 0 | U28: ='[5]ПП ВДГ'!U28+'[5]Корсак Л.Р.'!U28+'[5]Корсак В.І.'!U28+[5]Конякіна!U28 -> 0 | V28: ='[5]ПП ВДГ'!V28+'[5]Корсак Л.Р.'!V28+'[5]Корсак В.І.'!V28+[5]Конякіна!V28 -> 0 | W28: =SUM(U28:V28) -> 0 | X28: ='Солар Вест'!X28+Будник!X28 -> 0 | Y28: ='Солар Вест'!Y28+Будник!Y28 -> 0 | Z28: =SUM(X28:Y28) -> 0 | AA28: ='[5]ПП ВДГ'!AA28+'[5]Корсак Л.Р.'!AA28+'[5]Корсак В.І.'!AA28+[5]Конякіна!AA28 -> 0 | AB28: ='[5]ПП ВДГ'!AB28+'[5]Корсак Л.Р.'!AB28+'[5]Корсак В.І.'!AB28+[5]Конякіна!AB28 -> 0 | AC28: =SUM(AA28:AB28) -> 0 | AD28: ='Солар Вест'!AD28+Будник!AD28 -> 0 | AE28: ='Солар Вест'!AE28+Будник!AE28 -> 0 | AF28: =SUM(AD28:AE28) -> 0 | AG28: ='[5]ПП ВДГ'!AG28+'[5]Корсак Л.Р.'!AG28+'[5]Корсак В.І.'!AG28+[5]Конякіна!AG28 -> 0 | AH28: ='[5]ПП ВДГ'!AH28+'[5]Корсак Л.Р.'!AH28+'[5]Корсак В.І.'!AH28+[5]Конякіна!AH28 -> 0 | AI28: =SUM(AG28:AH28) -> 0 | AJ28: ='Солар Вест'!AJ28+Будник!AJ28 -> 0 | AK28: ='Солар Вест'!AK28+Будник!AK28 -> 0 | AL28: =SUM(AJ28:AK28) -> 0 | AM28: ='[5]ПП ВДГ'!AM28+'[5]Корсак Л.Р.'!AM28+'[5]Корсак В.І.'!AM28+[5]Конякіна!AM28 -> 0 | AN28: ='[5]ПП ВДГ'!AN28+'[5]Корсак Л.Р.'!AN28+'[5]Корсак В.І.'!AN28+[5]Конякіна!AN28 -> 0 | AO28: =SUM(AM28:AN28) -> 0 | AP28: ='Солар Вест'!AP28+Будник!AP28 -> 0 | AQ28: ='Солар Вест'!AQ28+Будник!AQ28 -> 0 | AR28: =SUM(AP28:AQ28) -> 0 | AS28: ='[5]ПП ВДГ'!AS28+'[5]Корсак Л.Р.'!AS28+'[5]Корсак В.І.'!AS28+[5]Конякіна!AS28 -> 0 | AT28: ='[5]ПП ВДГ'!AT28+'[5]Корсак Л.Р.'!AT28+'[5]Корсак В.І.'!AT28+[5]Конякіна!AT28 -> 0 | AU28: =SUM(AS28:AT28) -> 0 | AV28: ='Солар Вест'!AV28+Будник!AV28 -> 0 | AW28: ='Солар Вест'!AW28+Будник!AW28 -> 0 | AX28: =SUM(AV28:AW28) -> 0 | AY28: ='[5]ПП ВДГ'!AY28+'[5]Корсак Л.Р.'!AY28+'[5]Корсак В.І.'!AY28+[5]Конякіна!AY28 -> 0 | AZ28: ='[5]ПП ВДГ'!AZ28+'[5]Корсак Л.Р.'!AZ28+'[5]Корсак В.І.'!AZ28+[5]Конякіна!AZ28 -> 0 | BA28: =SUM(AY28:AZ28) -> 0 | BB28: ='Солар Вест'!BB28+Будник!BB28 -> 0 | BC28: ='Солар Вест'!BC28+Будник!BC28 -> 0 | BD28: =SUM(BB28:BC28) -> 0 | BE28: ='Солар Вест'!BE28+Будник!BE28 -> 0 | BF28: ='Солар Вест'!BF28+Будник!BF28 -> 0 | BG28: =SUM(BE28:BF28) -> 0 | BH28: ='Солар Вест'!BH28+Будник!BH28 -> 0 | BI28: ='Солар Вест'!BI28+Будник!BI28 -> 0 | BJ28: =SUM(BH28:BI28) -> 0 | BK28: ='[5]ПП ВДГ'!BK28+'[5]Корсак Л.Р.'!BK28+'[5]Корсак В.І.'!BK28+[5]Конякіна!BK28 -> 0 | BL28: ='[5]ПП ВДГ'!BL28+'[5]Корсак Л.Р.'!BL28+'[5]Корсак В.І.'!BL28+[5]Конякіна!BL28 -> 0 | BM28: =SUM(BK28:BL28) -> 0 | BN28: ='Солар Вест'!BN28+Будник!BN28 -> 0 | BO28: ='Солар Вест'!BO28+Будник!BO28 -> 0 | BP28: =SUM(BN28:BO28) -> 0 | BQ28: ='[5]ПП ВДГ'!BQ28+'[5]Корсак Л.Р.'!BQ28+'[5]Корсак В.І.'!BQ28+[5]Конякіна!BQ28 -> 0 | BR28: ='[5]ПП ВДГ'!BR28+'[5]Корсак Л.Р.'!BR28+'[5]Корсак В.І.'!BR28+[5]Конякіна!BR28 -> 0 | BS28: =SUM(BQ28:BR28) -> 0 | BT28: ='Солар Вест'!BT28+Будник!BT28 -> 0 | BU28: ='Солар Вест'!BU28+Будник!BU28 -> 0 | BV28: =SUM(BT28:BU28) -> 0 | BW28: =+C28+I28+O28+AA28+AG28+U28+AM28+AS28+AY28+BE28+BK28+BQ28 -> 0 | BX28: =+D28+J28+P28+AB28+AH28+V28+AN28+AT28+AZ28+BF28+BL28+BR28 -> 0 | BY28: =SUM(BW28:BX28) -> 0 | BZ28: =+F28+L28+R28+AD28+AJ28+X28+AP28+AV28+BB28+BH28+BN28+BT28 -> 0 | CA28: =+G28+M28+S28+AE28+AK28+Y28+AQ28+AW28+BC28+BI28+BO28+BU28 -> 0 | CB28: =SUM(BZ28:CA28) -> 0
A29: 319 | B29: Переміщення - прихід | C29: ='[5]ПП ВДГ'!C29+'[5]Корсак Л.Р.'!C29+'[5]Корсак В.І.'!C29+[5]Конякіна!C29 -> 0 | D29: ='[5]ПП ВДГ'!D29+'[5]Корсак Л.Р.'!D29+'[5]Корсак В.І.'!D29+[5]Конякіна!D29 -> 23000 | E29: =SUM(C29:D29) -> 23000 | F29: ='Солар Вест'!F29+Будник!F29 -> 0 | G29: ='Солар Вест'!G29+Будник!G29 -> 0 | H29: =SUM(F29:G29) -> 0 | I29: ='[5]ПП ВДГ'!I29+'[5]Корсак Л.Р.'!I29+'[5]Корсак В.І.'!I29+[5]Конякіна!I29 -> 0 | J29: ='[5]ПП ВДГ'!J29+'[5]Корсак Л.Р.'!J29+'[5]Корсак В.І.'!J29+[5]Конякіна!J29 -> 23000 | K29: =SUM(I29:J29) -> 23000 | L29: ='Солар Вест'!L29+Будник!L29 -> 6696268 | M29: ='Солар Вест'!M29+Будник!M29 -> 0 | N29: =SUM(L29:M29) -> 6696268 | O29: ='[5]ПП ВДГ'!O29+'[5]Корсак Л.Р.'!O29+'[5]Корсак В.І.'!O29+[5]Конякіна!O29 -> 15000 | P29: ='[5]ПП ВДГ'!P29+'[5]Корсак Л.Р.'!P29+'[5]Корсак В.І.'!P29+[5]Конякіна!P29 -> 23000 | Q29: =SUM(O29:P29) -> 38000 | R29: ='Солар Вест'!R29+Будник!R29 -> 348840 | S29: ='Солар Вест'!S29+Будник!S29 -> 0 | T29: =SUM(R29:S29) -> 348840 | U29: ='[5]ПП ВДГ'!U29+'[5]Корсак Л.Р.'!U29+'[5]Корсак В.І.'!U29+[5]Конякіна!U29 -> 120000 | V29: ='[5]ПП ВДГ'!V29+'[5]Корсак Л.Р.'!V29+'[5]Корсак В.І.'!V29+[5]Конякіна!V29 -> 17000 | W29: =SUM(U29:V29) -> 137000 | X29: ='Солар Вест'!X29+Будник!X29 -> 2000 | Y29: ='Солар Вест'!Y29+Будник!Y29 -> 0 | Z29: =SUM(X29:Y29) -> 2000 | AA29: ='[5]ПП ВДГ'!AA29+'[5]Корсак Л.Р.'!AA29+'[5]Корсак В.І.'!AA29+[5]Конякіна!AA29 -> 15000 | AB29: ='[5]ПП ВДГ'!AB29+'[5]Корсак Л.Р.'!AB29+'[5]Корсак В.І.'!AB29+[5]Конякіна!AB29 -> 21000 | AC29: =SUM(AA29:AB29) -> 36000 | AD29: ='Солар Вест'!AD29+Будник!AD29 -> 0 | AE29: ='Солар Вест'!AE29+Будник!AE29 -> 0 | AF29: =SUM(AD29:AE29) -> 0 | AG29: ='[5]ПП ВДГ'!AG29+'[5]Корсак Л.Р.'!AG29+'[5]Корсак В.І.'!AG29+[5]Конякіна!AG29 -> 12000 | AH29: ='[5]ПП ВДГ'!AH29+'[5]Корсак Л.Р.'!AH29+'[5]Корсак В.І.'!AH29+[5]Конякіна!AH29 -> 13000 | AI29: =SUM(AG29:AH29) -> 25000 | AJ29: ='Солар Вест'!AJ29+Будник!AJ29 -> 100000 | AK29: ='Солар Вест'!AK29+Будник!AK29 -> 0 | AL29: =SUM(AJ29:AK29) -> 100000 | AM29: ='[5]ПП ВДГ'!AM29+'[5]Корсак Л.Р.'!AM29+'[5]Корсак В.І.'!AM29+[5]Конякіна!AM29 -> 11000 | AN29: ='[5]ПП ВДГ'!AN29+'[5]Корсак Л.Р.'!AN29+'[5]Корсак В.І.'!AN29+[5]Конякіна!AN29 -> 13000 | AO29: =SUM(AM29:AN29) -> 24000 | AP29: ='Солар Вест'!AP29+Будник!AP29 -> 0 | AQ29: ='Солар Вест'!AQ29+Будник!AQ29 -> 0 | AR29: =SUM(AP29:AQ29) -> 0 | AS29: ='[5]ПП ВДГ'!AS29+'[5]Корсак Л.Р.'!AS29+'[5]Корсак В.І.'!AS29+[5]Конякіна!AS29 -> 15000 | AT29: ='[5]ПП ВДГ'!AT29+'[5]Корсак Л.Р.'!AT29+'[5]Корсак В.І.'!AT29+[5]Конякіна!AT29 -> 12000 | AU29: =SUM(AS29:AT29) -> 27000 | AV29: ='Солар Вест'!AV29+Будник!AV29 -> 69123.2 | AW29: ='Солар Вест'!AW29+Будник!AW29 -> 105000 | AX29: =SUM(AV29:AW29) -> 174123.2 | AY29: ='[5]ПП ВДГ'!AY29+'[5]Корсак Л.Р.'!AY29+'[5]Корсак В.І.'!AY29+[5]Конякіна!AY29 -> 15000 | AZ29: ='[5]ПП ВДГ'!AZ29+'[5]Корсак Л.Р.'!AZ29+'[5]Корсак В.І.'!AZ29+[5]Конякіна!AZ29 -> 21000 | BA29: =SUM(AY29:AZ29) -> 36000 | BB29: ='Солар Вест'!BB29+Будник!BB29 -> 54000 | BC29: ='Солар Вест'!BC29+Будник!BC29 -> 0 | BD29: =SUM(BB29:BC29) -> 54000 | BE29: ='Солар Вест'!BE29+Будник!BE29 -> 68500 | BF29: ='Солар Вест'!BF29+Будник!BF29 -> 8120 | BG29: =SUM(BE29:BF29) -> 76620 | BH29: ='Солар Вест'!BH29+Будник!BH29 -> 0 | BI29: ='Солар Вест'!BI29+Будник!BI29 -> 0 | BJ29: =SUM(BH29:BI29) -> 0 | BK29: ='[5]ПП ВДГ'!BK29+'[5]Корсак Л.Р.'!BK29+'[5]Корсак В.І.'!BK29+[5]Конякіна!BK29 -> 15000 | BL29: ='[5]ПП ВДГ'!BL29+'[5]Корсак Л.Р.'!BL29+'[5]Корсак В.І.'!BL29+[5]Конякіна!BL29 -> 23000 | BM29: =SUM(BK29:BL29) -> 38000 | BN29: ='Солар Вест'!BN29+Будник!BN29 -> 0 | BO29: ='Солар Вест'!BO29+Будник!BO29 -> 0 | BP29: =SUM(BN29:BO29) -> 0 | BQ29: ='[5]ПП ВДГ'!BQ29+'[5]Корсак Л.Р.'!BQ29+'[5]Корсак В.І.'!BQ29+[5]Конякіна!BQ29 -> 10000 | BR29: ='[5]ПП ВДГ'!BR29+'[5]Корсак Л.Р.'!BR29+'[5]Корсак В.І.'!BR29+[5]Конякіна!BR29 -> 13000 | BS29: =SUM(BQ29:BR29) -> 23000 | BT29: ='Солар Вест'!BT29+Будник!BT29 -> 0 | BU29: ='Солар Вест'!BU29+Будник!BU29 -> 0 | BV29: =SUM(BT29:BU29) -> 0 | BW29: =+C29+I29+O29+AA29+AG29+U29+AM29+AS29+AY29+BE29+BK29+BQ29 -> 296500 | BX29: =+D29+J29+P29+AB29+AH29+V29+AN29+AT29+AZ29+BF29+BL29+BR29 -> 210120 | BY29: =SUM(BW29:BX29) -> 506620 | BZ29: =+F29+L29+R29+AD29+AJ29+X29+AP29+AV29+BB29+BH29+BN29+BT29 -> 7270231.2 | CA29: =+G29+M29+S29+AE29+AK29+Y29+AQ29+AW29+BC29+BI29+BO29+BU29 -> 105000 | CB29: =SUM(BZ29:CA29) -> 7375231.2
B30: Всього | C30: =C12+C14+C16+C18+C20+C21+C22+C24+C26+C27+C28+C29 -> 175000 | D30: =D12+D14+D16+D18+D20+D21+D22+D24+D26+D27+D28+D29 -> 214000 | E30: =E12+E14+E16+E18+E20+E21+E22+E24+E26+E27+E28+E29 -> 389000 | F30: =F12+F14+F16+F18+F20+F21+F22+F24+F26+F27+F28+F29 -> 417791.1 | G30: =G12+G14+G16+G18+G20+G21+G22+G24+G26+G27+G28+G29 -> 232210 | H30: =H12+H14+H16+H18+H20+H21+H22+H24+H26+H27+H28+H29 -> 650001.1 | I30: =I12+I14+I16+I18+I20+I21+I22+I24+I26+I27+I28+I29 -> 175000 | J30: =J12+J14+J16+J18+J20+J21+J22+J24+J26+J27+J28+J29 -> 214000 | ... CB30: =CB12+CB14+CB16+CB18+CB20+CB21+CB22+CB24+CB26+CB27+CB28+CB29 -> 27762479
A31: Видатки
A32: 121 | B32: Закупка товарів (сировини) | C32: ='[5]ПП ВДГ'!C32+'[5]Корсак Л.Р.'!C32+'[5]Корсак В.І.'!C32+[5]Конякіна!C32 -> 0 | D32: ='[5]ПП ВДГ'!D32+'[5]Корсак Л.Р.'!D32+'[5]Корсак В.І.'!D32+[5]Конякіна!D32 -> 0 | E32: =SUM(C32:D32) -> 0 | F32: ='Солар Вест'!F32+Будник!F32 -> 418010.02 | G32: ='Солар Вест'!G32+Будник!G32 -> 831 | H32: =SUM(F32:G32) -> 418841.02 | I32: ='[5]ПП ВДГ'!I32+'[5]Корсак Л.Р.'!I32+'[5]Корсак В.І.'!I32+[5]Конякіна!I32 -> 0 | J32: ='[5]ПП ВДГ'!J32+'[5]Корсак Л.Р.'!J32+'[5]Корсак В.І.'!J32+[5]Конякіна!J32 -> 0 | K32: =SUM(I32:J32) -> 0 | L32: ='Солар Вест'!L32+Будник!L32 -> 543077.16 | M32: ='Солар Вест'!M32+Будник!M32 -> 1071 | N32: =SUM(L32:M32) -> 544148.16 | O32: ='[5]ПП ВДГ'!O32+'[5]Корсак Л.Р.'!O32+'[5]Корсак В.І.'!O32+[5]Конякіна!O32 -> 0 | P32: ='[5]ПП ВДГ'!P32+'[5]Корсак Л.Р.'!P32+'[5]Корсак В.І.'!P32+[5]Конякіна!P32 -> 0 | Q32: =SUM(O32:P32) -> 0 | R32: ='Солар Вест'!R32+Будник!R32 -> 4071799.3 | S32: ='Солар Вест'!S32+Будник!S32 -> 0 | T32: =SUM(R32:S32) -> 4071799.3 | U32: ='[5]ПП ВДГ'!U32+'[5]Корсак Л.Р.'!U32+'[5]Корсак В.І.'!U32+[5]Конякіна!U32 -> 0 | V32: ='[5]ПП ВДГ'!V32+'[5]Корсак Л.Р.'!V32+'[5]Корсак В.І.'!V32+[5]Конякіна!V32 -> 0 | W32: =SUM(U32:V32) -> 0 | X32: ='Солар Вест'!X32+Будник!X32 -> 1921223 | Y32: ='Солар Вест'!Y32+Будник!Y32 -> 0 | Z32: =SUM(X32:Y32) -> 1921223 | AA32: ='[5]ПП ВДГ'!AA32+'[5]Корсак Л.Р.'!AA32+'[5]Корсак В.І.'!AA32+[5]Конякіна!AA32 -> 0 | AB32: ='[5]ПП ВДГ'!AB32+'[5]Корсак Л.Р.'!AB32+'[5]Корсак В.І.'!AB32+[5]Конякіна!AB32 -> 0 | AC32: =SUM(AA32:AB32) -> 0 | AD32: ='Солар Вест'!AD32+Будник!AD32 -> 816349.37 | AE32: ='Солар Вест'!AE32+Будник!AE32 -> 0 | AF32: =SUM(AD32:AE32) -> 816349.37 | AG32: ='[5]ПП ВДГ'!AG32+'[5]Корсак Л.Р.'!AG32+'[5]Корсак В.І.'!AG32+[5]Конякіна!AG32 -> 0 | AH32: ='[5]ПП ВДГ'!AH32+'[5]Корсак Л.Р.'!AH32+'[5]Корсак В.І.'!AH32+[5]Конякіна!AH32 -> 0 | AI32: =SUM(AG32:AH32) -> 0 | AJ32: ='Солар Вест'!AJ32+Будник!AJ32 -> 4662456.7 | AK32: ='Солар Вест'!AK32+Будник!AK32 -> 0 | AL32: =SUM(AJ32:AK32) -> 4662456.7 | AM32: ='[5]ПП ВДГ'!AM32+'[5]Корсак Л.Р.'!AM32+'[5]Корсак В.І.'!AM32+[5]Конякіна!AM32 -> 0 | AN32: ='[5]ПП ВДГ'!AN32+'[5]Корсак Л.Р.'!AN32+'[5]Корсак В.І.'!AN32+[5]Конякіна!AN32 -> 0 | AO32: =SUM(AM32:AN32) -> 0 | AP32: ='Солар Вест'!AP32+Будник!AP32 -> 607458.15 | AQ32: ='Солар Вест'!AQ32+Будник!AQ32 -> 0 | AR32: =SUM(AP32:AQ32) -> 607458.15 | AS32: ='[5]ПП ВДГ'!AS32+'[5]Корсак Л.Р.'!AS32+'[5]Корсак В.І.'!AS32+[5]Конякіна!AS32 -> 0 | AT32: ='[5]ПП ВДГ'!AT32+'[5]Корсак Л.Р.'!AT32+'[5]Корсак В.І.'!AT32+[5]Конякіна!AT32 -> 0 | AU32: =SUM(AS32:AT32) -> 0 | AV32: ='Солар Вест'!AV32+Будник!AV32 -> 475720.1 | AW32: ='Солар Вест'!AW32+Будник!AW32 -> 85388 | AX32: =SUM(AV32:AW32) -> 561108.1 | AY32: ='[5]ПП ВДГ'!AY32+'[5]Корсак Л.Р.'!AY32+'[5]Корсак В.І.'!AY32+[5]Конякіна!AY32 -> 0 | AZ32: ='[5]ПП ВДГ'!AZ32+'[5]Корсак Л.Р.'!AZ32+'[5]Корсак В.І.'!AZ32+[5]Конякіна!AZ32 -> 0 | BA32: =SUM(AY32:AZ32) -> 0 | BB32: ='Солар Вест'!BB32+Будник!BB32 -> 643155.93 | BC32: ='Солар Вест'!BC32+Будник!BC32 -> 4681 | BD32: =SUM(BB32:BC32) -> 647836.93 | BE32: ='Солар Вест'!BE32+Будник!BE32 -> 548552.47 | BF32: ='Солар Вест'!BF32+Будник!BF32 -> 50521 | BG32: =SUM(BE32:BF32) -> 599073.47 | BH32: ='Солар Вест'!BH32+Будник!BH32 -> 0 | BI32: ='Солар Вест'!BI32+Будник!BI32 -> 0 | BJ32: =SUM(BH32:BI32) -> 0 | BK32: ='[5]ПП ВДГ'!BK32+'[5]Корсак Л.Р.'!BK32+'[5]Корсак В.І.'!BK32+[5]Конякіна!BK32 -> 0 | BL32: ='[5]ПП ВДГ'!BL32+'[5]Корсак Л.Р.'!BL32+'[5]Корсак В.І.'!BL32+[5]Конякіна!BL32 -> 0 | BM32: =SUM(BK32:BL32) -> 0 | BN32: ='Солар Вест'!BN32+Будник!BN32 -> 0 | BO32: ='Солар Вест'!BO32+Будник!BO32 -> 0 | BP32: =SUM(BN32:BO32) -> 0 | BQ32: ='[5]ПП ВДГ'!BQ32+'[5]Корсак Л.Р.'!BQ32+'[5]Корсак В.І.'!BQ32+[5]Конякіна!BQ32 -> 0 | BR32: ='[5]ПП ВДГ'!BR32+'[5]Корсак Л.Р.'!BR32+'[5]Корсак В.І.'!BR32+[5]Конякіна!BR32 -> 0 | BS32: =SUM(BQ32:BR32) -> 0 | BT32: ='Солар Вест'!BT32+Будник!BT32 -> 0 | BU32: ='Солар Вест'!BU32+Будник!BU32 -> 0 | BV32: =SUM(BT32:BU32) -> 0 | BW32: =+C32+I32+O32+AA32+AG32+U32+AM32+AS32+AY32+BE32+BK32+BQ32 -> 548552.47 | BX32: =+D32+J32+P32+AB32+AH32+V32+AN32+AT32+AZ32+BF32+BL32+BR32 -> 50521 | BY32: =SUM(BW32:BX32) -> 599073.47 | BZ32: =+F32+L32+R32+AD32+AJ32+X32+AP32+AV32+BB32+BH32+BN32+BT32 -> 14159250 | CA32: =+G32+M32+S32+AE32+AK32+Y32+AQ32+AW32+BC32+BI32+BO32+BU32 -> 91971 | CB32: =SUM(BZ32:CA32) -> 14251221
B33: в т.ч. внутрішньогрупова закупка товарів (сировини) | C33: ='[5]ПП ВДГ'!C33+'[5]Корсак Л.Р.'!C33+'[5]Корсак В.І.'!C33+[5]Конякіна!C33 -> 0 | D33: ='[5]ПП ВДГ'!D33+'[5]Корсак Л.Р.'!D33+'[5]Корсак В.І.'!D33+[5]Конякіна!D33 -> 0 | E33: =SUM(C33:D33) -> 0 | F33: ='Солар Вест'!F33+Будник!F33 -> 0 | G33: ='Солар Вест'!G33+Будник!G33 -> 0 | H33: =SUM(F33:G33) -> 0 | I33: ='[5]ПП ВДГ'!I33+'[5]Корсак Л.Р.'!I33+'[5]Корсак В.І.'!I33+[5]Конякіна!I33 -> 0 | J33: ='[5]ПП ВДГ'!J33+'[5]Корсак Л.Р.'!J33+'[5]Корсак В.І.'!J33+[5]Конякіна!J33 -> 0 | K33: =SUM(I33:J33) -> 0 | L33: ='Солар Вест'!L33+Будник!L33 -> 0 | M33: ='Солар Вест'!M33+Будник!M33 -> 0 | N33: =SUM(L33:M33) -> 0 | O33: ='[5]ПП ВДГ'!O33+'[5]Корсак Л.Р.'!O33+'[5]Корсак В.І.'!O33+[5]Конякіна!O33 -> 0 | P33: ='[5]ПП ВДГ'!P33+'[5]Корсак Л.Р.'!P33+'[5]Корсак В.І.'!P33+[5]Конякіна!P33 -> 0 | Q33: =SUM(O33:P33) -> 0 | R33: ='Солар Вест'!R33+Будник!R33 -> 0 | S33: ='Солар Вест'!S33+Будник!S33 -> 0 | T33: =SUM(R33:S33) -> 0 | U33: ='[5]ПП ВДГ'!U33+'[5]Корсак Л.Р.'!U33+'[5]Корсак В.І.'!U33+[5]Конякіна!U33 -> 0 | V33: ='[5]ПП ВДГ'!V33+'[5]Корсак Л.Р.'!V33+'[5]Корсак В.І.'!V33+[5]Конякіна!V33 -> 0 | W33: =SUM(U33:V33) -> 0 | X33: ='Солар Вест'!X33+Будник!X33 -> 0 | Y33: ='Солар Вест'!Y33+Будник!Y33 -> 0 | Z33: =SUM(X33:Y33) -> 0 | AA33: ='[5]ПП ВДГ'!AA33+'[5]Корсак Л.Р.'!AA33+'[5]Корсак В.І.'!AA33+[5]Конякіна!AA33 -> 0 | AB33: ='[5]ПП ВДГ'!AB33+'[5]Корсак Л.Р.'!AB33+'[5]Корсак В.І.'!AB33+[5]Конякіна!AB33 -> 0 | AC33: =SUM(AA33:AB33) -> 0 | AD33: ='Солар Вест'!AD33+Будник!AD33 -> 0 | AE33: ='Солар Вест'!AE33+Будник!AE33 -> 0 | AF33: =SUM(AD33:AE33) -> 0 | AG33: ='[5]ПП ВДГ'!AG33+'[5]Корсак Л.Р.'!AG33+'[5]Корсак В.І.'!AG33+[5]Конякіна!AG33 -> 0 | AH33: ='[5]ПП ВДГ'!AH33+'[5]Корсак Л.Р.'!AH33+'[5]Корсак В.І.'!AH33+[5]Конякіна!AH33 -> 0 | AI33: =SUM(AG33:AH33) -> 0 | AJ33: ='Солар Вест'!AJ33+Будник!AJ33 -> 0 | AK33: ='Солар Вест'!AK33+Будник!AK33 -> 0 | AL33: =SUM(AJ33:AK33) -> 0 | AM33: ='[5]ПП ВДГ'!AM33+'[5]Корсак Л.Р.'!AM33+'[5]Корсак В.І.'!AM33+[5]Конякіна!AM33 -> 0 | AN33: ='[5]ПП ВДГ'!AN33+'[5]Корсак Л.Р.'!AN33+'[5]Корсак В.І.'!AN33+[5]Конякіна!AN33 -> 0 | AO33: =SUM(AM33:AN33) -> 0 | AP33: ='Солар Вест'!AP33+Будник!AP33 -> 0 | AQ33: ='Солар Вест'!AQ33+Будник!AQ33 -> 0 | AR33: =SUM(AP33:AQ33) -> 0 | AS33: ='[5]ПП ВДГ'!AS33+'[5]Корсак Л.Р.'!AS33+'[5]Корсак В.І.'!AS33+[5]Конякіна!AS33 -> 0 | AT33: ='[5]ПП ВДГ'!AT33+'[5]Корсак Л.Р.'!AT33+'[5]Корсак В.І.'!AT33+[5]Конякіна!AT33 -> 0 | AU33: =SUM(AS33:AT33) -> 0 | AV33: ='Солар Вест'!AV33+Будник!AV33 -> 0 | AW33: ='Солар Вест'!AW33+Будник!AW33 -> 0 | AX33: =SUM(AV33:AW33) -> 0 | AY33: ='[5]ПП ВДГ'!AY33+'[5]Корсак Л.Р.'!AY33+'[5]Корсак В.І.'!AY33+[5]Конякіна!AY33 -> 0 | AZ33: ='[5]ПП ВДГ'!AZ33+'[5]Корсак Л.Р.'!AZ33+'[5]Корсак В.І.'!AZ33+[5]Конякіна!AZ33 -> 0 | BA33: =SUM(AY33:AZ33) -> 0 | BB33: ='Солар Вест'!BB33+Будник!BB33 -> 0 | BC33: ='Солар Вест'!BC33+Будник!BC33 -> 0 | BD33: =SUM(BB33:BC33) -> 0 | BE33: ='Солар Вест'!BE33+Будник!BE33 -> 0 | BF33: ='Солар Вест'!BF33+Будник!BF33 -> 0 | BG33: =SUM(BE33:BF33) -> 0 | BH33: ='Солар Вест'!BH33+Будник!BH33 -> 0 | BI33: ='Солар Вест'!BI33+Будник!BI33 -> 0 | BJ33: =SUM(BH33:BI33) -> 0 | BK33: ='[5]ПП ВДГ'!BK33+'[5]Корсак Л.Р.'!BK33+'[5]Корсак В.І.'!BK33+[5]Конякіна!BK33 -> 0 | BL33: ='[5]ПП ВДГ'!BL33+'[5]Корсак Л.Р.'!BL33+'[5]Корсак В.І.'!BL33+[5]Конякіна!BL33 -> 0 | BM33: =SUM(BK33:BL33) -> 0 | BN33: ='Солар Вест'!BN33+Будник!BN33 -> 0 | BO33: ='Солар Вест'!BO33+Будник!BO33 -> 0 | BP33: =SUM(BN33:BO33) -> 0 | BQ33: ='[5]ПП ВДГ'!BQ33+'[5]Корсак Л.Р.'!BQ33+'[5]Корсак В.І.'!BQ33+[5]Конякіна!BQ33 -> 0 | BR33: ='[5]ПП ВДГ'!BR33+'[5]Корсак Л.Р.'!BR33+'[5]Корсак В.І.'!BR33+[5]Конякіна!BR33 -> 0 | BS33: =SUM(BQ33:BR33) -> 0 | BT33: ='Солар Вест'!BT33+Будник!BT33 -> 0 | BU33: ='Солар Вест'!BU33+Будник!BU33 -> 0 | BV33: =SUM(BT33:BU33) -> 0 | BW33: =+C33+I33+O33+AA33+AG33+U33+AM33+AS33+AY33+BE33+BK33+BQ33 -> 0 | BX33: =+D33+J33+P33+AB33+AH33+V33+AN33+AT33+AZ33+BF33+BL33+BR33 -> 0 | BY33: =SUM(BW33:BX33) -> 0 | BZ33: =+F33+L33+R33+AD33+AJ33+X33+AP33+AV33+BB33+BH33+BN33+BT33 -> 0 | CA33: =+G33+M33+S33+AE33+AK33+Y33+AQ33+AW33+BC33+BI33+BO33+BU33 -> 0 | CB33: =SUM(BZ33:CA33) -> 0
A34: 122 | B34: Зарплата | C34: ='[5]ПП ВДГ'!C34+'[5]Корсак Л.Р.'!C34+'[5]Корсак В.І.'!C34+[5]Конякіна!C34 -> 24030 | D34: ='[5]ПП ВДГ'!D34+'[5]Корсак Л.Р.'!D34+'[5]Корсак В.І.'!D34+[5]Конякіна!D34 -> 19150 | E34: =SUM(C34:D34) -> 43180 | F34: ='Солар Вест'!F34+Будник!F34 -> 9779 | G34: ='Солар Вест'!G34+Будник!G34 -> 175485 | H34: =SUM(F34:G34) -> 185264 | I34: ='[5]ПП ВДГ'!I34+'[5]Корсак Л.Р.'!I34+'[5]Корсак В.І.'!I34+[5]Конякіна!I34 -> 24030 | J34: ='[5]ПП ВДГ'!J34+'[5]Корсак Л.Р.'!J34+'[5]Корсак В.І.'!J34+[5]Конякіна!J34 -> 19150 | K34: =SUM(I34:J34) -> 43180 | L34: ='Солар Вест'!L34+Будник!L34 -> 9779 | M34: ='Солар Вест'!M34+Будник!M34 -> 166771 | N34: =SUM(L34:M34) -> 176550 | O34: ='[5]ПП ВДГ'!O34+'[5]Корсак Л.Р.'!O34+'[5]Корсак В.І.'!O34+[5]Конякіна!O34 -> 24030 | P34: ='[5]ПП ВДГ'!P34+'[5]Корсак Л.Р.'!P34+'[5]Корсак В.І.'!P34+[5]Конякіна!P34 -> 19150 | Q34: =SUM(O34:P34) -> 43180 | R34: ='Солар Вест'!R34+Будник!R34 -> 9779 | S34: ='Солар Вест'!S34+Будник!S34 -> 181721 | T34: =SUM(R34:S34) -> 191500 | U34: ='[5]ПП ВДГ'!U34+'[5]Корсак Л.Р.'!U34+'[5]Корсак В.І.'!U34+[5]Конякіна!U34 -> 23000 | V34: ='[5]ПП ВДГ'!V34+'[5]Корсак Л.Р.'!V34+'[5]Корсак В.І.'!V34+[5]Конякіна!V34 -> 22000 | W34: =SUM(U34:V34) -> 45000 | X34: ='Солар Вест'!X34+Будник!X34 -> 9779 | Y34: ='Солар Вест'!Y34+Будник!Y34 -> 213395 | Z34: =SUM(X34:Y34) -> 223174 | AA34: ='[5]ПП ВДГ'!AA34+'[5]Корсак Л.Р.'!AA34+'[5]Корсак В.І.'!AA34+[5]Конякіна!AA34 -> 22030 | AB34: ='[5]ПП ВДГ'!AB34+'[5]Корсак Л.Р.'!AB34+'[5]Корсак В.І.'!AB34+[5]Конякіна!AB34 -> 17150 | AC34: =SUM(AA34:AB34) -> 39180 | AD34: ='Солар Вест'!AD34+Будник!AD34 -> 10606.03 | AE34: ='Солар Вест'!AE34+Будник!AE34 -> 265005 | AF34: =SUM(AD34:AE34) -> 275611.03 | AG34: ='[5]ПП ВДГ'!AG34+'[5]Корсак Л.Р.'!AG34+'[5]Корсак В.І.'!AG34+[5]Конякіна!AG34 -> 22085 | AH34: ='[5]ПП ВДГ'!AH34+'[5]Корсак Л.Р.'!AH34+'[5]Корсак В.І.'!AH34+[5]Конякіна!AH34 -> 17150 | AI34: =SUM(AG34:AH34) -> 39235 | AJ34: ='Солар Вест'!AJ34+Будник!AJ34 -> 15952.33 | AK34: ='Солар Вест'!AK34+Будник!AK34 -> 499084 | AL34: =SUM(AJ34:AK34) -> 515036.33 | AM34: ='[5]ПП ВДГ'!AM34+'[5]Корсак Л.Р.'!AM34+'[5]Корсак В.І.'!AM34+[5]Конякіна!AM34 -> 25084 | AN34: ='[5]ПП ВДГ'!AN34+'[5]Корсак Л.Р.'!AN34+'[5]Корсак В.І.'!AN34+[5]Конякіна!AN34 -> 11150 | AO34: =SUM(AM34:AN34) -> 36234 | AP34: ='Солар Вест'!AP34+Будник!AP34 -> 21956.91 | AQ34: ='Солар Вест'!AQ34+Будник!AQ34 -> 379229 | AR34: =SUM(AP34:AQ34) -> 401185.91 | AS34: ='[5]ПП ВДГ'!AS34+'[5]Корсак Л.Р.'!AS34+'[5]Корсак В.І.'!AS34+[5]Конякіна!AS34 -> 25130 | AT34: ='[5]ПП ВДГ'!AT34+'[5]Корсак Л.Р.'!AT34+'[5]Корсак В.І.'!AT34+[5]Конякіна!AT34 -> 20150 | AU34: =SUM(AS34:AT34) -> 45280 | AV34: ='Солар Вест'!AV34+Будник!AV34 -> 32841.37 | AW34: ='Солар Вест'!AW34+Будник!AW34 -> 363605 | AX34: =SUM(AV34:AW34) -> 396446.37 | AY34: ='[5]ПП ВДГ'!AY34+'[5]Корсак Л.Р.'!AY34+'[5]Корсак В.І.'!AY34+[5]Конякіна!AY34 -> 22030 | AZ34: ='[5]ПП ВДГ'!AZ34+'[5]Корсак Л.Р.'!AZ34+'[5]Корсак В.І.'!AZ34+[5]Конякіна!AZ34 -> 17150 | BA34: =SUM(AY34:AZ34) -> 39180 | BB34: ='Солар Вест'!BB34+Будник!BB34 -> 32689.25 | BC34: ='Солар Вест'!BC34+Будник!BC34 -> 155028 | BD34: =SUM(BB34:BC34) -> 187717.25 | BE34: ='Солар Вест'!BE34+Будник!BE34 -> 18514.06 | BF34: ='Солар Вест'!BF34+Будник!BF34 -> 226338 | BG34: =SUM(BE34:BF34) -> 244852.06 | BH34: ='Солар Вест'!BH34+Будник!BH34 -> 0 | BI34: ='Солар Вест'!BI34+Будник!BI34 -> 0 | BJ34: =SUM(BH34:BI34) -> 0 | BK34: ='[5]ПП ВДГ'!BK34+'[5]Корсак Л.Р.'!BK34+'[5]Корсак В.І.'!BK34+[5]Конякіна!BK34 -> 24120 | BL34: ='[5]ПП ВДГ'!BL34+'[5]Корсак Л.Р.'!BL34+'[5]Корсак В.І.'!BL34+[5]Конякіна!BL34 -> 19150 | BM34: =SUM(BK34:BL34) -> 43270 | BN34: ='Солар Вест'!BN34+Будник!BN34 -> 0 | BO34: ='Солар Вест'!BO34+Будник!BO34 -> 0 | BP34: =SUM(BN34:BO34) -> 0 | BQ34: ='[5]ПП ВДГ'!BQ34+'[5]Корсак Л.Р.'!BQ34+'[5]Корсак В.І.'!BQ34+[5]Конякіна!BQ34 -> 27127 | BR34: ='[5]ПП ВДГ'!BR34+'[5]Корсак Л.Р.'!BR34+'[5]Корсак В.І.'!BR34+[5]Конякіна!BR34 -> 20450 | BS34: =SUM(BQ34:BR34) -> 47577 | BT34: ='Солар Вест'!BT34+Будник!BT34 -> 0 | BU34: ='Солар Вест'!BU34+Будник!BU34 -> 0 | BV34: =SUM(BT34:BU34) -> 0 | BW34: =+C34+I34+O34+AA34+AG34+U34+AM34+AS34+AY34+BE34+BK34+BQ34 -> 281210.06 | BX34: =+D34+J34+P34+AB34+AH34+V34+AN34+AT34+AZ34+BF34+BL34+BR34 -> 428138 | BY34: =SUM(BW34:BX34) -> 709348.06 | BZ34: =+F34+L34+R34+AD34+AJ34+X34+AP34+AV34+BB34+BH34+BN34+BT34 -> 153161.89 | CA34: =+G34+M34+S34+AE34+AK34+Y34+AQ34+AW34+BC34+BI34+BO34+BU34 -> 2399323 | CB34: =SUM(BZ34:CA34) -> 2552484.9
A35: 122.1 | B35: Податки по заробітній платі (утримання+нарахув.) | C35: ='[5]ПП ВДГ'!C35+'[5]Корсак Л.Р.'!C35+'[5]Корсак В.І.'!C35+[5]Конякіна!C35 -> 17550 | D35: ='[5]ПП ВДГ'!D35+'[5]Корсак Л.Р.'!D35+'[5]Корсак В.І.'!D35+[5]Конякіна!D35 -> 0 | E35: =SUM(C35:D35) -> 17550 | F35: ='Солар Вест'!F35+Будник!F35 -> 5560 | G35: ='Солар Вест'!G35+Будник!G35 -> 0 | H35: =SUM(F35:G35) -> 5560 | I35: ='[5]ПП ВДГ'!I35+'[5]Корсак Л.Р.'!I35+'[5]Корсак В.І.'!I35+[5]Конякіна!I35 -> 17550 | J35: ='[5]ПП ВДГ'!J35+'[5]Корсак Л.Р.'!J35+'[5]Корсак В.І.'!J35+[5]Конякіна!J35 -> 0 | K35: =SUM(I35:J35) -> 17550 | L35: ='Солар Вест'!L35+Будник!L35 -> 5315 | M35: ='Солар Вест'!M35+Будник!M35 -> 0 | N35: =SUM(L35:M35) -> 5315 | O35: ='[5]ПП ВДГ'!O35+'[5]Корсак Л.Р.'!O35+'[5]Корсак В.І.'!O35+[5]Конякіна!O35 -> 17550 | P35: ='[5]ПП ВДГ'!P35+'[5]Корсак Л.Р.'!P35+'[5]Корсак В.І.'!P35+[5]Конякіна!P35 -> 0 | Q35: =SUM(O35:P35) -> 17550 | R35: ='Солар Вест'!R35+Будник!R35 -> 6000 | S35: ='Солар Вест'!S35+Будник!S35 -> 0 | T35: =SUM(R35:S35) -> 6000 | U35: ='[5]ПП ВДГ'!U35+'[5]Корсак Л.Р.'!U35+'[5]Корсак В.І.'!U35+[5]Конякіна!U35 -> 12300 | V35: ='[5]ПП ВДГ'!V35+'[5]Корсак Л.Р.'!V35+'[5]Корсак В.І.'!V35+[5]Конякіна!V35 -> 0 | W35: =SUM(U35:V35) -> 12300 | X35: ='Солар Вест'!X35+Будник!X35 -> 5615 | Y35: ='Солар Вест'!Y35+Будник!Y35 -> 0 | Z35: =SUM(X35:Y35) -> 5615 | AA35: ='[5]ПП ВДГ'!AA35+'[5]Корсак Л.Р.'!AA35+'[5]Корсак В.І.'!AA35+[5]Конякіна!AA35 -> 16550 | AB35: ='[5]ПП ВДГ'!AB35+'[5]Корсак Л.Р.'!AB35+'[5]Корсак В.І.'!AB35+[5]Конякіна!AB35 -> 0 | AC35: =SUM(AA35:AB35) -> 16550 | AD35: ='Солар Вест'!AD35+Будник!AD35 -> 6413.82 | AE35: ='Солар Вест'!AE35+Будник!AE35 -> 0 | AF35: =SUM(AD35:AE35) -> 6413.82 | AG35: ='[5]ПП ВДГ'!AG35+'[5]Корсак Л.Р.'!AG35+'[5]Корсак В.І.'!AG35+[5]Конякіна!AG35 -> 13090 | AH35: ='[5]ПП ВДГ'!AH35+'[5]Корсак Л.Р.'!AH35+'[5]Корсак В.І.'!AH35+[5]Конякіна!AH35 -> 0 | AI35: =SUM(AG35:AH35) -> 13090 | AJ35: ='Солар Вест'!AJ35+Будник!AJ35 -> 8902 | AK35: ='Солар Вест'!AK35+Будник!AK35 -> 0 | AL35: =SUM(AJ35:AK35) -> 8902 | AM35: ='[5]ПП ВДГ'!AM35+'[5]Корсак Л.Р.'!AM35+'[5]Корсак В.І.'!AM35+[5]Конякіна!AM35 -> 11500 | AN35: ='[5]ПП ВДГ'!AN35+'[5]Корсак Л.Р.'!AN35+'[5]Корсак В.І.'!AN35+[5]Конякіна!AN35 -> 0 | AO35: =SUM(AM35:AN35) -> 11500 | AP35: ='Солар Вест'!AP35+Будник!AP35 -> 11397.57 | AQ35: ='Солар Вест'!AQ35+Будник!AQ35 -> 0 | AR35: =SUM(AP35:AQ35) -> 11397.57 | AS35: ='[5]ПП ВДГ'!AS35+'[5]Корсак Л.Р.'!AS35+'[5]Корсак В.І.'!AS35+[5]Конякіна!AS35 -> 12610 | AT35: ='[5]ПП ВДГ'!AT35+'[5]Корсак Л.Р.'!AT35+'[5]Корсак В.І.'!AT35+[5]Конякіна!AT35 -> 0 | AU35: =SUM(AS35:AT35) -> 12610 | AV35: ='Солар Вест'!AV35+Будник!AV35 -> 17570.24 | AW35: ='Солар Вест'!AW35+Будник!AW35 -> 0 | AX35: =SUM(AV35:AW35) -> 17570.24 | AY35: ='[5]ПП ВДГ'!AY35+'[5]Корсак Л.Р.'!AY35+'[5]Корсак В.І.'!AY35+[5]Конякіна!AY35 -> 16550 | AZ35: ='[5]ПП ВДГ'!AZ35+'[5]Корсак Л.Р.'!AZ35+'[5]Корсак В.І.'!AZ35+[5]Конякіна!AZ35 -> 0 | BA35: =SUM(AY35:AZ35) -> 16550 | BB35: ='Солар Вест'!BB35+Будник!BB35 -> 17744.25 | BC35: ='Солар Вест'!BC35+Будник!BC35 -> 0 | BD35: =SUM(BB35:BC35) -> 17744.25 | BE35: ='Солар Вест'!BE35+Будник!BE35 -> 5210.1 | BF35: ='Солар Вест'!BF35+Будник!BF35 -> 0 | BG35: =SUM(BE35:BF35) -> 5210.1 | BH35: ='Солар Вест'!BH35+Будник!BH35 -> 0 | BI35: ='Солар Вест'!BI35+Будник!BI35 -> 0 | BJ35: =SUM(BH35:BI35) -> 0 | BK35: ='[5]ПП ВДГ'!BK35+'[5]Корсак Л.Р.'!BK35+'[5]Корсак В.І.'!BK35+[5]Конякіна!BK35 -> 19630 | BL35: ='[5]ПП ВДГ'!BL35+'[5]Корсак Л.Р.'!BL35+'[5]Корсак В.І.'!BL35+[5]Конякіна!BL35 -> 0 | BM35: =SUM(BK35:BL35) -> 19630 | BN35: ='Солар Вест'!BN35+Будник!BN35 -> 0 | BO35: ='Солар Вест'!BO35+Будник!BO35 -> 0 | BP35: =SUM(BN35:BO35) -> 0 | BQ35: ='[5]ПП ВДГ'!BQ35+'[5]Корсак Л.Р.'!BQ35+'[5]Корсак В.І.'!BQ35+[5]Конякіна!BQ35 -> 17640 | BR35: ='[5]ПП ВДГ'!BR35+'[5]Корсак Л.Р.'!BR35+'[5]Корсак В.І.'!BR35+[5]Конякіна!BR35 -> 0 | BS35: =SUM(BQ35:BR35) -> 17640 | BT35: ='Солар Вест'!BT35+Будник!BT35 -> 0 | BU35: ='Солар Вест'!BU35+Будник!BU35 -> 0 | BV35: =SUM(BT35:BU35) -> 0 | BW35: =+C35+I35+O35+AA35+AG35+U35+AM35+AS35+AY35+BE35+BK35+BQ35 -> 177730.1 | BX35: =+D35+J35+P35+AB35+AH35+V35+AN35+AT35+AZ35+BF35+BL35+BR35 -> 0 | BY35: =SUM(BW35:BX35) -> 177730.1 | BZ35: =+F35+L35+R35+AD35+AJ35+X35+AP35+AV35+BB35+BH35+BN35+BT35 -> 84517.88 | CA35: =+G35+M35+S35+AE35+AK35+Y35+AQ35+AW35+BC35+BI35+BO35+BU35 -> 0 | CB35: =SUM(BZ35:CA35) -> 84517.88
A36: 123 | B36: Оренда | C36: ='[5]ПП ВДГ'!C36+'[5]Корсак Л.Р.'!C36+'[5]Корсак В.І.'!C36+[5]Конякіна!C36 -> 0 | D36: ='[5]ПП ВДГ'!D36+'[5]Корсак Л.Р.'!D36+'[5]Корсак В.І.'!D36+[5]Конякіна!D36 -> 0 | E36: =SUM(C36:D36) -> 0 | F36: ='Солар Вест'!F36+Будник!F36 -> 0 | G36: ='Солар Вест'!G36+Будник!G36 -> 0 | H36: =SUM(F36:G36) -> 0 | I36: ='[5]ПП ВДГ'!I36+'[5]Корсак Л.Р.'!I36+'[5]Корсак В.І.'!I36+[5]Конякіна!I36 -> 0 | J36: ='[5]ПП ВДГ'!J36+'[5]Корсак Л.Р.'!J36+'[5]Корсак В.І.'!J36+[5]Конякіна!J36 -> 0 | K36: =SUM(I36:J36) -> 0 | L36: ='Солар Вест'!L36+Будник!L36 -> 0 | M36: ='Солар Вест'!M36+Будник!M36 -> 0 | N36: =SUM(L36:M36) -> 0 | O36: ='[5]ПП ВДГ'!O36+'[5]Корсак Л.Р.'!O36+'[5]Корсак В.І.'!O36+[5]Конякіна!O36 -> 0 | P36: ='[5]ПП ВДГ'!P36+'[5]Корсак Л.Р.'!P36+'[5]Корсак В.І.'!P36+[5]Конякіна!P36 -> 0 | Q36: =SUM(O36:P36) -> 0 | R36: ='Солар Вест'!R36+Будник!R36 -> 0 | S36: ='Солар Вест'!S36+Будник!S36 -> 0 | T36: =SUM(R36:S36) -> 0 | U36: ='[5]ПП ВДГ'!U36+'[5]Корсак Л.Р.'!U36+'[5]Корсак В.І.'!U36+[5]Конякіна!U36 -> 0 | V36: ='[5]ПП ВДГ'!V36+'[5]Корсак Л.Р.'!V36+'[5]Корсак В.І.'!V36+[5]Конякіна!V36 -> 0 | W36: =SUM(U36:V36) -> 0 | X36: ='Солар Вест'!X36+Будник!X36 -> 0 | Y36: ='Солар Вест'!Y36+Будник!Y36 -> 0 | Z36: =SUM(X36:Y36) -> 0 | AA36: ='[5]ПП ВДГ'!AA36+'[5]Корсак Л.Р.'!AA36+'[5]Корсак В.І.'!AA36+[5]Конякіна!AA36 -> 0 | AB36: ='[5]ПП ВДГ'!AB36+'[5]Корсак Л.Р.'!AB36+'[5]Корсак В.І.'!AB36+[5]Конякіна!AB36 -> 0 | AC36: =SUM(AA36:AB36) -> 0 | AD36: ='Солар Вест'!AD36+Будник!AD36 -> 0 | AE36: ='Солар Вест'!AE36+Будник!AE36 -> 0 | AF36: =SUM(AD36:AE36) -> 0 | AG36: ='[5]ПП ВДГ'!AG36+'[5]Корсак Л.Р.'!AG36+'[5]Корсак В.І.'!AG36+[5]Конякіна!AG36 -> 0 | AH36: ='[5]ПП ВДГ'!AH36+'[5]Корсак Л.Р.'!AH36+'[5]Корсак В.І.'!AH36+[5]Конякіна!AH36 -> 0 | AI36: =SUM(AG36:AH36) -> 0 | AJ36: ='Солар Вест'!AJ36+Будник!AJ36 -> 6915.6 | AK36: ='Солар Вест'!AK36+Будник!AK36 -> 0 | AL36: =SUM(AJ36:AK36) -> 6915.6 | AM36: ='[5]ПП ВДГ'!AM36+'[5]Корсак Л.Р.'!AM36+'[5]Корсак В.І.'!AM36+[5]Конякіна!AM36 -> 0 | AN36: ='[5]ПП ВДГ'!AN36+'[5]Корсак Л.Р.'!AN36+'[5]Корсак В.І.'!AN36+[5]Конякіна!AN36 -> 0 | AO36: =SUM(AM36:AN36) -> 0 | AP36: ='Солар Вест'!AP36+Будник!AP36 -> 0 | AQ36: ='Солар Вест'!AQ36+Будник!AQ36 -> 0 | AR36: =SUM(AP36:AQ36) -> 0 | AS36: ='[5]ПП ВДГ'!AS36+'[5]Корсак Л.Р.'!AS36+'[5]Корсак В.І.'!AS36+[5]Конякіна!AS36 -> 0 | AT36: ='[5]ПП ВДГ'!AT36+'[5]Корсак Л.Р.'!AT36+'[5]Корсак В.І.'!AT36+[5]Конякіна!AT36 -> 0 | AU36: =SUM(AS36:AT36) -> 0 | AV36: ='Солар Вест'!AV36+Будник!AV36 -> 0 | AW36: ='Солар Вест'!AW36+Будник!AW36 -> 0 | AX36: =SUM(AV36:AW36) -> 0 | AY36: ='[5]ПП ВДГ'!AY36+'[5]Корсак Л.Р.'!AY36+'[5]Корсак В.І.'!AY36+[5]Конякіна!AY36 -> 0 | AZ36: ='[5]ПП ВДГ'!AZ36+'[5]Корсак Л.Р.'!AZ36+'[5]Корсак В.І.'!AZ36+[5]Конякіна!AZ36 -> 0 | BA36: =SUM(AY36:AZ36) -> 0 | BB36: ='Солар Вест'!BB36+Будник!BB36 -> 13831.2 | BC36: ='Солар Вест'!BC36+Будник!BC36 -> 0 | BD36: =SUM(BB36:BC36) -> 13831.2 | BE36: ='Солар Вест'!BE36+Будник!BE36 -> 0 | BF36: ='Солар Вест'!BF36+Будник!BF36 -> 0 | BG36: =SUM(BE36:BF36) -> 0 | BH36: ='Солар Вест'!BH36+Будник!BH36 -> 0 | BI36: ='Солар Вест'!BI36+Будник!BI36 -> 0 | BJ36: =SUM(BH36:BI36) -> 0 | BK36: ='[5]ПП ВДГ'!BK36+'[5]Корсак Л.Р.'!BK36+'[5]Корсак В.І.'!BK36+[5]Конякіна!BK36 -> 0 | BL36: ='[5]ПП ВДГ'!BL36+'[5]Корсак Л.Р.'!BL36+'[5]Корсак В.І.'!BL36+[5]Конякіна!BL36 -> 0 | BM36: =SUM(BK36:BL36) -> 0 | BN36: ='Солар Вест'!BN36+Будник!BN36 -> 0 | BO36: ='Солар Вест'!BO36+Будник!BO36 -> 0 | BP36: =SUM(BN36:BO36) -> 0 | BQ36: ='[5]ПП ВДГ'!BQ36+'[5]Корсак Л.Р.'!BQ36+'[5]Корсак В.І.'!BQ36+[5]Конякіна!BQ36 -> 0 | BR36: ='[5]ПП ВДГ'!BR36+'[5]Корсак Л.Р.'!BR36+'[5]Корсак В.І.'!BR36+[5]Конякіна!BR36 -> 0 | BS36: =SUM(BQ36:BR36) -> 0 | BT36: ='Солар Вест'!BT36+Будник!BT36 -> 0 | BU36: ='Солар Вест'!BU36+Будник!BU36 -> 0 | BV36: =SUM(BT36:BU36) -> 0 | BW36: =+C36+I36+O36+AA36+AG36+U36+AM36+AS36+AY36+BE36+BK36+BQ36 -> 0 | BX36: =+D36+J36+P36+AB36+AH36+V36+AN36+AT36+AZ36+BF36+BL36+BR36 -> 0 | BY36: =SUM(BW36:BX36) -> 0 | BZ36: =+F36+L36+R36+AD36+AJ36+X36+AP36+AV36+BB36+BH36+BN36+BT36 -> 20746.8 | CA36: =+G36+M36+S36+AE36+AK36+Y36+AQ36+AW36+BC36+BI36+BO36+BU36 -> 0 | CB36: =SUM(BZ36:CA36) -> 20746.8
B37: в т.ч. внутрішньогрупова оренда | C37: ='[5]ПП ВДГ'!C37+'[5]Корсак Л.Р.'!C37+'[5]Корсак В.І.'!C37+[5]Конякіна!C37 -> 0 | D37: ='[5]ПП ВДГ'!D37+'[5]Корсак Л.Р.'!D37+'[5]Корсак В.І.'!D37+[5]Конякіна!D37 -> 0 | E37: =SUM(C37:D37) -> 0 | F37: ='Солар Вест'!F37+Будник!F37 -> 0 | G37: ='Солар Вест'!G37+Будник!G37 -> 0 | H37: =SUM(F37:G37) -> 0 | I37: ='[5]ПП ВДГ'!I37+'[5]Корсак Л.Р.'!I37+'[5]Корсак В.І.'!I37+[5]Конякіна!I37 -> 0 | J37: ='[5]ПП ВДГ'!J37+'[5]Корсак Л.Р.'!J37+'[5]Корсак В.І.'!J37+[5]Конякіна!J37 -> 0 | K37: =SUM(I37:J37) -> 0 | L37: ='Солар Вест'!L37+Будник!L37 -> 0 | M37: ='Солар Вест'!M37+Будник!M37 -> 0 | N37: =SUM(L37:M37) -> 0 | O37: ='[5]ПП ВДГ'!O37+'[5]Корсак Л.Р.'!O37+'[5]Корсак В.І.'!O37+[5]Конякіна!O37 -> 0 | P37: ='[5]ПП ВДГ'!P37+'[5]Корсак Л.Р.'!P37+'[5]Корсак В.І.'!P37+[5]Конякіна!P37 -> 0 | Q37: =SUM(O37:P37) -> 0 | R37: ='Солар Вест'!R37+Будник!R37 -> 0 | S37: ='Солар Вест'!S37+Будник!S37 -> 0 | T37: =SUM(R37:S37) -> 0 | U37: ='[5]ПП ВДГ'!U37+'[5]Корсак Л.Р.'!U37+'[5]Корсак В.І.'!U37+[5]Конякіна!U37 -> 0 | V37: ='[5]ПП ВДГ'!V37+'[5]Корсак Л.Р.'!V37+'[5]Корсак В.І.'!V37+[5]Конякіна!V37 -> 0 | W37: =SUM(U37:V37) -> 0 | X37: ='Солар Вест'!X37+Будник!X37 -> 0 | Y37: ='Солар Вест'!Y37+Будник!Y37 -> 0 | Z37: =SUM(X37:Y37) -> 0 | AA37: ='[5]ПП ВДГ'!AA37+'[5]Корсак Л.Р.'!AA37+'[5]Корсак В.І.'!AA37+[5]Конякіна!AA37 -> 0 | AB37: ='[5]ПП ВДГ'!AB37+'[5]Корсак Л.Р.'!AB37+'[5]Корсак В.І.'!AB37+[5]Конякіна!AB37 -> 0 | AC37: =SUM(AA37:AB37) -> 0 | AD37: ='Солар Вест'!AD37+Будник!AD37 -> 0 | AE37: ='Солар Вест'!AE37+Будник!AE37 -> 0 | AF37: =SUM(AD37:AE37) -> 0 | AG37: ='[5]ПП ВДГ'!AG37+'[5]Корсак Л.Р.'!AG37+'[5]Корсак В.І.'!AG37+[5]Конякіна!AG37 -> 0 | AH37: ='[5]ПП ВДГ'!AH37+'[5]Корсак Л.Р.'!AH37+'[5]Корсак В.І.'!AH37+[5]Конякіна!AH37 -> 0 | AI37: =SUM(AG37:AH37) -> 0 | AJ37: ='Солар Вест'!AJ37+Будник!AJ37 -> 0 | AK37: ='Солар Вест'!AK37+Будник!AK37 -> 0 | AL37: =SUM(AJ37:AK37) -> 0 | AM37: ='[5]ПП ВДГ'!AM37+'[5]Корсак Л.Р.'!AM37+'[5]Корсак В.І.'!AM37+[5]Конякіна!AM37 -> 0 | AN37: ='[5]ПП ВДГ'!AN37+'[5]Корсак Л.Р.'!AN37+'[5]Корсак В.І.'!AN37+[5]Конякіна!AN37 -> 0 | AO37: =SUM(AM37:AN37) -> 0 | AP37: ='Солар Вест'!AP37+Будник!AP37 -> 0 | AQ37: ='Солар Вест'!AQ37+Будник!AQ37 -> 0 | AR37: =SUM(AP37:AQ37) -> 0 | AS37: ='[5]ПП ВДГ'!AS37+'[5]Корсак Л.Р.'!AS37+'[5]Корсак В.І.'!AS37+[5]Конякіна!AS37 -> 0 | AT37: ='[5]ПП ВДГ'!AT37+'[5]Корсак Л.Р.'!AT37+'[5]Корсак В.І.'!AT37+[5]Конякіна!AT37 -> 0 | AU37: =SUM(AS37:AT37) -> 0 | AV37: ='Солар Вест'!AV37+Будник!AV37 -> 0 | AW37: ='Солар Вест'!AW37+Будник!AW37 -> 0 | AX37: =SUM(AV37:AW37) -> 0 | AY37: ='[5]ПП ВДГ'!AY37+'[5]Корсак Л.Р.'!AY37+'[5]Корсак В.І.'!AY37+[5]Конякіна!AY37 -> 0 | AZ37: ='[5]ПП ВДГ'!AZ37+'[5]Корсак Л.Р.'!AZ37+'[5]Корсак В.І.'!AZ37+[5]Конякіна!AZ37 -> 0 | BA37: =SUM(AY37:AZ37) -> 0 | BB37: ='Солар Вест'!BB37+Будник!BB37 -> 0 | BC37: ='Солар Вест'!BC37+Будник!BC37 -> 0 | BD37: =SUM(BB37:BC37) -> 0 | BE37: ='Солар Вест'!BE37+Будник!BE37 -> 0 | BF37: ='Солар Вест'!BF37+Будник!BF37 -> 0 | BG37: =SUM(BE37:BF37) -> 0 | BH37: ='Солар Вест'!BH37+Будник!BH37 -> 0 | BI37: ='Солар Вест'!BI37+Будник!BI37 -> 0 | BJ37: =SUM(BH37:BI37) -> 0 | BK37: ='[5]ПП ВДГ'!BK37+'[5]Корсак Л.Р.'!BK37+'[5]Корсак В.І.'!BK37+[5]Конякіна!BK37 -> 0 | BL37: ='[5]ПП ВДГ'!BL37+'[5]Корсак Л.Р.'!BL37+'[5]Корсак В.І.'!BL37+[5]Конякіна!BL37 -> 0 | BM37: =SUM(BK37:BL37) -> 0 | BN37: ='Солар Вест'!BN37+Будник!BN37 -> 0 | BO37: ='Солар Вест'!BO37+Будник!BO37 -> 0 | BP37: =SUM(BN37:BO37) -> 0 | BQ37: ='[5]ПП ВДГ'!BQ37+'[5]Корсак Л.Р.'!BQ37+'[5]Корсак В.І.'!BQ37+[5]Конякіна!BQ37 -> 0 | BR37: ='[5]ПП ВДГ'!BR37+'[5]Корсак Л.Р.'!BR37+'[5]Корсак В.І.'!BR37+[5]Конякіна!BR37 -> 0 | BS37: =SUM(BQ37:BR37) -> 0 | BT37: ='Солар Вест'!BT37+Будник!BT37 -> 0 | BU37: ='Солар Вест'!BU37+Будник!BU37 -> 0 | BV37: =SUM(BT37:BU37) -> 0 | BW37: =+C37+I37+O37+AA37+AG37+U37+AM37+AS37+AY37+BE37+BK37+BQ37 -> 0 | BX37: =+D37+J37+P37+AB37+AH37+V37+AN37+AT37+AZ37+BF37+BL37+BR37 -> 0 | BY37: =SUM(BW37:BX37) -> 0 | BZ37: =+F37+L37+R37+AD37+AJ37+X37+AP37+AV37+BB37+BH37+BN37+BT37 -> 0 | CA37: =+G37+M37+S37+AE37+AK37+Y37+AQ37+AW37+BC37+BI37+BO37+BU37 -> 0 | CB37: =SUM(BZ37:CA37) -> 0
A38: 124 | B38: Відсотки по кредитах банків | C38: ='[5]ПП ВДГ'!C38+'[5]Корсак Л.Р.'!C38+'[5]Корсак В.І.'!C38+[5]Конякіна!C38 -> 0 | D38: ='[5]ПП ВДГ'!D38+'[5]Корсак Л.Р.'!D38+'[5]Корсак В.І.'!D38+[5]Конякіна!D38 -> 0 | E38: =SUM(C38:D38) -> 0 | F38: ='Солар Вест'!F38+Будник!F38 -> 0 | G38: ='Солар Вест'!G38+Будник!G38 -> 0 | H38: =SUM(F38:G38) -> 0 | I38: ='[5]ПП ВДГ'!I38+'[5]Корсак Л.Р.'!I38+'[5]Корсак В.І.'!I38+[5]Конякіна!I38 -> 0 | J38: ='[5]ПП ВДГ'!J38+'[5]Корсак Л.Р.'!J38+'[5]Корсак В.І.'!J38+[5]Конякіна!J38 -> 0 | K38: =SUM(I38:J38) -> 0 | L38: ='Солар Вест'!L38+Будник!L38 -> 0 | M38: ='Солар Вест'!M38+Будник!M38 -> 0 | N38: =SUM(L38:M38) -> 0 | O38: ='[5]ПП ВДГ'!O38+'[5]Корсак Л.Р.'!O38+'[5]Корсак В.І.'!O38+[5]Конякіна!O38 -> 0 | P38: ='[5]ПП ВДГ'!P38+'[5]Корсак Л.Р.'!P38+'[5]Корсак В.І.'!P38+[5]Конякіна!P38 -> 0 | Q38: =SUM(O38:P38) -> 0 | R38: ='Солар Вест'!R38+Будник!R38 -> 0 | S38: ='Солар Вест'!S38+Будник!S38 -> 0 | T38: =SUM(R38:S38) -> 0 | U38: ='[5]ПП ВДГ'!U38+'[5]Корсак Л.Р.'!U38+'[5]Корсак В.І.'!U38+[5]Конякіна!U38 -> 12210 | V38: ='[5]ПП ВДГ'!V38+'[5]Корсак Л.Р.'!V38+'[5]Корсак В.І.'!V38+[5]Конякіна!V38 -> 0 | W38: =SUM(U38:V38) -> 12210 | X38: ='Солар Вест'!X38+Будник!X38 -> 0 | Y38: ='Солар Вест'!Y38+Будник!Y38 -> 0 | Z38: =SUM(X38:Y38) -> 0 | AA38: ='[5]ПП ВДГ'!AA38+'[5]Корсак Л.Р.'!AA38+'[5]Корсак В.І.'!AA38+[5]Конякіна!AA38 -> 2596 | AB38: ='[5]ПП ВДГ'!AB38+'[5]Корсак Л.Р.'!AB38+'[5]Корсак В.І.'!AB38+[5]Конякіна!AB38 -> 0 | AC38: =SUM(AA38:AB38) -> 2596 | AD38: ='Солар Вест'!AD38+Будник!AD38 -> 0 | AE38: ='Солар Вест'!AE38+Будник!AE38 -> 0 | AF38: =SUM(AD38:AE38) -> 0 | AG38: ='[5]ПП ВДГ'!AG38+'[5]Корсак Л.Р.'!AG38+'[5]Корсак В.І.'!AG38+[5]Конякіна!AG38 -> 2554 | AH38: ='[5]ПП ВДГ'!AH38+'[5]Корсак Л.Р.'!AH38+'[5]Корсак В.І.'!AH38+[5]Конякіна!AH38 -> 0 | AI38: =SUM(AG38:AH38) -> 2554 | AJ38: ='Солар Вест'!AJ38+Будник!AJ38 -> 0 | AK38: ='Солар Вест'!AK38+Будник!AK38 -> 0 | AL38: =SUM(AJ38:AK38) -> 0 | AM38: ='[5]ПП ВДГ'!AM38+'[5]Корсак Л.Р.'!AM38+'[5]Корсак В.І.'!AM38+[5]Конякіна!AM38 -> 2514 | AN38: ='[5]ПП ВДГ'!AN38+'[5]Корсак Л.Р.'!AN38+'[5]Корсак В.І.'!AN38+[5]Конякіна!AN38 -> 0 | AO38: =SUM(AM38:AN38) -> 2514 | AP38: ='Солар Вест'!AP38+Будник!AP38 -> 0 | AQ38: ='Солар Вест'!AQ38+Будник!AQ38 -> 0 | AR38: =SUM(AP38:AQ38) -> 0 | AS38: ='[5]ПП ВДГ'!AS38+'[5]Корсак Л.Р.'!AS38+'[5]Корсак В.І.'!AS38+[5]Конякіна!AS38 -> 2475 | AT38: ='[5]ПП ВДГ'!AT38+'[5]Корсак Л.Р.'!AT38+'[5]Корсак В.І.'!AT38+[5]Конякіна!AT38 -> 0 | AU38: =SUM(AS38:AT38) -> 2475 | AV38: ='Солар Вест'!AV38+Будник!AV38 -> 0 | AW38: ='Солар Вест'!AW38+Будник!AW38 -> 0 | AX38: =SUM(AV38:AW38) -> 0 | AY38: ='[5]ПП ВДГ'!AY38+'[5]Корсак Л.Р.'!AY38+'[5]Корсак В.І.'!AY38+[5]Конякіна!AY38 -> 0 | AZ38: ='[5]ПП ВДГ'!AZ38+'[5]Корсак Л.Р.'!AZ38+'[5]Корсак В.І.'!AZ38+[5]Конякіна!AZ38 -> 0 | BA38: =SUM(AY38:AZ38) -> 0 | BB38: ='Солар Вест'!BB38+Будник!BB38 -> 0 | BC38: ='Солар Вест'!BC38+Будник!BC38 -> 0 | BD38: =SUM(BB38:BC38) -> 0 | BE38: ='Солар Вест'!BE38+Будник!BE38 -> 0 | BF38: ='Солар Вест'!BF38+Будник!BF38 -> 0 | BG38: =SUM(BE38:BF38) -> 0 | BH38: ='Солар Вест'!BH38+Будник!BH38 -> 0 | BI38: ='Солар Вест'!BI38+Будник!BI38 -> 0 | BJ38: =SUM(BH38:BI38) -> 0 | BK38: ='[5]ПП ВДГ'!BK38+'[5]Корсак Л.Р.'!BK38+'[5]Корсак В.І.'!BK38+[5]Конякіна!BK38 -> 2366 | BL38: ='[5]ПП ВДГ'!BL38+'[5]Корсак Л.Р.'!BL38+'[5]Корсак В.І.'!BL38+[5]Конякіна!BL38 -> 0 | BM38: =SUM(BK38:BL38) -> 2366 | BN38: ='Солар Вест'!BN38+Будник!BN38 -> 0 | BO38: ='Солар Вест'!BO38+Будник!BO38 -> 0 | BP38: =SUM(BN38:BO38) -> 0 | BQ38: ='[5]ПП ВДГ'!BQ38+'[5]Корсак Л.Р.'!BQ38+'[5]Корсак В.І.'!BQ38+[5]Конякіна!BQ38 -> 2332 | BR38: ='[5]ПП ВДГ'!BR38+'[5]Корсак Л.Р.'!BR38+'[5]Корсак В.І.'!BR38+[5]Конякіна!BR38 -> 0 | BS38: =SUM(BQ38:BR38) -> 2332 | BT38: ='Солар Вест'!BT38+Будник!BT38 -> 0 | BU38: ='Солар Вест'!BU38+Будник!BU38 -> 0 | BV38: =SUM(BT38:BU38) -> 0 | BW38: =+C38+I38+O38+AA38+AG38+U38+AM38+AS38+AY38+BE38+BK38+BQ38 -> 27047 | BX38: =+D38+J38+P38+AB38+AH38+V38+AN38+AT38+AZ38+BF38+BL38+BR38 -> 0 | BY38: =SUM(BW38:BX38) -> 27047 | BZ38: =+F38+L38+R38+AD38+AJ38+X38+AP38+AV38+BB38+BH38+BN38+BT38 -> 0 | CA38: =+G38+M38+S38+AE38+AK38+Y38+AQ38+AW38+BC38+BI38+BO38+BU38 -> 0 | CB38: =SUM(BZ38:CA38) -> 0
A39: 124.1 | B39: в т.ч. відсотки РФБА іпотечні | C39: ='[5]ПП ВДГ'!C39+'[5]Корсак Л.Р.'!C39+'[5]Корсак В.І.'!C39+[5]Конякіна!C39 -> 0 | D39: ='[5]ПП ВДГ'!D39+'[5]Корсак Л.Р.'!D39+'[5]Корсак В.І.'!D39+[5]Конякіна!D39 -> 0 | E39: =SUM(C39:D39) -> 0 | F39: ='Солар Вест'!F39+Будник!F39 -> 0 | G39: ='Солар Вест'!G39+Будник!G39 -> 0 | H39: =SUM(F39:G39) -> 0 | I39: ='[5]ПП ВДГ'!I39+'[5]Корсак Л.Р.'!I39+'[5]Корсак В.І.'!I39+[5]Конякіна!I39 -> 0 | J39: ='[5]ПП ВДГ'!J39+'[5]Корсак Л.Р.'!J39+'[5]Корсак В.І.'!J39+[5]Конякіна!J39 -> 0 | K39: =SUM(I39:J39) -> 0 | L39: ='Солар Вест'!L39+Будник!L39 -> 0 | M39: ='Солар Вест'!M39+Будник!M39 -> 0 | N39: =SUM(L39:M39) -> 0 | O39: ='[5]ПП ВДГ'!O39+'[5]Корсак Л.Р.'!O39+'[5]Корсак В.І.'!O39+[5]Конякіна!O39 -> 0 | P39: ='[5]ПП ВДГ'!P39+'[5]Корсак Л.Р.'!P39+'[5]Корсак В.І.'!P39+[5]Конякіна!P39 -> 0 | Q39: =SUM(O39:P39) -> 0 | R39: ='Солар Вест'!R39+Будник!R39 -> 0 | S39: ='Солар Вест'!S39+Будник!S39 -> 0 | T39: =SUM(R39:S39) -> 0 | U39: ='[5]ПП ВДГ'!U39+'[5]Корсак Л.Р.'!U39+'[5]Корсак В.І.'!U39+[5]Конякіна!U39 -> 0 | V39: ='[5]ПП ВДГ'!V39+'[5]Корсак Л.Р.'!V39+'[5]Корсак В.І.'!V39+[5]Конякіна!V39 -> 0 | W39: =SUM(U39:V39) -> 0 | X39: ='Солар Вест'!X39+Будник!X39 -> 0 | Y39: ='Солар Вест'!Y39+Будник!Y39 -> 0 | Z39: =SUM(X39:Y39) -> 0 | AA39: ='[5]ПП ВДГ'!AA39+'[5]Корсак Л.Р.'!AA39+'[5]Корсак В.І.'!AA39+[5]Конякіна!AA39 -> 0 | AB39: ='[5]ПП ВДГ'!AB39+'[5]Корсак Л.Р.'!AB39+'[5]Корсак В.І.'!AB39+[5]Конякіна!AB39 -> 0 | AC39: =SUM(AA39:AB39) -> 0 | AD39: ='Солар Вест'!AD39+Будник!AD39 -> 0 | AE39: ='Солар Вест'!AE39+Будник!AE39 -> 0 | AF39: =SUM(AD39:AE39) -> 0 | AG39: ='[5]ПП ВДГ'!AG39+'[5]Корсак Л.Р.'!AG39+'[5]Корсак В.І.'!AG39+[5]Конякіна!AG39 -> 0 | AH39: ='[5]ПП ВДГ'!AH39+'[5]Корсак Л.Р.'!AH39+'[5]Корсак В.І.'!AH39+[5]Конякіна!AH39 -> 0 | AI39: =SUM(AG39:AH39) -> 0 | AJ39: ='Солар Вест'!AJ39+Будник!AJ39 -> 0 | AK39: ='Солар Вест'!AK39+Будник!AK39 -> 0 | AL39: =SUM(AJ39:AK39) -> 0 | AM39: ='[5]ПП ВДГ'!AM39+'[5]Корсак Л.Р.'!AM39+'[5]Корсак В.І.'!AM39+[5]Конякіна!AM39 -> 0 | AN39: ='[5]ПП ВДГ'!AN39+'[5]Корсак Л.Р.'!AN39+'[5]Корсак В.І.'!AN39+[5]Конякіна!AN39 -> 0 | AO39: =SUM(AM39:AN39) -> 0 | AP39: ='Солар Вест'!AP39+Будник!AP39 -> 0 | AQ39: ='Солар Вест'!AQ39+Будник!AQ39 -> 0 | AR39: =SUM(AP39:AQ39) -> 0 | AS39: ='[5]ПП ВДГ'!AS39+'[5]Корсак Л.Р.'!AS39+'[5]Корсак В.І.'!AS39+[5]Конякіна!AS39 -> 0 | AT39: ='[5]ПП ВДГ'!AT39+'[5]Корсак Л.Р.'!AT39+'[5]Корсак В.І.'!AT39+[5]Конякіна!AT39 -> 0 | AU39: =SUM(AS39:AT39) -> 0 | AV39: ='Солар Вест'!AV39+Будник!AV39 -> 0 | AW39: ='Солар Вест'!AW39+Будник!AW39 -> 0 | AX39: =SUM(AV39:AW39) -> 0 | AY39: ='[5]ПП ВДГ'!AY39+'[5]Корсак Л.Р.'!AY39+'[5]Корсак В.І.'!AY39+[5]Конякіна!AY39 -> 0 | AZ39: ='[5]ПП ВДГ'!AZ39+'[5]Корсак Л.Р.'!AZ39+'[5]Корсак В.І.'!AZ39+[5]Конякіна!AZ39 -> 0 | BA39: =SUM(AY39:AZ39) -> 0 | BB39: ='Солар Вест'!BB39+Будник!BB39 -> 0 | BC39: ='Солар Вест'!BC39+Будник!BC39 -> 0 | BD39: =SUM(BB39:BC39) -> 0 | BE39: ='Солар Вест'!BE39+Будник!BE39 -> 0 | BF39: ='Солар Вест'!BF39+Будник!BF39 -> 0 | BG39: =SUM(BE39:BF39) -> 0 | BH39: ='Солар Вест'!BH39+Будник!BH39 -> 0 | BI39: ='Солар Вест'!BI39+Будник!BI39 -> 0 | BJ39: =SUM(BH39:BI39) -> 0 | BK39: ='[5]ПП ВДГ'!BK39+'[5]Корсак Л.Р.'!BK39+'[5]Корсак В.І.'!BK39+[5]Конякіна!BK39 -> 0 | BL39: ='[5]ПП ВДГ'!BL39+'[5]Корсак Л.Р.'!BL39+'[5]Корсак В.І.'!BL39+[5]Конякіна!BL39 -> 0 | BM39: =SUM(BK39:BL39) -> 0 | BN39: ='Солар Вест'!BN39+Будник!BN39 -> 0 | BO39: ='Солар Вест'!BO39+Будник!BO39 -> 0 | BP39: =SUM(BN39:BO39) -> 0 | BQ39: ='[5]ПП ВДГ'!BQ39+'[5]Корсак Л.Р.'!BQ39+'[5]Корсак В.І.'!BQ39+[5]Конякіна!BQ39 -> 0 | BR39: ='[5]ПП ВДГ'!BR39+'[5]Корсак Л.Р.'!BR39+'[5]Корсак В.І.'!BR39+[5]Конякіна!BR39 -> 0 | BS39: =SUM(BQ39:BR39) -> 0 | BT39: ='Солар Вест'!BT39+Будник!BT39 -> 0 | BU39: ='Солар Вест'!BU39+Будник!BU39 -> 0 | BV39: =SUM(BT39:BU39) -> 0 | BW39: =+C39+I39+O39+AA39+AG39+U39+AM39+AS39+AY39+BE39+BK39+BQ39 -> 0 | BX39: =+D39+J39+P39+AB39+AH39+V39+AN39+AT39+AZ39+BF39+BL39+BR39 -> 0 | BY39: =SUM(BW39:BX39) -> 0 | BZ39: =+F39+L39+R39+AD39+AJ39+X39+AP39+AV39+BB39+BH39+BN39+BT39 -> 0 | CA39: =+G39+M39+S39+AE39+AK39+Y39+AQ39+AW39+BC39+BI39+BO39+BU39 -> 0 | CB39: =SUM(BZ39:CA39) -> 0
A40: 124.2 | B40: в т.ч. відсотки РФБА інший (кредитна лінія, овердрафт, авто) | C40: ='[5]ПП ВДГ'!C40+'[5]Корсак Л.Р.'!C40+'[5]Корсак В.І.'!C40+[5]Конякіна!C40 -> 0 | D40: ='[5]ПП ВДГ'!D40+'[5]Корсак Л.Р.'!D40+'[5]Корсак В.І.'!D40+[5]Конякіна!D40 -> 0 | E40: =SUM(C40:D40) -> 0 | F40: ='Солар Вест'!F40+Будник!F40 -> 0 | G40: ='Солар Вест'!G40+Будник!G40 -> 0 | H40: =SUM(F40:G40) -> 0 | I40: ='[5]ПП ВДГ'!I40+'[5]Корсак Л.Р.'!I40+'[5]Корсак В.І.'!I40+[5]Конякіна!I40 -> 0 | J40: ='[5]ПП ВДГ'!J40+'[5]Корсак Л.Р.'!J40+'[5]Корсак В.І.'!J40+[5]Конякіна!J40 -> 0 | K40: =SUM(I40:J40) -> 0 | L40: ='Солар Вест'!L40+Будник!L40 -> 0 | M40: ='Солар Вест'!M40+Будник!M40 -> 0 | N40: =SUM(L40:M40) -> 0 | O40: ='[5]ПП ВДГ'!O40+'[5]Корсак Л.Р.'!O40+'[5]Корсак В.І.'!O40+[5]Конякіна!O40 -> 0 | P40: ='[5]ПП ВДГ'!P40+'[5]Корсак Л.Р.'!P40+'[5]Корсак В.І.'!P40+[5]Конякіна!P40 -> 0 | Q40: =SUM(O40:P40) -> 0 | R40: ='Солар Вест'!R40+Будник!R40 -> 0 | S40: ='Солар Вест'!S40+Будник!S40 -> 0 | T40: =SUM(R40:S40) -> 0 | U40: ='[5]ПП ВДГ'!U40+'[5]Корсак Л.Р.'!U40+'[5]Корсак В.І.'!U40+[5]Конякіна!U40 -> 0 | V40: ='[5]ПП ВДГ'!V40+'[5]Корсак Л.Р.'!V40+'[5]Корсак В.І.'!V40+[5]Конякіна!V40 -> 0 | W40: =SUM(U40:V40) -> 0 | X40: ='Солар Вест'!X40+Будник!X40 -> 0 | Y40: ='Солар Вест'!Y40+Будник!Y40 -> 0 | Z40: =SUM(X40:Y40) -> 0 | AA40: ='[5]ПП ВДГ'!AA40+'[5]Корсак Л.Р.'!AA40+'[5]Корсак В.І.'!AA40+[5]Конякіна!AA40 -> 0 | AB40: ='[5]ПП ВДГ'!AB40+'[5]Корсак Л.Р.'!AB40+'[5]Корсак В.І.'!AB40+[5]Конякіна!AB40 -> 0 | AC40: =SUM(AA40:AB40) -> 0 | AD40: ='Солар Вест'!AD40+Будник!AD40 -> 0 | AE40: ='Солар Вест'!AE40+Будник!AE40 -> 0 | AF40: =SUM(AD40:AE40) -> 0 | AG40: ='[5]ПП ВДГ'!AG40+'[5]Корсак Л.Р.'!AG40+'[5]Корсак В.І.'!AG40+[5]Конякіна!AG40 -> 0 | AH40: ='[5]ПП ВДГ'!AH40+'[5]Корсак Л.Р.'!AH40+'[5]Корсак В.І.'!AH40+[5]Конякіна!AH40 -> 0 | AI40: =SUM(AG40:AH40) -> 0 | AJ40: ='Солар Вест'!AJ40+Будник!AJ40 -> 0 | AK40: ='Солар Вест'!AK40+Будник!AK40 -> 0 | AL40: =SUM(AJ40:AK40) -> 0 | AM40: ='[5]ПП ВДГ'!AM40+'[5]Корсак Л.Р.'!AM40+'[5]Корсак В.І.'!AM40+[5]Конякіна!AM40 -> 0 | AN40: ='[5]ПП ВДГ'!AN40+'[5]Корсак Л.Р.'!AN40+'[5]Корсак В.І.'!AN40+[5]Конякіна!AN40 -> 0 | AO40: =SUM(AM40:AN40) -> 0 | AP40: ='Солар Вест'!AP40+Будник!AP40 -> 0 | AQ40: ='Солар Вест'!AQ40+Будник!AQ40 -> 0 | AR40: =SUM(AP40:AQ40) -> 0 | AS40: ='[5]ПП ВДГ'!AS40+'[5]Корсак Л.Р.'!AS40+'[5]Корсак В.І.'!AS40+[5]Конякіна!AS40 -> 0 | AT40: ='[5]ПП ВДГ'!AT40+'[5]Корсак Л.Р.'!AT40+'[5]Корсак В.І.'!AT40+[5]Конякіна!AT40 -> 0 | AU40: =SUM(AS40:AT40) -> 0 | AV40: ='Солар Вест'!AV40+Будник!AV40 -> 0 | AW40: ='Солар Вест'!AW40+Будник!AW40 -> 0 | AX40: =SUM(AV40:AW40) -> 0 | AY40: ='[5]ПП ВДГ'!AY40+'[5]Корсак Л.Р.'!AY40+'[5]Корсак В.І.'!AY40+[5]Конякіна!AY40 -> 0 | AZ40: ='[5]ПП ВДГ'!AZ40+'[5]Корсак Л.Р.'!AZ40+'[5]Корсак В.І.'!AZ40+[5]Конякіна!AZ40 -> 0 | BA40: =SUM(AY40:AZ40) -> 0 | BB40: ='Солар Вест'!BB40+Будник!BB40 -> 0 | BC40: ='Солар Вест'!BC40+Будник!BC40 -> 0 | BD40: =SUM(BB40:BC40) -> 0 | BE40: ='Солар Вест'!BE40+Будник!BE40 -> 0 | BF40: ='Солар Вест'!BF40+Будник!BF40 -> 0 | BG40: =SUM(BE40:BF40) -> 0 | BH40: ='Солар Вест'!BH40+Будник!BH40 -> 0 | BI40: ='Солар Вест'!BI40+Будник!BI40 -> 0 | BJ40: =SUM(BH40:BI40) -> 0 | BK40: ='[5]ПП ВДГ'!BK40+'[5]Корсак Л.Р.'!BK40+'[5]Корсак В.І.'!BK40+[5]Конякіна!BK40 -> 0 | BL40: ='[5]ПП ВДГ'!BL40+'[5]Корсак Л.Р.'!BL40+'[5]Корсак В.І.'!BL40+[5]Конякіна!BL40 -> 0 | BM40: =SUM(BK40:BL40) -> 0 | BN40: ='Солар Вест'!BN40+Будник!BN40 -> 0 | BO40: ='Солар Вест'!BO40+Будник!BO40 -> 0 | BP40: =SUM(BN40:BO40) -> 0 | BQ40: ='[5]ПП ВДГ'!BQ40+'[5]Корсак Л.Р.'!BQ40+'[5]Корсак В.І.'!BQ40+[5]Конякіна!BQ40 -> 0 | BR40: ='[5]ПП ВДГ'!BR40+'[5]Корсак Л.Р.'!BR40+'[5]Корсак В.І.'!BR40+[5]Конякіна!BR40 -> 0 | BS40: =SUM(BQ40:BR40) -> 0 | BT40: ='Солар Вест'!BT40+Будник!BT40 -> 0 | BU40: ='Солар Вест'!BU40+Будник!BU40 -> 0 | BV40: =SUM(BT40:BU40) -> 0 | BW40: =+C40+I40+O40+AA40+AG40+U40+AM40+AS40+AY40+BE40+BK40+BQ40 -> 0 | BX40: =+D40+J40+P40+AB40+AH40+V40+AN40+AT40+AZ40+BF40+BL40+BR40 -> 0 | BY40: =SUM(BW40:BX40) -> 0 | BZ40: =+F40+L40+R40+AD40+AJ40+X40+AP40+AV40+BB40+BH40+BN40+BT40 -> 0 | CA40: =+G40+M40+S40+AE40+AK40+Y40+AQ40+AW40+BC40+BI40+BO40+BU40 -> 0 | CB40: =SUM(BZ40:CA40) -> 0
A41: 124.5 | B41: в т.ч. відсотки інших банків іпотечні | C41: ='[5]ПП ВДГ'!C41+'[5]Корсак Л.Р.'!C41+'[5]Корсак В.І.'!C41+[5]Конякіна!C41 -> 0 | D41: ='[5]ПП ВДГ'!D41+'[5]Корсак Л.Р.'!D41+'[5]Корсак В.І.'!D41+[5]Конякіна!D41 -> 0 | E41: =SUM(C41:D41) -> 0 | F41: ='Солар Вест'!F41+Будник!F41 -> 0 | G41: ='Солар Вест'!G41+Будник!G41 -> 0 | H41: =SUM(F41:G41) -> 0 | I41: ='[5]ПП ВДГ'!I41+'[5]Корсак Л.Р.'!I41+'[5]Корсак В.І.'!I41+[5]Конякіна!I41 -> 0 | J41: ='[5]ПП ВДГ'!J41+'[5]Корсак Л.Р.'!J41+'[5]Корсак В.І.'!J41+[5]Конякіна!J41 -> 0 | K41: =SUM(I41:J41) -> 0 | L41: ='Солар Вест'!L41+Будник!L41 -> 0 | M41: ='Солар Вест'!M41+Будник!M41 -> 0 | N41: =SUM(L41:M41) -> 0 | O41: ='[5]ПП ВДГ'!O41+'[5]Корсак Л.Р.'!O41+'[5]Корсак В.І.'!O41+[5]Конякіна!O41 -> 0 | P41: ='[5]ПП ВДГ'!P41+'[5]Корсак Л.Р.'!P41+'[5]Корсак В.І.'!P41+[5]Конякіна!P41 -> 0 | Q41: =SUM(O41:P41) -> 0 | R41: ='Солар Вест'!R41+Будник!R41 -> 0 | S41: ='Солар Вест'!S41+Будник!S41 -> 0 | T41: =SUM(R41:S41) -> 0 | U41: ='[5]ПП ВДГ'!U41+'[5]Корсак Л.Р.'!U41+'[5]Корсак В.І.'!U41+[5]Конякіна!U41 -> 10000 | V41: ='[5]ПП ВДГ'!V41+'[5]Корсак Л.Р.'!V41+'[5]Корсак В.І.'!V41+[5]Конякіна!V41 -> 0 | W41: =SUM(U41:V41) -> 10000 | X41: ='Солар Вест'!X41+Будник!X41 -> 0 | Y41: ='Солар Вест'!Y41+Будник!Y41 -> 0 | Z41: =SUM(X41:Y41) -> 0 | AA41: ='[5]ПП ВДГ'!AA41+'[5]Корсак Л.Р.'!AA41+'[5]Корсак В.І.'!AA41+[5]Конякіна!AA41 -> 0 | AB41: ='[5]ПП ВДГ'!AB41+'[5]Корсак Л.Р.'!AB41+'[5]Корсак В.І.'!AB41+[5]Конякіна!AB41 -> 0 | AC41: =SUM(AA41:AB41) -> 0 | AD41: ='Солар Вест'!AD41+Будник!AD41 -> 0 | AE41: ='Солар Вест'!AE41+Будник!AE41 -> 0 | AF41: =SUM(AD41:AE41) -> 0 | AG41: ='[5]ПП ВДГ'!AG41+'[5]Корсак Л.Р.'!AG41+'[5]Корсак В.І.'!AG41+[5]Конякіна!AG41 -> 0 | AH41: ='[5]ПП ВДГ'!AH41+'[5]Корсак Л.Р.'!AH41+'[5]Корсак В.І.'!AH41+[5]Конякіна!AH41 -> 0 | AI41: =SUM(AG41:AH41) -> 0 | AJ41: ='Солар Вест'!AJ41+Будник!AJ41 -> 0 | AK41: ='Солар Вест'!AK41+Будник!AK41 -> 0 | AL41: =SUM(AJ41:AK41) -> 0 | AM41: ='[5]ПП ВДГ'!AM41+'[5]Корсак Л.Р.'!AM41+'[5]Корсак В.І.'!AM41+[5]Конякіна!AM41 -> 0 | AN41: ='[5]ПП ВДГ'!AN41+'[5]Корсак Л.Р.'!AN41+'[5]Корсак В.І.'!AN41+[5]Конякіна!AN41 -> 0 | AO41: =SUM(AM41:AN41) -> 0 | AP41: ='Солар Вест'!AP41+Будник!AP41 -> 0 | AQ41: ='Солар Вест'!AQ41+Будник!AQ41 -> 0 | AR41: =SUM(AP41:AQ41) -> 0 | AS41: ='[5]ПП ВДГ'!AS41+'[5]Корсак Л.Р.'!AS41+'[5]Корсак В.І.'!AS41+[5]Конякіна!AS41 -> 0 | AT41: ='[5]ПП ВДГ'!AT41+'[5]Корсак Л.Р.'!AT41+'[5]Корсак В.І.'!AT41+[5]Конякіна!AT41 -> 0 | AU41: =SUM(AS41:AT41) -> 0 | AV41: ='Солар Вест'!AV41+Будник!AV41 -> 0 | AW41: ='Солар Вест'!AW41+Будник!AW41 -> 0 | AX41: =SUM(AV41:AW41) -> 0 | AY41: ='[5]ПП ВДГ'!AY41+'[5]Корсак Л.Р.'!AY41+'[5]Корсак В.І.'!AY41+[5]Конякіна!AY41 -> 0 | AZ41: ='[5]ПП ВДГ'!AZ41+'[5]Корсак Л.Р.'!AZ41+'[5]Корсак В.І.'!AZ41+[5]Конякіна!AZ41 -> 0 | BA41: =SUM(AY41:AZ41) -> 0 | BB41: ='Солар Вест'!BB41+Будник!BB41 -> 0 | BC41: ='Солар Вест'!BC41+Будник!BC41 -> 0 | BD41: =SUM(BB41:BC41) -> 0 | BE41: ='Солар Вест'!BE41+Будник!BE41 -> 0 | BF41: ='Солар Вест'!BF41+Будник!BF41 -> 0 | BG41: =SUM(BE41:BF41) -> 0 | BH41: ='Солар Вест'!BH41+Будник!BH41 -> 0 | BI41: ='Солар Вест'!BI41+Будник!BI41 -> 0 | BJ41: =SUM(BH41:BI41) -> 0 | BK41: ='[5]ПП ВДГ'!BK41+'[5]Корсак Л.Р.'!BK41+'[5]Корсак В.І.'!BK41+[5]Конякіна!BK41 -> 0 | BL41: ='[5]ПП ВДГ'!BL41+'[5]Корсак Л.Р.'!BL41+'[5]Корсак В.І.'!BL41+[5]Конякіна!BL41 -> 0 | BM41: =SUM(BK41:BL41) -> 0 | BN41: ='Солар Вест'!BN41+Будник!BN41 -> 0 | BO41: ='Солар Вест'!BO41+Будник!BO41 -> 0 | BP41: =SUM(BN41:BO41) -> 0 | BQ41: ='[5]ПП ВДГ'!BQ41+'[5]Корсак Л.Р.'!BQ41+'[5]Корсак В.І.'!BQ41+[5]Конякіна!BQ41 -> 0 | BR41: ='[5]ПП ВДГ'!BR41+'[5]Корсак Л.Р.'!BR41+'[5]Корсак В.І.'!BR41+[5]Конякіна!BR41 -> 0 | BS41: =SUM(BQ41:BR41) -> 0 | BT41: ='Солар Вест'!BT41+Будник!BT41 -> 0 | BU41: ='Солар Вест'!BU41+Будник!BU41 -> 0 | BV41: =SUM(BT41:BU41) -> 0 | BW41: =+C41+I41+O41+AA41+AG41+U41+AM41+AS41+AY41+BE41+BK41+BQ41 -> 10000 | BX41: =+D41+J41+P41+AB41+AH41+V41+AN41+AT41+AZ41+BF41+BL41+BR41 -> 0 | BY41: =SUM(BW41:BX41) -> 10000 | BZ41: =+F41+L41+R41+AD41+AJ41+X41+AP41+AV41+BB41+BH41+BN41+BT41 -> 0 | CA41: =+G41+M41+S41+AE41+AK41+Y41+AQ41+AW41+BC41+BI41+BO41+BU41 -> 0 | CB41: =SUM(BZ41:CA41) -> 0
A42: 124.6 | B42: в т.ч. відсотки інших банків (кредитна лінія, овердрафт, авто) | C42: ='[5]ПП ВДГ'!C42+'[5]Корсак Л.Р.'!C42+'[5]Корсак В.І.'!C42+[5]Конякіна!C42 -> 0 | D42: ='[5]ПП ВДГ'!D42+'[5]Корсак Л.Р.'!D42+'[5]Корсак В.І.'!D42+[5]Конякіна!D42 -> 0 | E42: =SUM(C42:D42) -> 0 | F42: ='Солар Вест'!F42+Будник!F42 -> 0 | G42: ='Солар Вест'!G42+Будник!G42 -> 0 | H42: =SUM(F42:G42) -> 0 | I42: ='[5]ПП ВДГ'!I42+'[5]Корсак Л.Р.'!I42+'[5]Корсак В.І.'!I42+[5]Конякіна!I42 -> 0 | J42: ='[5]ПП ВДГ'!J42+'[5]Корсак Л.Р.'!J42+'[5]Корсак В.І.'!J42+[5]Конякіна!J42 -> 0 | K42: =SUM(I42:J42) -> 0 | L42: ='Солар Вест'!L42+Будник!L42 -> 0 | M42: ='Солар Вест'!M42+Будник!M42 -> 0 | N42: =SUM(L42:M42) -> 0 | O42: ='[5]ПП ВДГ'!O42+'[5]Корсак Л.Р.'!O42+'[5]Корсак В.І.'!O42+[5]Конякіна!O42 -> 0 | P42: ='[5]ПП ВДГ'!P42+'[5]Корсак Л.Р.'!P42+'[5]Корсак В.І.'!P42+[5]Конякіна!P42 -> 0 | Q42: =SUM(O42:P42) -> 0 | R42: ='Солар Вест'!R42+Будник!R42 -> 0 | S42: ='Солар Вест'!S42+Будник!S42 -> 0 | T42: =SUM(R42:S42) -> 0 | U42: ='[5]ПП ВДГ'!U42+'[5]Корсак Л.Р.'!U42+'[5]Корсак В.І.'!U42+[5]Конякіна!U42 -> 2210 | V42: ='[5]ПП ВДГ'!V42+'[5]Корсак Л.Р.'!V42+'[5]Корсак В.І.'!V42+[5]Конякіна!V42 -> 0 | W42: =SUM(U42:V42) -> 2210 | X42: ='Солар Вест'!X42+Будник!X42 -> 0 | Y42: ='Солар Вест'!Y42+Будник!Y42 -> 0 | Z42: =SUM(X42:Y42) -> 0 | AA42: ='[5]ПП ВДГ'!AA42+'[5]Корсак Л.Р.'!AA42+'[5]Корсак В.І.'!AA42+[5]Конякіна!AA42 -> 2596 | AB42: ='[5]ПП ВДГ'!AB42+'[5]Корсак Л.Р.'!AB42+'[5]Корсак В.І.'!AB42+[5]Конякіна!AB42 -> 0 | AC42: =SUM(AA42:AB42) -> 2596 | AD42: ='Солар Вест'!AD42+Будник!AD42 -> 0 | AE42: ='Солар Вест'!AE42+Будник!AE42 -> 0 | AF42: =SUM(AD42:AE42) -> 0 | AG42: ='[5]ПП ВДГ'!AG42+'[5]Корсак Л.Р.'!AG42+'[5]Корсак В.І.'!AG42+[5]Конякіна!AG42 -> 2554 | AH42: ='[5]ПП ВДГ'!AH42+'[5]Корсак Л.Р.'!AH42+'[5]Корсак В.І.'!AH42+[5]Конякіна!AH42 -> 0 | AI42: =SUM(AG42:AH42) -> 2554 | AJ42: ='Солар Вест'!AJ42+Будник!AJ42 -> 0 | AK42: ='Солар Вест'!AK42+Будник!AK42 -> 0 | AL42: =SUM(AJ42:AK42) -> 0 | AM42: ='[5]ПП ВДГ'!AM42+'[5]Корсак Л.Р.'!AM42+'[5]Корсак В.І.'!AM42+[5]Конякіна!AM42 -> 2514 | AN42: ='[5]ПП ВДГ'!AN42+'[5]Корсак Л.Р.'!AN42+'[5]Корсак В.І.'!AN42+[5]Конякіна!AN42 -> 0 | AO42: =SUM(AM42:AN42) -> 2514 | AP42: ='Солар Вест'!AP42+Будник!AP42 -> 0 | AQ42: ='Солар Вест'!AQ42+Будник!AQ42 -> 0 | AR42: =SUM(AP42:AQ42) -> 0 | AS42: ='[5]ПП ВДГ'!AS42+'[5]Корсак Л.Р.'!AS42+'[5]Корсак В.І.'!AS42+[5]Конякіна!AS42 -> 2475 | AT42: ='[5]ПП ВДГ'!AT42+'[5]Корсак Л.Р.'!AT42+'[5]Корсак В.І.'!AT42+[5]Конякіна!AT42 -> 0 | AU42: =SUM(AS42:AT42) -> 2475 | AV42: ='Солар Вест'!AV42+Будник!AV42 -> 0 | AW42: ='Солар Вест'!AW42+Будник!AW42 -> 0 | AX42: =SUM(AV42:AW42) -> 0 | AY42: ='[5]ПП ВДГ'!AY42+'[5]Корсак Л.Р.'!AY42+'[5]Корсак В.І.'!AY42+[5]Конякіна!AY42 -> 0 | AZ42: ='[5]ПП ВДГ'!AZ42+'[5]Корсак Л.Р.'!AZ42+'[5]Корсак В.І.'!AZ42+[5]Конякіна!AZ42 -> 0 | BA42: =SUM(AY42:AZ42) -> 0 | BB42: ='Солар Вест'!BB42+Будник!BB42 -> 0 | BC42: ='Солар Вест'!BC42+Будник!BC42 -> 0 | BD42: =SUM(BB42:BC42) -> 0 | BE42: ='Солар Вест'!BE42+Будник!BE42 -> 0 | BF42: ='Солар Вест'!BF42+Будник!BF42 -> 0 | BG42: =SUM(BE42:BF42) -> 0 | BH42: ='Солар Вест'!BH42+Будник!BH42 -> 0 | BI42: ='Солар Вест'!BI42+Будник!BI42 -> 0 | BJ42: =SUM(BH42:BI42) -> 0 | BK42: ='[5]ПП ВДГ'!BK42+'[5]Корсак Л.Р.'!BK42+'[5]Корсак В.І.'!BK42+[5]Конякіна!BK42 -> 2366 | BL42: ='[5]ПП ВДГ'!BL42+'[5]Корсак Л.Р.'!BL42+'[5]Корсак В.І.'!BL42+[5]Конякіна!BL42 -> 0 | BM42: =SUM(BK42:BL42) -> 2366 | BN42: ='Солар Вест'!BN42+Будник!BN42 -> 0 | BO42: ='Солар Вест'!BO42+Будник!BO42 -> 0 | BP42: =SUM(BN42:BO42) -> 0 | BQ42: ='[5]ПП ВДГ'!BQ42+'[5]Корсак Л.Р.'!BQ42+'[5]Корсак В.І.'!BQ42+[5]Конякіна!BQ42 -> 2332 | BR42: ='[5]ПП ВДГ'!BR42+'[5]Корсак Л.Р.'!BR42+'[5]Корсак В.І.'!BR42+[5]Конякіна!BR42 -> 0 | BS42: =SUM(BQ42:BR42) -> 2332 | BT42: ='Солар Вест'!BT42+Будник!BT42 -> 0 | BU42: ='Солар Вест'!BU42+Будник!BU42 -> 0 | BV42: =SUM(BT42:BU42) -> 0 | BW42: =+C42+I42+O42+AA42+AG42+U42+AM42+AS42+AY42+BE42+BK42+BQ42 -> 17047 | BX42: =+D42+J42+P42+AB42+AH42+V42+AN42+AT42+AZ42+BF42+BL42+BR42 -> 0 | BY42: =SUM(BW42:BX42) -> 17047 | BZ42: =+F42+L42+R42+AD42+AJ42+X42+AP42+AV42+BB42+BH42+BN42+BT42 -> 0 | CA42: =+G42+M42+S42+AE42+AK42+Y42+AQ42+AW42+BC42+BI42+BO42+BU42 -> 0 | CB42: =SUM(BZ42:CA42) -> 0
A43: 125 | B43: Відсотки по кредитах внутрішніх | C43: ='[5]ПП ВДГ'!C43+'[5]Корсак Л.Р.'!C43+'[5]Корсак В.І.'!C43+[5]Конякіна!C43 -> 0 | D43: ='[5]ПП ВДГ'!D43+'[5]Корсак Л.Р.'!D43+'[5]Корсак В.І.'!D43+[5]Конякіна!D43 -> 0 | E43: =SUM(C43:D43) -> 0 | F43: ='Солар Вест'!F43+Будник!F43 -> 0 | G43: ='Солар Вест'!G43+Будник!G43 -> 0 | H43: =SUM(F43:G43) -> 0 | I43: ='[5]ПП ВДГ'!I43+'[5]Корсак Л.Р.'!I43+'[5]Корсак В.І.'!I43+[5]Конякіна!I43 -> 0 | J43: ='[5]ПП ВДГ'!J43+'[5]Корсак Л.Р.'!J43+'[5]Корсак В.І.'!J43+[5]Конякіна!J43 -> 0 | K43: =SUM(I43:J43) -> 0 | L43: ='Солар Вест'!L43+Будник!L43 -> 0 | M43: ='Солар Вест'!M43+Будник!M43 -> 0 | N43: =SUM(L43:M43) -> 0 | O43: ='[5]ПП ВДГ'!O43+'[5]Корсак Л.Р.'!O43+'[5]Корсак В.І.'!O43+[5]Конякіна!O43 -> 0 | P43: ='[5]ПП ВДГ'!P43+'[5]Корсак Л.Р.'!P43+'[5]Корсак В.І.'!P43+[5]Конякіна!P43 -> 0 | Q43: =SUM(O43:P43) -> 0 | R43: ='Солар Вест'!R43+Будник!R43 -> 0 | S43: ='Солар Вест'!S43+Будник!S43 -> 0 | T43: =SUM(R43:S43) -> 0 | U43: ='[5]ПП ВДГ'!U43+'[5]Корсак Л.Р.'!U43+'[5]Корсак В.І.'!U43+[5]Конякіна!U43 -> 0 | V43: ='[5]ПП ВДГ'!V43+'[5]Корсак Л.Р.'!V43+'[5]Корсак В.І.'!V43+[5]Конякіна!V43 -> 0 | W43: =SUM(U43:V43) -> 0 | X43: ='Солар Вест'!X43+Будник!X43 -> 0 | Y43: ='Солар Вест'!Y43+Будник!Y43 -> 0 | Z43: =SUM(X43:Y43) -> 0 | AA43: ='[5]ПП ВДГ'!AA43+'[5]Корсак Л.Р.'!AA43+'[5]Корсак В.І.'!AA43+[5]Конякіна!AA43 -> 0 | AB43: ='[5]ПП ВДГ'!AB43+'[5]Корсак Л.Р.'!AB43+'[5]Корсак В.І.'!AB43+[5]Конякіна!AB43 -> 0 | AC43: =SUM(AA43:AB43) -> 0 | AD43: ='Солар Вест'!AD43+Будник!AD43 -> 0 | AE43: ='Солар Вест'!AE43+Будник!AE43 -> 0 | AF43: =SUM(AD43:AE43) -> 0 | AG43: ='[5]ПП ВДГ'!AG43+'[5]Корсак Л.Р.'!AG43+'[5]Корсак В.І.'!AG43+[5]Конякіна!AG43 -> 0 | AH43: ='[5]ПП ВДГ'!AH43+'[5]Корсак Л.Р.'!AH43+'[5]Корсак В.І.'!AH43+[5]Конякіна!AH43 -> 0 | AI43: =SUM(AG43:AH43) -> 0 | AJ43: ='Солар Вест'!AJ43+Будник!AJ43 -> 0 | AK43: ='Солар Вест'!AK43+Будник!AK43 -> 0 | AL43: =SUM(AJ43:AK43) -> 0 | AM43: ='[5]ПП ВДГ'!AM43+'[5]Корсак Л.Р.'!AM43+'[5]Корсак В.І.'!AM43+[5]Конякіна!AM43 -> 0 | AN43: ='[5]ПП ВДГ'!AN43+'[5]Корсак Л.Р.'!AN43+'[5]Корсак В.І.'!AN43+[5]Конякіна!AN43 -> 0 | AO43: =SUM(AM43:AN43) -> 0 | AP43: ='Солар Вест'!AP43+Будник!AP43 -> 0 | AQ43: ='Солар Вест'!AQ43+Будник!AQ43 -> 0 | AR43: =SUM(AP43:AQ43) -> 0 | AS43: ='[5]ПП ВДГ'!AS43+'[5]Корсак Л.Р.'!AS43+'[5]Корсак В.І.'!AS43+[5]Конякіна!AS43 -> 0 | AT43: ='[5]ПП ВДГ'!AT43+'[5]Корсак Л.Р.'!AT43+'[5]Корсак В.І.'!AT43+[5]Конякіна!AT43 -> 0 | AU43: =SUM(AS43:AT43) -> 0 | AV43: ='Солар Вест'!AV43+Будник!AV43 -> 0 | AW43: ='Солар Вест'!AW43+Будник!AW43 -> 0 | AX43: =SUM(AV43:AW43) -> 0 | AY43: ='[5]ПП ВДГ'!AY43+'[5]Корсак Л.Р.'!AY43+'[5]Корсак В.І.'!AY43+[5]Конякіна!AY43 -> 0 | AZ43: ='[5]ПП ВДГ'!AZ43+'[5]Корсак Л.Р.'!AZ43+'[5]Корсак В.І.'!AZ43+[5]Конякіна!AZ43 -> 0 | BA43: =SUM(AY43:AZ43) -> 0 | BB43: ='Солар Вест'!BB43+Будник!BB43 -> 0 | BC43: ='Солар Вест'!BC43+Будник!BC43 -> 0 | BD43: =SUM(BB43:BC43) -> 0 | BE43: ='Солар Вест'!BE43+Будник!BE43 -> 0 | BF43: ='Солар Вест'!BF43+Будник!BF43 -> 0 | BG43: =SUM(BE43:BF43) -> 0 | BH43: ='Солар Вест'!BH43+Будник!BH43 -> 0 | BI43: ='Солар Вест'!BI43+Будник!BI43 -> 0 | BJ43: =SUM(BH43:BI43) -> 0 | BK43: ='[5]ПП ВДГ'!BK43+'[5]Корсак Л.Р.'!BK43+'[5]Корсак В.І.'!BK43+[5]Конякіна!BK43 -> 0 | BL43: ='[5]ПП ВДГ'!BL43+'[5]Корсак Л.Р.'!BL43+'[5]Корсак В.І.'!BL43+[5]Конякіна!BL43 -> 0 | BM43: =SUM(BK43:BL43) -> 0 | BN43: ='Солар Вест'!BN43+Будник!BN43 -> 0 | BO43: ='Солар Вест'!BO43+Будник!BO43 -> 0 | BP43: =SUM(BN43:BO43) -> 0 | BQ43: ='[5]ПП ВДГ'!BQ43+'[5]Корсак Л.Р.'!BQ43+'[5]Корсак В.І.'!BQ43+[5]Конякіна!BQ43 -> 0 | BR43: ='[5]ПП ВДГ'!BR43+'[5]Корсак Л.Р.'!BR43+'[5]Корсак В.І.'!BR43+[5]Конякіна!BR43 -> 0 | BS43: =SUM(BQ43:BR43) -> 0 | BT43: ='Солар Вест'!BT43+Будник!BT43 -> 0 | BU43: ='Солар Вест'!BU43+Будник!BU43 -> 0 | BV43: =SUM(BT43:BU43) -> 0 | BW43: =+C43+I43+O43+AA43+AG43+U43+AM43+AS43+AY43+BE43+BK43+BQ43 -> 0 | BX43: =+D43+J43+P43+AB43+AH43+V43+AN43+AT43+AZ43+BF43+BL43+BR43 -> 0 | BY43: =SUM(BW43:BX43) -> 0 | BZ43: =+F43+L43+R43+AD43+AJ43+X43+AP43+AV43+BB43+BH43+BN43+BT43 -> 0 | CA43: =+G43+M43+S43+AE43+AK43+Y43+AQ43+AW43+BC43+BI43+BO43+BU43 -> 0 | CB43: =SUM(BZ43:CA43) -> 0
A44: 126 | B44: Відсотки по кредитах венчурного фонду | C44: ='[5]ПП ВДГ'!C44+'[5]Корсак Л.Р.'!C44+'[5]Корсак В.І.'!C44+[5]Конякіна!C44 -> 9400 | D44: ='[5]ПП ВДГ'!D44+'[5]Корсак Л.Р.'!D44+'[5]Корсак В.І.'!D44+[5]Конякіна!D44 -> 0 | E44: =SUM(C44:D44) -> 9400 | F44: ='Солар Вест'!F44+Будник!F44 -> 0 | G44: ='Солар Вест'!G44+Будник!G44 -> 0 | H44: =SUM(F44:G44) -> 0 | I44: ='[5]ПП ВДГ'!I44+'[5]Корсак Л.Р.'!I44+'[5]Корсак В.І.'!I44+[5]Конякіна!I44 -> 9100 | J44: ='[5]ПП ВДГ'!J44+'[5]Корсак Л.Р.'!J44+'[5]Корсак В.І.'!J44+[5]Конякіна!J44 -> 0 | K44: =SUM(I44:J44) -> 9100 | L44: ='Солар Вест'!L44+Будник!L44 -> 0 | M44: ='Солар Вест'!M44+Будник!M44 -> 0 | N44: =SUM(L44:M44) -> 0 | O44: ='[5]ПП ВДГ'!O44+'[5]Корсак Л.Р.'!O44+'[5]Корсак В.І.'!O44+[5]Конякіна!O44 -> 8800 | P44: ='[5]ПП ВДГ'!P44+'[5]Корсак Л.Р.'!P44+'[5]Корсак В.І.'!P44+[5]Конякіна!P44 -> 0 | Q44: =SUM(O44:P44) -> 8800 | R44: ='Солар Вест'!R44+Будник!R44 -> 0 | S44: ='Солар Вест'!S44+Будник!S44 -> 0 | T44: =SUM(R44:S44) -> 0 | U44: ='[5]ПП ВДГ'!U44+'[5]Корсак Л.Р.'!U44+'[5]Корсак В.І.'!U44+[5]Конякіна!U44 -> 0 | V44: ='[5]ПП ВДГ'!V44+'[5]Корсак Л.Р.'!V44+'[5]Корсак В.І.'!V44+[5]Конякіна!V44 -> 0 | W44: =SUM(U44:V44) -> 0 | X44: ='Солар Вест'!X44+Будник!X44 -> 0 | Y44: ='Солар Вест'!Y44+Будник!Y44 -> 0 | Z44: =SUM(X44:Y44) -> 0 | AA44: ='[5]ПП ВДГ'!AA44+'[5]Корсак Л.Р.'!AA44+'[5]Корсак В.І.'!AA44+[5]Конякіна!AA44 -> 0 | AB44: ='[5]ПП ВДГ'!AB44+'[5]Корсак Л.Р.'!AB44+'[5]Корсак В.І.'!AB44+[5]Конякіна!AB44 -> 0 | AC44: =SUM(AA44:AB44) -> 0 | AD44: ='Солар Вест'!AD44+Будник!AD44 -> 0 | AE44: ='Солар Вест'!AE44+Будник!AE44 -> 0 | AF44: =SUM(AD44:AE44) -> 0 | AG44: ='[5]ПП ВДГ'!AG44+'[5]Корсак Л.Р.'!AG44+'[5]Корсак В.І.'!AG44+[5]Конякіна!AG44 -> 0 | AH44: ='[5]ПП ВДГ'!AH44+'[5]Корсак Л.Р.'!AH44+'[5]Корсак В.І.'!AH44+[5]Конякіна!AH44 -> 0 | AI44: =SUM(AG44:AH44) -> 0 | AJ44: ='Солар Вест'!AJ44+Будник!AJ44 -> 0 | AK44: ='Солар Вест'!AK44+Будник!AK44 -> 0 | AL44: =SUM(AJ44:AK44) -> 0 | AM44: ='[5]ПП ВДГ'!AM44+'[5]Корсак Л.Р.'!AM44+'[5]Корсак В.І.'!AM44+[5]Конякіна!AM44 -> 0 | AN44: ='[5]ПП ВДГ'!AN44+'[5]Корсак Л.Р.'!AN44+'[5]Корсак В.І.'!AN44+[5]Конякіна!AN44 -> 0 | AO44: =SUM(AM44:AN44) -> 0 | AP44: ='Солар Вест'!AP44+Будник!AP44 -> 0 | AQ44: ='Солар Вест'!AQ44+Будник!AQ44 -> 0 | AR44: =SUM(AP44:AQ44) -> 0 | AS44: ='[5]ПП ВДГ'!AS44+'[5]Корсак Л.Р.'!AS44+'[5]Корсак В.І.'!AS44+[5]Конякіна!AS44 -> 0 | AT44: ='[5]ПП ВДГ'!AT44+'[5]Корсак Л.Р.'!AT44+'[5]Корсак В.І.'!AT44+[5]Конякіна!AT44 -> 0 | AU44: =SUM(AS44:AT44) -> 0 | AV44: ='Солар Вест'!AV44+Будник!AV44 -> 0 | AW44: ='Солар Вест'!AW44+Будник!AW44 -> 0 | AX44: =SUM(AV44:AW44) -> 0 | AY44: ='[5]ПП ВДГ'!AY44+'[5]Корсак Л.Р.'!AY44+'[5]Корсак В.І.'!AY44+[5]Конякіна!AY44 -> 7200 | AZ44: ='[5]ПП ВДГ'!AZ44+'[5]Корсак Л.Р.'!AZ44+'[5]Корсак В.І.'!AZ44+[5]Конякіна!AZ44 -> 0 | BA44: =SUM(AY44:AZ44) -> 7200 | BB44: ='Солар Вест'!BB44+Будник!BB44 -> 0 | BC44: ='Солар Вест'!BC44+Будник!BC44 -> 0 | BD44: =SUM(BB44:BC44) -> 0 | BE44: ='Солар Вест'!BE44+Будник!BE44 -> 0 | BF44: ='Солар Вест'!BF44+Будник!BF44 -> 0 | BG44: =SUM(BE44:BF44) -> 0 | BH44: ='Солар Вест'!BH44+Будник!BH44 -> 0 | BI44: ='Солар Вест'!BI44+Будник!BI44 -> 0 | BJ44: =SUM(BH44:BI44) -> 0 | BK44: ='[5]ПП ВДГ'!BK44+'[5]Корсак Л.Р.'!BK44+'[5]Корсак В.І.'!BK44+[5]Конякіна!BK44 -> 0 | BL44: ='[5]ПП ВДГ'!BL44+'[5]Корсак Л.Р.'!BL44+'[5]Корсак В.І.'!BL44+[5]Конякіна!BL44 -> 0 | BM44: =SUM(BK44:BL44) -> 0 | BN44: ='Солар Вест'!BN44+Будник!BN44 -> 0 | BO44: ='Солар Вест'!BO44+Будник!BO44 -> 0 | BP44: =SUM(BN44:BO44) -> 0 | BQ44: ='[5]ПП ВДГ'!BQ44+'[5]Корсак Л.Р.'!BQ44+'[5]Корсак В.І.'!BQ44+[5]Конякіна!BQ44 -> 0 | BR44: ='[5]ПП ВДГ'!BR44+'[5]Корсак Л.Р.'!BR44+'[5]Корсак В.І.'!BR44+[5]Конякіна!BR44 -> 0 | BS44: =SUM(BQ44:BR44) -> 0 | BT44: ='Солар Вест'!BT44+Будник!BT44 -> 0 | BU44: ='Солар Вест'!BU44+Будник!BU44 -> 0 | BV44: =SUM(BT44:BU44) -> 0 | BW44: =+C44+I44+O44+AA44+AG44+U44+AM44+AS44+AY44+BE44+BK44+BQ44 -> 34500 | BX44: =+D44+J44+P44+AB44+AH44+V44+AN44+AT44+AZ44+BF44+BL44+BR44 -> 0 | BY44: =SUM(BW44:BX44) -> 34500 | BZ44: =+F44+L44+R44+AD44+AJ44+X44+AP44+AV44+BB44+BH44+BN44+BT44 -> 0 | CA44: =+G44+M44+S44+AE44+AK44+Y44+AQ44+AW44+BC44+BI44+BO44+BU44 -> 0 | CB44: =SUM(BZ44:CA44) -> 0
A45: 127 | B45: Енергоресурси та комунальні послуги | C45: ='[5]ПП ВДГ'!C45+'[5]Корсак Л.Р.'!C45+'[5]Корсак В.І.'!C45+[5]Конякіна!C45 -> 70000 | D45: ='[5]ПП ВДГ'!D45+'[5]Корсак Л.Р.'!D45+'[5]Корсак В.І.'!D45+[5]Конякіна!D45 -> 5000 | E45: =SUM(C45:D45) -> 75000 | F45: ='Солар Вест'!F45+Будник!F45 -> 0 | G45: ='Солар Вест'!G45+Будник!G45 -> 0 | H45: =SUM(F45:G45) -> 0 | I45: ='[5]ПП ВДГ'!I45+'[5]Корсак Л.Р.'!I45+'[5]Корсак В.І.'!I45+[5]Конякіна!I45 -> 65000 | J45: ='[5]ПП ВДГ'!J45+'[5]Корсак Л.Р.'!J45+'[5]Корсак В.І.'!J45+[5]Конякіна!J45 -> 0 | K45: =SUM(I45:J45) -> 65000 | L45: ='Солар Вест'!L45+Будник!L45 -> 0 | M45: ='Солар Вест'!M45+Будник!M45 -> 0 | N45: =SUM(L45:M45) -> 0 | O45: ='[5]ПП ВДГ'!O45+'[5]Корсак Л.Р.'!O45+'[5]Корсак В.І.'!O45+[5]Конякіна!O45 -> 65000 | P45: ='[5]ПП ВДГ'!P45+'[5]Корсак Л.Р.'!P45+'[5]Корсак В.І.'!P45+[5]Конякіна!P45 -> 0 | Q45: =SUM(O45:P45) -> 65000 | R45: ='Солар Вест'!R45+Будник!R45 -> 0 | S45: ='Солар Вест'!S45+Будник!S45 -> 0 | T45: =SUM(R45:S45) -> 0 | U45: ='[5]ПП ВДГ'!U45+'[5]Корсак Л.Р.'!U45+'[5]Корсак В.І.'!U45+[5]Конякіна!U45 -> 80000 | V45: ='[5]ПП ВДГ'!V45+'[5]Корсак Л.Р.'!V45+'[5]Корсак В.І.'!V45+[5]Конякіна!V45 -> 0 | W45: =SUM(U45:V45) -> 80000 | X45: ='Солар Вест'!X45+Будник!X45 -> 0 | Y45: ='Солар Вест'!Y45+Будник!Y45 -> 0 | Z45: =SUM(X45:Y45) -> 0 | AA45: ='[5]ПП ВДГ'!AA45+'[5]Корсак Л.Р.'!AA45+'[5]Корсак В.І.'!AA45+[5]Конякіна!AA45 -> 60000 | AB45: ='[5]ПП ВДГ'!AB45+'[5]Корсак Л.Р.'!AB45+'[5]Корсак В.І.'!AB45+[5]Конякіна!AB45 -> 0 | AC45: =SUM(AA45:AB45) -> 60000 | AD45: ='Солар Вест'!AD45+Будник!AD45 -> 0 | AE45: ='Солар Вест'!AE45+Будник!AE45 -> 0 | AF45: =SUM(AD45:AE45) -> 0 | AG45: ='[5]ПП ВДГ'!AG45+'[5]Корсак Л.Р.'!AG45+'[5]Корсак В.І.'!AG45+[5]Конякіна!AG45 -> 60000 | AH45: ='[5]ПП ВДГ'!AH45+'[5]Корсак Л.Р.'!AH45+'[5]Корсак В.І.'!AH45+[5]Конякіна!AH45 -> 0 | AI45: =SUM(AG45:AH45) -> 60000 | AJ45: ='Солар Вест'!AJ45+Будник!AJ45 -> 0 | AK45: ='Солар Вест'!AK45+Будник!AK45 -> 0 | AL45: =SUM(AJ45:AK45) -> 0 | AM45: ='[5]ПП ВДГ'!AM45+'[5]Корсак Л.Р.'!AM45+'[5]Корсак В.І.'!AM45+[5]Конякіна!AM45 -> 60000 | AN45: ='[5]ПП ВДГ'!AN45+'[5]Корсак Л.Р.'!AN45+'[5]Корсак В.І.'!AN45+[5]Конякіна!AN45 -> 0 | AO45: =SUM(AM45:AN45) -> 60000 | AP45: ='Солар Вест'!AP45+Будник!AP45 -> 0 | AQ45: ='Солар Вест'!AQ45+Будник!AQ45 -> 0 | AR45: =SUM(AP45:AQ45) -> 0 | AS45: ='[5]ПП ВДГ'!AS45+'[5]Корсак Л.Р.'!AS45+'[5]Корсак В.І.'!AS45+[5]Конякіна!AS45 -> 60000 | AT45: ='[5]ПП ВДГ'!AT45+'[5]Корсак Л.Р.'!AT45+'[5]Корсак В.І.'!AT45+[5]Конякіна!AT45 -> 0 | AU45: =SUM(AS45:AT45) -> 60000 | AV45: ='Солар Вест'!AV45+Будник!AV45 -> 0 | AW45: ='Солар Вест'!AW45+Будник!AW45 -> 0 | AX45: =SUM(AV45:AW45) -> 0 | AY45: ='[5]ПП ВДГ'!AY45+'[5]Корсак Л.Р.'!AY45+'[5]Корсак В.І.'!AY45+[5]Конякіна!AY45 -> 60000 | AZ45: ='[5]ПП ВДГ'!AZ45+'[5]Корсак Л.Р.'!AZ45+'[5]Корсак В.І.'!AZ45+[5]Конякіна!AZ45 -> 0 | BA45: =SUM(AY45:AZ45) -> 60000 | BB45: ='Солар Вест'!BB45+Будник!BB45 -> 0 | BC45: ='Солар Вест'!BC45+Будник!BC45 -> 0 | BD45: =SUM(BB45:BC45) -> 0 | BE45: ='Солар Вест'!BE45+Будник!BE45 -> 0 | BF45: ='Солар Вест'!BF45+Будник!BF45 -> 0 | BG45: =SUM(BE45:BF45) -> 0 | BH45: ='Солар Вест'!BH45+Будник!BH45 -> 0 | BI45: ='Солар Вест'!BI45+Будник!BI45 -> 0 | BJ45: =SUM(BH45:BI45) -> 0 | BK45: ='[5]ПП ВДГ'!BK45+'[5]Корсак Л.Р.'!BK45+'[5]Корсак В.І.'!BK45+[5]Конякіна!BK45 -> 65000 | BL45: ='[5]ПП ВДГ'!BL45+'[5]Корсак Л.Р.'!BL45+'[5]Корсак В.І.'!BL45+[5]Конякіна!BL45 -> 5000 | BM45: =SUM(BK45:BL45) -> 70000 | BN45: ='Солар Вест'!BN45+Будник!BN45 -> 0 | BO45: ='Солар Вест'!BO45+Будник!BO45 -> 0 | BP45: =SUM(BN45:BO45) -> 0 | BQ45: ='[5]ПП ВДГ'!BQ45+'[5]Корсак Л.Р.'!BQ45+'[5]Корсак В.І.'!BQ45+[5]Конякіна!BQ45 -> 75000 | BR45: ='[5]ПП ВДГ'!BR45+'[5]Корсак Л.Р.'!BR45+'[5]Корсак В.І.'!BR45+[5]Конякіна!BR45 -> 5000 | BS45: =SUM(BQ45:BR45) -> 80000 | BT45: ='Солар Вест'!BT45+Будник!BT45 -> 0 | BU45: ='Солар Вест'!BU45+Будник!BU45 -> 0 | BV45: =SUM(BT45:BU45) -> 0 | BW45: =+C45+I45+O45+AA45+AG45+U45+AM45+AS45+AY45+BE45+BK45+BQ45 -> 720000 | BX45: =+D45+J45+P45+AB45+AH45+V45+AN45+AT45+AZ45+BF45+BL45+BR45 -> 15000 | BY45: =SUM(BW45:BX45) -> 735000 | BZ45: =+F45+L45+R45+AD45+AJ45+X45+AP45+AV45+BB45+BH45+BN45+BT45 -> 0 | CA45: =+G45+M45+S45+AE45+AK45+Y45+AQ45+AW45+BC45+BI45+BO45+BU45 -> 0 | CB45: =SUM(BZ45:CA45) -> 0
A46: 128 | B46: Придбання ТМЦ (МШП, з/ч, буд.матеріали, інш.) | C46: ='[5]ПП ВДГ'!C46+'[5]Корсак Л.Р.'!C46+'[5]Корсак В.І.'!C46+[5]Конякіна!C46 -> 3000 | D46: ='[5]ПП ВДГ'!D46+'[5]Корсак Л.Р.'!D46+'[5]Корсак В.І.'!D46+[5]Конякіна!D46 -> 0 | E46: =SUM(C46:D46) -> 3000 | F46: ='Солар Вест'!F46+Будник!F46 -> 0 | G46: ='Солар Вест'!G46+Будник!G46 -> 0 | H46: =SUM(F46:G46) -> 0 | I46: ='[5]ПП ВДГ'!I46+'[5]Корсак Л.Р.'!I46+'[5]Корсак В.І.'!I46+[5]Конякіна!I46 -> 3000 | J46: ='[5]ПП ВДГ'!J46+'[5]Корсак Л.Р.'!J46+'[5]Корсак В.І.'!J46+[5]Конякіна!J46 -> 0 | K46: =SUM(I46:J46) -> 3000 | L46: ='Солар Вест'!L46+Будник!L46 -> 0 | M46: ='Солар Вест'!M46+Будник!M46 -> 3900 | N46: =SUM(L46:M46) -> 3900 | O46: ='[5]ПП ВДГ'!O46+'[5]Корсак Л.Р.'!O46+'[5]Корсак В.І.'!O46+[5]Конякіна!O46 -> 3000 | P46: ='[5]ПП ВДГ'!P46+'[5]Корсак Л.Р.'!P46+'[5]Корсак В.І.'!P46+[5]Конякіна!P46 -> 0 | Q46: =SUM(O46:P46) -> 3000 | R46: ='Солар Вест'!R46+Будник!R46 -> 0 | S46: ='Солар Вест'!S46+Будник!S46 -> 0 | T46: =SUM(R46:S46) -> 0 | U46: ='[5]ПП ВДГ'!U46+'[5]Корсак Л.Р.'!U46+'[5]Корсак В.І.'!U46+[5]Конякіна!U46 -> 3000 | V46: ='[5]ПП ВДГ'!V46+'[5]Корсак Л.Р.'!V46+'[5]Корсак В.І.'!V46+[5]Конякіна!V46 -> 0 | W46: =SUM(U46:V46) -> 3000 | X46: ='Солар Вест'!X46+Будник!X46 -> 8520 | Y46: ='Солар Вест'!Y46+Будник!Y46 -> 23155 | Z46: =SUM(X46:Y46) -> 31675 | AA46: ='[5]ПП ВДГ'!AA46+'[5]Корсак Л.Р.'!AA46+'[5]Корсак В.І.'!AA46+[5]Конякіна!AA46 -> 3000 | AB46: ='[5]ПП ВДГ'!AB46+'[5]Корсак Л.Р.'!AB46+'[5]Корсак В.І.'!AB46+[5]Конякіна!AB46 -> 0 | AC46: =SUM(AA46:AB46) -> 3000 | AD46: ='Солар Вест'!AD46+Будник!AD46 -> 23656.99 | AE46: ='Солар Вест'!AE46+Будник!AE46 -> 270174 | AF46: =SUM(AD46:AE46) -> 293830.99 | AG46: ='[5]ПП ВДГ'!AG46+'[5]Корсак Л.Р.'!AG46+'[5]Корсак В.І.'!AG46+[5]Конякіна!AG46 -> 3000 | AH46: ='[5]ПП ВДГ'!AH46+'[5]Корсак Л.Р.'!AH46+'[5]Корсак В.І.'!AH46+[5]Конякіна!AH46 -> 0 | AI46: =SUM(AG46:AH46) -> 3000 | AJ46: ='Солар Вест'!AJ46+Будник!AJ46 -> 7621 | AK46: ='Солар Вест'!AK46+Будник!AK46 -> 63870 | AL46: =SUM(AJ46:AK46) -> 71491 | AM46: ='[5]ПП ВДГ'!AM46+'[5]Корсак Л.Р.'!AM46+'[5]Корсак В.І.'!AM46+[5]Конякіна!AM46 -> 3000 | AN46: ='[5]ПП ВДГ'!AN46+'[5]Корсак Л.Р.'!AN46+'[5]Корсак В.І.'!AN46+[5]Конякіна!AN46 -> 0 | AO46: =SUM(AM46:AN46) -> 3000 | AP46: ='Солар Вест'!AP46+Будник!AP46 -> 0 | AQ46: ='Солар Вест'!AQ46+Будник!AQ46 -> 76813 | AR46: =SUM(AP46:AQ46) -> 76813 | AS46: ='[5]ПП ВДГ'!AS46+'[5]Корсак Л.Р.'!AS46+'[5]Корсак В.І.'!AS46+[5]Конякіна!AS46 -> 3000 | AT46: ='[5]ПП ВДГ'!AT46+'[5]Корсак Л.Р.'!AT46+'[5]Корсак В.І.'!AT46+[5]Конякіна!AT46 -> 3000 | AU46: =SUM(AS46:AT46) -> 6000 | AV46: ='Солар Вест'!AV46+Будник!AV46 -> 64551.5 | AW46: ='Солар Вест'!AW46+Будник!AW46 -> 8265 | AX46: =SUM(AV46:AW46) -> 72816.5 | AY46: ='[5]ПП ВДГ'!AY46+'[5]Корсак Л.Р.'!AY46+'[5]Корсак В.І.'!AY46+[5]Конякіна!AY46 -> 3000 | AZ46: ='[5]ПП ВДГ'!AZ46+'[5]Корсак Л.Р.'!AZ46+'[5]Корсак В.І.'!AZ46+[5]Конякіна!AZ46 -> 0 | BA46: =SUM(AY46:AZ46) -> 3000 | BB46: ='Солар Вест'!BB46+Будник!BB46 -> 35500 | BC46: ='Солар Вест'!BC46+Будник!BC46 -> 2087 | BD46: =SUM(BB46:BC46) -> 37587 | BE46: ='Солар Вест'!BE46+Будник!BE46 -> 0 | BF46: ='Солар Вест'!BF46+Будник!BF46 -> 0 | BG46: =SUM(BE46:BF46) -> 0 | BH46: ='Солар Вест'!BH46+Будник!BH46 -> 0 | BI46: ='Солар Вест'!BI46+Будник!BI46 -> 0 | BJ46: =SUM(BH46:BI46) -> 0 | BK46: ='[5]ПП ВДГ'!BK46+'[5]Корсак Л.Р.'!BK46+'[5]Корсак В.І.'!BK46+[5]Конякіна!BK46 -> 3000 | BL46: ='[5]ПП ВДГ'!BL46+'[5]Корсак Л.Р.'!BL46+'[5]Корсак В.І.'!BL46+[5]Конякіна!BL46 -> 0 | BM46: =SUM(BK46:BL46) -> 3000 | BN46: ='Солар Вест'!BN46+Будник!BN46 -> 0 | BO46: ='Солар Вест'!BO46+Будник!BO46 -> 0 | BP46: =SUM(BN46:BO46) -> 0 | BQ46: ='[5]ПП ВДГ'!BQ46+'[5]Корсак Л.Р.'!BQ46+'[5]Корсак В.І.'!BQ46+[5]Конякіна!BQ46 -> 3000 | BR46: ='[5]ПП ВДГ'!BR46+'[5]Корсак Л.Р.'!BR46+'[5]Корсак В.І.'!BR46+[5]Конякіна!BR46 -> 0 | BS46: =SUM(BQ46:BR46) -> 3000 | BT46: ='Солар Вест'!BT46+Будник!BT46 -> 0 | BU46: ='Солар Вест'!BU46+Будник!BU46 -> 0 | BV46: =SUM(BT46:BU46) -> 0 | BW46: =+C46+I46+O46+AA46+AG46+U46+AM46+AS46+AY46+BE46+BK46+BQ46 -> 33000 | BX46: =+D46+J46+P46+AB46+AH46+V46+AN46+AT46+AZ46+BF46+BL46+BR46 -> 3000 | BY46: =SUM(BW46:BX46) -> 36000 | BZ46: =+F46+L46+R46+AD46+AJ46+X46+AP46+AV46+BB46+BH46+BN46+BT46 -> 139849.49 | CA46: =+G46+M46+S46+AE46+AK46+Y46+AQ46+AW46+BC46+BI46+BO46+BU46 -> 448264 | CB46: =SUM(BZ46:CA46) -> 588113.49
B47: в т.ч. внутрішньогрупове придбання ТМЦ (МШП, з/ч, буд.матеріали, інш.) | C47: ='[5]ПП ВДГ'!C47+'[5]Корсак Л.Р.'!C47+'[5]Корсак В.І.'!C47+[5]Конякіна!C47 -> 0 | D47: ='[5]ПП ВДГ'!D47+'[5]Корсак Л.Р.'!D47+'[5]Корсак В.І.'!D47+[5]Конякіна!D47 -> 0 | E47: =SUM(C47:D47) -> 0 | F47: ='Солар Вест'!F47+Будник!F47 -> 0 | G47: ='Солар Вест'!G47+Будник!G47 -> 0 | H47: =SUM(F47:G47) -> 0 | I47: ='[5]ПП ВДГ'!I47+'[5]Корсак Л.Р.'!I47+'[5]Корсак В.І.'!I47+[5]Конякіна!I47 -> 0 | J47: ='[5]ПП ВДГ'!J47+'[5]Корсак Л.Р.'!J47+'[5]Корсак В.І.'!J47+[5]Конякіна!J47 -> 0 | K47: =SUM(I47:J47) -> 0 | L47: ='Солар Вест'!L47+Будник!L47 -> 0 | M47: ='Солар Вест'!M47+Будник!M47 -> 0 | N47: =SUM(L47:M47) -> 0 | O47: ='[5]ПП ВДГ'!O47+'[5]Корсак Л.Р.'!O47+'[5]Корсак В.І.'!O47+[5]Конякіна!O47 -> 0 | P47: ='[5]ПП ВДГ'!P47+'[5]Корсак Л.Р.'!P47+'[5]Корсак В.І.'!P47+[5]Конякіна!P47 -> 0 | Q47: =SUM(O47:P47) -> 0 | R47: ='Солар Вест'!R47+Будник!R47 -> 0 | S47: ='Солар Вест'!S47+Будник!S47 -> 0 | T47: =SUM(R47:S47) -> 0 | U47: ='[5]ПП ВДГ'!U47+'[5]Корсак Л.Р.'!U47+'[5]Корсак В.І.'!U47+[5]Конякіна!U47 -> 0 | V47: ='[5]ПП ВДГ'!V47+'[5]Корсак Л.Р.'!V47+'[5]Корсак В.І.'!V47+[5]Конякіна!V47 -> 0 | W47: =SUM(U47:V47) -> 0 | X47: ='Солар Вест'!X47+Будник!X47 -> 0 | Y47: ='Солар Вест'!Y47+Будник!Y47 -> 0 | Z47: =SUM(X47:Y47) -> 0 | AA47: ='[5]ПП ВДГ'!AA47+'[5]Корсак Л.Р.'!AA47+'[5]Корсак В.І.'!AA47+[5]Конякіна!AA47 -> 0 | AB47: ='[5]ПП ВДГ'!AB47+'[5]Корсак Л.Р.'!AB47+'[5]Корсак В.І.'!AB47+[5]Конякіна!AB47 -> 0 | AC47: =SUM(AA47:AB47) -> 0 | AD47: ='Солар Вест'!AD47+Будник!AD47 -> 0 | AE47: ='Солар Вест'!AE47+Будник!AE47 -> 0 | AF47: =SUM(AD47:AE47) -> 0 | AG47: ='[5]ПП ВДГ'!AG47+'[5]Корсак Л.Р.'!AG47+'[5]Корсак В.І.'!AG47+[5]Конякіна!AG47 -> 0 | AH47: ='[5]ПП ВДГ'!AH47+'[5]Корсак Л.Р.'!AH47+'[5]Корсак В.І.'!AH47+[5]Конякіна!AH47 -> 0 | AI47: =SUM(AG47:AH47) -> 0 | AJ47: ='Солар Вест'!AJ47+Будник!AJ47 -> 0 | AK47: ='Солар Вест'!AK47+Будник!AK47 -> 0 | AL47: =SUM(AJ47:AK47) -> 0 | AM47: ='[5]ПП ВДГ'!AM47+'[5]Корсак Л.Р.'!AM47+'[5]Корсак В.І.'!AM47+[5]Конякіна!AM47 -> 0 | AN47: ='[5]ПП ВДГ'!AN47+'[5]Корсак Л.Р.'!AN47+'[5]Корсак В.І.'!AN47+[5]Конякіна!AN47 -> 0 | AO47: =SUM(AM47:AN47) -> 0 | AP47: ='Солар Вест'!AP47+Будник!AP47 -> 0 | AQ47: ='Солар Вест'!AQ47+Будник!AQ47 -> 0 | AR47: =SUM(AP47:AQ47) -> 0 | AS47: ='[5]ПП ВДГ'!AS47+'[5]Корсак Л.Р.'!AS47+'[5]Корсак В.І.'!AS47+[5]Конякіна!AS47 -> 0 | AT47: ='[5]ПП ВДГ'!AT47+'[5]Корсак Л.Р.'!AT47+'[5]Корсак В.І.'!AT47+[5]Конякіна!AT47 -> 0 | AU47: =SUM(AS47:AT47) -> 0 | AV47: ='Солар Вест'!AV47+Будник!AV47 -> 0 | AW47: ='Солар Вест'!AW47+Будник!AW47 -> 0 | AX47: =SUM(AV47:AW47) -> 0 | AY47: ='[5]ПП ВДГ'!AY47+'[5]Корсак Л.Р.'!AY47+'[5]Корсак В.І.'!AY47+[5]Конякіна!AY47 -> 0 | AZ47: ='[5]ПП ВДГ'!AZ47+'[5]Корсак Л.Р.'!AZ47+'[5]Корсак В.І.'!AZ47+[5]Конякіна!AZ47 -> 0 | BA47: =SUM(AY47:AZ47) -> 0 | BB47: ='Солар Вест'!BB47+Будник!BB47 -> 0 | BC47: ='Солар Вест'!BC47+Будник!BC47 -> 0 | BD47: =SUM(BB47:BC47) -> 0 | BE47: ='Солар Вест'!BE47+Будник!BE47 -> 0 | BF47: ='Солар Вест'!BF47+Будник!BF47 -> 0 | BG47: =SUM(BE47:BF47) -> 0 | BH47: ='Солар Вест'!BH47+Будник!BH47 -> 0 | BI47: ='Солар Вест'!BI47+Будник!BI47 -> 0 | BJ47: =SUM(BH47:BI47) -> 0 | BK47: ='[5]ПП ВДГ'!BK47+'[5]Корсак Л.Р.'!BK47+'[5]Корсак В.І.'!BK47+[5]Конякіна!BK47 -> 0 | BL47: ='[5]ПП ВДГ'!BL47+'[5]Корсак Л.Р.'!BL47+'[5]Корсак В.І.'!BL47+[5]Конякіна!BL47 -> 0 | BM47: =SUM(BK47:BL47) -> 0 | BN47: ='Солар Вест'!BN47+Будник!BN47 -> 0 | BO47: ='Солар Вест'!BO47+Будник!BO47 -> 0 | BP47: =SUM(BN47:BO47) -> 0 | BQ47: ='[5]ПП ВДГ'!BQ47+'[5]Корсак Л.Р.'!BQ47+'[5]Корсак В.І.'!BQ47+[5]Конякіна!BQ47 -> 0 | BR47: ='[5]ПП ВДГ'!BR47+'[5]Корсак Л.Р.'!BR47+'[5]Корсак В.І.'!BR47+[5]Конякіна!BR47 -> 0 | BS47: =SUM(BQ47:BR47) -> 0 | BT47: ='Солар Вест'!BT47+Будник!BT47 -> 0 | BU47: ='Солар Вест'!BU47+Будник!BU47 -> 0 | BV47: =SUM(BT47:BU47) -> 0 | BW47: =+C47+I47+O47+AA47+AG47+U47+AM47+AS47+AY47+BE47+BK47+BQ47 -> 0 | BX47: =+D47+J47+P47+AB47+AH47+V47+AN47+AT47+AZ47+BF47+BL47+BR47 -> 0 | BY47: =SUM(BW47:BX47) -> 0 | BZ47: =+F47+L47+R47+AD47+AJ47+X47+AP47+AV47+BB47+BH47+BN47+BT47 -> 0 | CA47: =+G47+M47+S47+AE47+AK47+Y47+AQ47+AW47+BC47+BI47+BO47+BU47 -> 0 | CB47: =SUM(BZ47:CA47) -> 0
A48: 129 | B48: Послуги сторонніх організацій | C48: ='[5]ПП ВДГ'!C48+'[5]Корсак Л.Р.'!C48+'[5]Корсак В.І.'!C48+[5]Конякіна!C48 -> 2300 | D48: ='[5]ПП ВДГ'!D48+'[5]Корсак Л.Р.'!D48+'[5]Корсак В.І.'!D48+[5]Конякіна!D48 -> 0 | E48: =SUM(C48:D48) -> 2300 | F48: ='Солар Вест'!F48+Будник!F48 -> 3910 | G48: ='Солар Вест'!G48+Будник!G48 -> 10000 | H48: =SUM(F48:G48) -> 13910 | I48: ='[5]ПП ВДГ'!I48+'[5]Корсак Л.Р.'!I48+'[5]Корсак В.І.'!I48+[5]Конякіна!I48 -> 2300 | J48: ='[5]ПП ВДГ'!J48+'[5]Корсак Л.Р.'!J48+'[5]Корсак В.І.'!J48+[5]Конякіна!J48 -> 0 | K48: =SUM(I48:J48) -> 2300 | L48: ='Солар Вест'!L48+Будник!L48 -> 7012.89 | M48: ='Солар Вест'!M48+Будник!M48 -> 515 | N48: =SUM(L48:M48) -> 7527.89 | O48: ='[5]ПП ВДГ'!O48+'[5]Корсак Л.Р.'!O48+'[5]Корсак В.І.'!O48+[5]Конякіна!O48 -> 2300 | P48: ='[5]ПП ВДГ'!P48+'[5]Корсак Л.Р.'!P48+'[5]Корсак В.І.'!P48+[5]Конякіна!P48 -> 0 | Q48: =SUM(O48:P48) -> 2300 | R48: ='Солар Вест'!R48+Будник!R48 -> 3483 | S48: ='Солар Вест'!S48+Будник!S48 -> 2100 | T48: =SUM(R48:S48) -> 5583 | U48: ='[5]ПП ВДГ'!U48+'[5]Корсак Л.Р.'!U48+'[5]Корсак В.І.'!U48+[5]Конякіна!U48 -> 2000 | V48: ='[5]ПП ВДГ'!V48+'[5]Корсак Л.Р.'!V48+'[5]Корсак В.І.'!V48+[5]Конякіна!V48 -> 0 | W48: =SUM(U48:V48) -> 2000 | X48: ='Солар Вест'!X48+Будник!X48 -> 82371 | Y48: ='Солар Вест'!Y48+Будник!Y48 -> 10990 | Z48: =SUM(X48:Y48) -> 93361 | AA48: ='[5]ПП ВДГ'!AA48+'[5]Корсак Л.Р.'!AA48+'[5]Корсак В.І.'!AA48+[5]Конякіна!AA48 -> 5300 | AB48: ='[5]ПП ВДГ'!AB48+'[5]Корсак Л.Р.'!AB48+'[5]Корсак В.І.'!AB48+[5]Конякіна!AB48 -> 0 | AC48: =SUM(AA48:AB48) -> 5300 | AD48: ='Солар Вест'!AD48+Будник!AD48 -> 10415.15 | AE48: ='Солар Вест'!AE48+Будник!AE48 -> 18062 | AF48: =SUM(AD48:AE48) -> 28477.15 | AG48: ='[5]ПП ВДГ'!AG48+'[5]Корсак Л.Р.'!AG48+'[5]Корсак В.І.'!AG48+[5]Конякіна!AG48 -> 4000 | AH48: ='[5]ПП ВДГ'!AH48+'[5]Корсак Л.Р.'!AH48+'[5]Корсак В.І.'!AH48+[5]Конякіна!AH48 -> 0 | AI48: =SUM(AG48:AH48) -> 4000 | AJ48: ='Солар Вест'!AJ48+Будник!AJ48 -> 62726.75 | AK48: ='Солар Вест'!AK48+Будник!AK48 -> 24974 | AL48: =SUM(AJ48:AK48) -> 87700.75 | AM48: ='[5]ПП ВДГ'!AM48+'[5]Корсак Л.Р.'!AM48+'[5]Корсак В.І.'!AM48+[5]Конякіна!AM48 -> 2300 | AN48: ='[5]ПП ВДГ'!AN48+'[5]Корсак Л.Р.'!AN48+'[5]Корсак В.І.'!AN48+[5]Конякіна!AN48 -> 0 | AO48: =SUM(AM48:AN48) -> 2300 | AP48: ='Солар Вест'!AP48+Будник!AP48 -> 75539.1 | AQ48: ='Солар Вест'!AQ48+Будник!AQ48 -> 15122 | AR48: =SUM(AP48:AQ48) -> 90661.1 | AS48: ='[5]ПП ВДГ'!AS48+'[5]Корсак Л.Р.'!AS48+'[5]Корсак В.І.'!AS48+[5]Конякіна!AS48 -> 2300 | AT48: ='[5]ПП ВДГ'!AT48+'[5]Корсак Л.Р.'!AT48+'[5]Корсак В.І.'!AT48+[5]Конякіна!AT48 -> 0 | AU48: =SUM(AS48:AT48) -> 2300 | AV48: ='Солар Вест'!AV48+Будник!AV48 -> 9700 | AW48: ='Солар Вест'!AW48+Будник!AW48 -> 39378 | AX48: =SUM(AV48:AW48) -> 49078 | AY48: ='[5]ПП ВДГ'!AY48+'[5]Корсак Л.Р.'!AY48+'[5]Корсак В.І.'!AY48+[5]Конякіна!AY48 -> 2300 | AZ48: ='[5]ПП ВДГ'!AZ48+'[5]Корсак Л.Р.'!AZ48+'[5]Корсак В.І.'!AZ48+[5]Конякіна!AZ48 -> 0 | BA48: =SUM(AY48:AZ48) -> 2300 | BB48: ='Солар Вест'!BB48+Будник!BB48 -> 6843.01 | BC48: ='Солар Вест'!BC48+Будник!BC48 -> 26513 | BD48: =SUM(BB48:BC48) -> 33356.01 | BE48: ='Солар Вест'!BE48+Будник!BE48 -> 9510.79 | BF48: ='Солар Вест'!BF48+Будник!BF48 -> 16692 | BG48: =SUM(BE48:BF48) -> 26202.79 | BH48: ='Солар Вест'!BH48+Будник!BH48 -> 0 | BI48: ='Солар Вест'!BI48+Будник!BI48 -> 0 | BJ48: =SUM(BH48:BI48) -> 0 | BK48: ='[5]ПП ВДГ'!BK48+'[5]Корсак Л.Р.'!BK48+'[5]Корсак В.І.'!BK48+[5]Конякіна!BK48 -> 3500 | BL48: ='[5]ПП ВДГ'!BL48+'[5]Корсак Л.Р.'!BL48+'[5]Корсак В.І.'!BL48+[5]Конякіна!BL48 -> 0 | BM48: =SUM(BK48:BL48) -> 3500 | BN48: ='Солар Вест'!BN48+Будник!BN48 -> 0 | BO48: ='Солар Вест'!BO48+Будник!BO48 -> 0 | BP48: =SUM(BN48:BO48) -> 0 | BQ48: ='[5]ПП ВДГ'!BQ48+'[5]Корсак Л.Р.'!BQ48+'[5]Корсак В.І.'!BQ48+[5]Конякіна!BQ48 -> 3500 | BR48: ='[5]ПП ВДГ'!BR48+'[5]Корсак Л.Р.'!BR48+'[5]Корсак В.І.'!BR48+[5]Конякіна!BR48 -> 500 | BS48: =SUM(BQ48:BR48) -> 4000 | BT48: ='Солар Вест'!BT48+Будник!BT48 -> 0 | BU48: ='Солар Вест'!BU48+Будник!BU48 -> 0 | BV48: =SUM(BT48:BU48) -> 0 | BW48: =+C48+I48+O48+AA48+AG48+U48+AM48+AS48+AY48+BE48+BK48+BQ48 -> 41610.79 | BX48: =+D48+J48+P48+AB48+AH48+V48+AN48+AT48+AZ48+BF48+BL48+BR48 -> 17192 | BY48: =SUM(BW48:BX48) -> 58802.79 | BZ48: =+F48+L48+R48+AD48+AJ48+X48+AP48+AV48+BB48+BH48+BN48+BT48 -> 262000.9 | CA48: =+G48+M48+S48+AE48+AK48+Y48+AQ48+AW48+BC48+BI48+BO48+BU48 -> 147654 | CB48: =SUM(BZ48:CA48) -> 409654.9
B49: в т.ч. внутрішньогрупові послуги сторонніх організацій | C49: ='[5]ПП ВДГ'!C49+'[5]Корсак Л.Р.'!C49+'[5]Корсак В.І.'!C49+[5]Конякіна!C49 -> 0 | D49: ='[5]ПП ВДГ'!D49+'[5]Корсак Л.Р.'!D49+'[5]Корсак В.І.'!D49+[5]Конякіна!D49 -> 0 | E49: =SUM(C49:D49) -> 0 | F49: ='Солар Вест'!F49+Будник!F49 -> 0 | G49: ='Солар Вест'!G49+Будник!G49 -> 0 | H49: =SUM(F49:G49) -> 0 | I49: ='[5]ПП ВДГ'!I49+'[5]Корсак Л.Р.'!I49+'[5]Корсак В.І.'!I49+[5]Конякіна!I49 -> 0 | J49: ='[5]ПП ВДГ'!J49+'[5]Корсак Л.Р.'!J49+'[5]Корсак В.І.'!J49+[5]Конякіна!J49 -> 0 | K49: =SUM(I49:J49) -> 0 | L49: ='Солар Вест'!L49+Будник!L49 -> 0 | M49: ='Солар Вест'!M49+Будник!M49 -> 0 | N49: =SUM(L49:M49) -> 0 | O49: ='[5]ПП ВДГ'!O49+'[5]Корсак Л.Р.'!O49+'[5]Корсак В.І.'!O49+[5]Конякіна!O49 -> 0 | P49: ='[5]ПП ВДГ'!P49+'[5]Корсак Л.Р.'!P49+'[5]Корсак В.І.'!P49+[5]Конякіна!P49 -> 0 | Q49: =SUM(O49:P49) -> 0 | R49: ='Солар Вест'!R49+Будник!R49 -> 0 | S49: ='Солар Вест'!S49+Будник!S49 -> 0 | T49: =SUM(R49:S49) -> 0 | U49: ='[5]ПП ВДГ'!U49+'[5]Корсак Л.Р.'!U49+'[5]Корсак В.І.'!U49+[5]Конякіна!U49 -> 0 | V49: ='[5]ПП ВДГ'!V49+'[5]Корсак Л.Р.'!V49+'[5]Корсак В.І.'!V49+[5]Конякіна!V49 -> 0 | W49: =SUM(U49:V49) -> 0 | X49: ='Солар Вест'!X49+Будник!X49 -> 0 | Y49: ='Солар Вест'!Y49+Будник!Y49 -> 0 | Z49: =SUM(X49:Y49) -> 0 | AA49: ='[5]ПП ВДГ'!AA49+'[5]Корсак Л.Р.'!AA49+'[5]Корсак В.І.'!AA49+[5]Конякіна!AA49 -> 0 | AB49: ='[5]ПП ВДГ'!AB49+'[5]Корсак Л.Р.'!AB49+'[5]Корсак В.І.'!AB49+[5]Конякіна!AB49 -> 0 | AC49: =SUM(AA49:AB49) -> 0 | AD49: ='Солар Вест'!AD49+Будник!AD49 -> 0 | AE49: ='Солар Вест'!AE49+Будник!AE49 -> 0 | AF49: =SUM(AD49:AE49) -> 0 | AG49: ='[5]ПП ВДГ'!AG49+'[5]Корсак Л.Р.'!AG49+'[5]Корсак В.І.'!AG49+[5]Конякіна!AG49 -> 0 | AH49: ='[5]ПП ВДГ'!AH49+'[5]Корсак Л.Р.'!AH49+'[5]Корсак В.І.'!AH49+[5]Конякіна!AH49 -> 0 | AI49: =SUM(AG49:AH49) -> 0 | AJ49: ='Солар Вест'!AJ49+Будник!AJ49 -> 0 | AK49: ='Солар Вест'!AK49+Будник!AK49 -> 0 | AL49: =SUM(AJ49:AK49) -> 0 | AM49: ='[5]ПП ВДГ'!AM49+'[5]Корсак Л.Р.'!AM49+'[5]Корсак В.І.'!AM49+[5]Конякіна!AM49 -> 0 | AN49: ='[5]ПП ВДГ'!AN49+'[5]Корсак Л.Р.'!AN49+'[5]Корсак В.І.'!AN49+[5]Конякіна!AN49 -> 0 | AO49: =SUM(AM49:AN49) -> 0 | AP49: ='Солар Вест'!AP49+Будник!AP49 -> 0 | AQ49: ='Солар Вест'!AQ49+Будник!AQ49 -> 0 | AR49: =SUM(AP49:AQ49) -> 0 | AS49: ='[5]ПП ВДГ'!AS49+'[5]Корсак Л.Р.'!AS49+'[5]Корсак В.І.'!AS49+[5]Конякіна!AS49 -> 0 | AT49: ='[5]ПП ВДГ'!AT49+'[5]Корсак Л.Р.'!AT49+'[5]Корсак В.І.'!AT49+[5]Конякіна!AT49 -> 0 | AU49: =SUM(AS49:AT49) -> 0 | AV49: ='Солар Вест'!AV49+Будник!AV49 -> 0 | AW49: ='Солар Вест'!AW49+Будник!AW49 -> 0 | AX49: =SUM(AV49:AW49) -> 0 | AY49: ='[5]ПП ВДГ'!AY49+'[5]Корсак Л.Р.'!AY49+'[5]Корсак В.І.'!AY49+[5]Конякіна!AY49 -> 0 | AZ49: ='[5]ПП ВДГ'!AZ49+'[5]Корсак Л.Р.'!AZ49+'[5]Корсак В.І.'!AZ49+[5]Конякіна!AZ49 -> 0 | BA49: =SUM(AY49:AZ49) -> 0 | BB49: ='Солар Вест'!BB49+Будник!BB49 -> 0 | BC49: ='Солар Вест'!BC49+Будник!BC49 -> 0 | BD49: =SUM(BB49:BC49) -> 0 | BE49: ='Солар Вест'!BE49+Будник!BE49 -> 0 | BF49: ='Солар Вест'!BF49+Будник!BF49 -> 0 | BG49: =SUM(BE49:BF49) -> 0 | BH49: ='Солар Вест'!BH49+Будник!BH49 -> 0 | BI49: ='Солар Вест'!BI49+Будник!BI49 -> 0 | BJ49: =SUM(BH49:BI49) -> 0 | BK49: ='[5]ПП ВДГ'!BK49+'[5]Корсак Л.Р.'!BK49+'[5]Корсак В.І.'!BK49+[5]Конякіна!BK49 -> 0 | BL49: ='[5]ПП ВДГ'!BL49+'[5]Корсак Л.Р.'!BL49+'[5]Корсак В.І.'!BL49+[5]Конякіна!BL49 -> 0 | BM49: =SUM(BK49:BL49) -> 0 | BN49: ='Солар Вест'!BN49+Будник!BN49 -> 0 | BO49: ='Солар Вест'!BO49+Будник!BO49 -> 0 | BP49: =SUM(BN49:BO49) -> 0 | BQ49: ='[5]ПП ВДГ'!BQ49+'[5]Корсак Л.Р.'!BQ49+'[5]Корсак В.І.'!BQ49+[5]Конякіна!BQ49 -> 0 | BR49: ='[5]ПП ВДГ'!BR49+'[5]Корсак Л.Р.'!BR49+'[5]Корсак В.І.'!BR49+[5]Конякіна!BR49 -> 0 | BS49: =SUM(BQ49:BR49) -> 0 | BT49: ='Солар Вест'!BT49+Будник!BT49 -> 0 | BU49: ='Солар Вест'!BU49+Будник!BU49 -> 0 | BV49: =SUM(BT49:BU49) -> 0 | BW49: =+C49+I49+O49+AA49+AG49+U49+AM49+AS49+AY49+BE49+BK49+BQ49 -> 0 | BX49: =+D49+J49+P49+AB49+AH49+V49+AN49+AT49+AZ49+BF49+BL49+BR49 -> 0 | BY49: =SUM(BW49:BX49) -> 0 | BZ49: =+F49+L49+R49+AD49+AJ49+X49+AP49+AV49+BB49+BH49+BN49+BT49 -> 0 | CA49: =+G49+M49+S49+AE49+AK49+Y49+AQ49+AW49+BC49+BI49+BO49+BU49 -> 0 | CB49: =SUM(BZ49:CA49) -> 0
A50: 130 | B50: Маркетинг та реклама | C50: ='[5]ПП ВДГ'!C50+'[5]Корсак Л.Р.'!C50+'[5]Корсак В.І.'!C50+[5]Конякіна!C50 -> 0 | D50: ='[5]ПП ВДГ'!D50+'[5]Корсак Л.Р.'!D50+'[5]Корсак В.І.'!D50+[5]Конякіна!D50 -> 0 | E50: =SUM(C50:D50) -> 0 | F50: ='Солар Вест'!F50+Будник!F50 -> 0 | G50: ='Солар Вест'!G50+Будник!G50 -> 0 | H50: =SUM(F50:G50) -> 0 | I50: ='[5]ПП ВДГ'!I50+'[5]Корсак Л.Р.'!I50+'[5]Корсак В.І.'!I50+[5]Конякіна!I50 -> 0 | J50: ='[5]ПП ВДГ'!J50+'[5]Корсак Л.Р.'!J50+'[5]Корсак В.І.'!J50+[5]Конякіна!J50 -> 0 | K50: =SUM(I50:J50) -> 0 | L50: ='Солар Вест'!L50+Будник!L50 -> 0 | M50: ='Солар Вест'!M50+Будник!M50 -> 0 | N50: =SUM(L50:M50) -> 0 | O50: ='[5]ПП ВДГ'!O50+'[5]Корсак Л.Р.'!O50+'[5]Корсак В.І.'!O50+[5]Конякіна!O50 -> 0 | P50: ='[5]ПП ВДГ'!P50+'[5]Корсак Л.Р.'!P50+'[5]Корсак В.І.'!P50+[5]Конякіна!P50 -> 0 | Q50: =SUM(O50:P50) -> 0 | R50: ='Солар Вест'!R50+Будник!R50 -> 0 | S50: ='Солар Вест'!S50+Будник!S50 -> 130 | T50: =SUM(R50:S50) -> 130 | U50: ='[5]ПП ВДГ'!U50+'[5]Корсак Л.Р.'!U50+'[5]Корсак В.І.'!U50+[5]Конякіна!U50 -> 0 | V50: ='[5]ПП ВДГ'!V50+'[5]Корсак Л.Р.'!V50+'[5]Корсак В.І.'!V50+[5]Конякіна!V50 -> 0 | W50: =SUM(U50:V50) -> 0 | X50: ='Солар Вест'!X50+Будник!X50 -> 0 | Y50: ='Солар Вест'!Y50+Будник!Y50 -> 200 | Z50: =SUM(X50:Y50) -> 200 | AA50: ='[5]ПП ВДГ'!AA50+'[5]Корсак Л.Р.'!AA50+'[5]Корсак В.І.'!AA50+[5]Конякіна!AA50 -> 0 | AB50: ='[5]ПП ВДГ'!AB50+'[5]Корсак Л.Р.'!AB50+'[5]Корсак В.І.'!AB50+[5]Конякіна!AB50 -> 0 | AC50: =SUM(AA50:AB50) -> 0 | AD50: ='Солар Вест'!AD50+Будник!AD50 -> 3000 | AE50: ='Солар Вест'!AE50+Будник!AE50 -> 978 | AF50: =SUM(AD50:AE50) -> 3978 | AG50: ='[5]ПП ВДГ'!AG50+'[5]Корсак Л.Р.'!AG50+'[5]Корсак В.І.'!AG50+[5]Конякіна!AG50 -> 0 | AH50: ='[5]ПП ВДГ'!AH50+'[5]Корсак Л.Р.'!AH50+'[5]Корсак В.І.'!AH50+[5]Конякіна!AH50 -> 0 | AI50: =SUM(AG50:AH50) -> 0 | AJ50: ='Солар Вест'!AJ50+Будник!AJ50 -> 0 | AK50: ='Солар Вест'!AK50+Будник!AK50 -> 950 | AL50: =SUM(AJ50:AK50) -> 950 | AM50: ='[5]ПП ВДГ'!AM50+'[5]Корсак Л.Р.'!AM50+'[5]Корсак В.І.'!AM50+[5]Конякіна!AM50 -> 0 | AN50: ='[5]ПП ВДГ'!AN50+'[5]Корсак Л.Р.'!AN50+'[5]Корсак В.І.'!AN50+[5]Конякіна!AN50 -> 0 | AO50: =SUM(AM50:AN50) -> 0 | AP50: ='Солар Вест'!AP50+Будник!AP50 -> 0 | AQ50: ='Солар Вест'!AQ50+Будник!AQ50 -> 0 | AR50: =SUM(AP50:AQ50) -> 0 | AS50: ='[5]ПП ВДГ'!AS50+'[5]Корсак Л.Р.'!AS50+'[5]Корсак В.І.'!AS50+[5]Конякіна!AS50 -> 0 | AT50: ='[5]ПП ВДГ'!AT50+'[5]Корсак Л.Р.'!AT50+'[5]Корсак В.І.'!AT50+[5]Конякіна!AT50 -> 0 | AU50: =SUM(AS50:AT50) -> 0 | AV50: ='Солар Вест'!AV50+Будник!AV50 -> 6700 | AW50: ='Солар Вест'!AW50+Будник!AW50 -> 0 | AX50: =SUM(AV50:AW50) -> 6700 | AY50: ='[5]ПП ВДГ'!AY50+'[5]Корсак Л.Р.'!AY50+'[5]Корсак В.І.'!AY50+[5]Конякіна!AY50 -> 0 | AZ50: ='[5]ПП ВДГ'!AZ50+'[5]Корсак Л.Р.'!AZ50+'[5]Корсак В.І.'!AZ50+[5]Конякіна!AZ50 -> 0 | BA50: =SUM(AY50:AZ50) -> 0 | BB50: ='Солар Вест'!BB50+Будник!BB50 -> 0 | BC50: ='Солар Вест'!BC50+Будник!BC50 -> 232 | BD50: =SUM(BB50:BC50) -> 232 | BE50: ='Солар Вест'!BE50+Будник!BE50 -> 16000 | BF50: ='Солар Вест'!BF50+Будник!BF50 -> 10147 | BG50: =SUM(BE50:BF50) -> 26147 | BH50: ='Солар Вест'!BH50+Будник!BH50 -> 0 | BI50: ='Солар Вест'!BI50+Будник!BI50 -> 0 | BJ50: =SUM(BH50:BI50) -> 0 | BK50: ='[5]ПП ВДГ'!BK50+'[5]Корсак Л.Р.'!BK50+'[5]Корсак В.І.'!BK50+[5]Конякіна!BK50 -> 0 | BL50: ='[5]ПП ВДГ'!BL50+'[5]Корсак Л.Р.'!BL50+'[5]Корсак В.І.'!BL50+[5]Конякіна!BL50 -> 0 | BM50: =SUM(BK50:BL50) -> 0 | BN50: ='Солар Вест'!BN50+Будник!BN50 -> 0 | BO50: ='Солар Вест'!BO50+Будник!BO50 -> 0 | BP50: =SUM(BN50:BO50) -> 0 | BQ50: ='[5]ПП ВДГ'!BQ50+'[5]Корсак Л.Р.'!BQ50+'[5]Корсак В.І.'!BQ50+[5]Конякіна!BQ50 -> 0 | BR50: ='[5]ПП ВДГ'!BR50+'[5]Корсак Л.Р.'!BR50+'[5]Корсак В.І.'!BR50+[5]Конякіна!BR50 -> 0 | BS50: =SUM(BQ50:BR50) -> 0 | BT50: ='Солар Вест'!BT50+Будник!BT50 -> 0 | BU50: ='Солар Вест'!BU50+Будник!BU50 -> 0 | BV50: =SUM(BT50:BU50) -> 0 | BW50: =+C50+I50+O50+AA50+AG50+U50+AM50+AS50+AY50+BE50+BK50+BQ50 -> 16000 | BX50: =+D50+J50+P50+AB50+AH50+V50+AN50+AT50+AZ50+BF50+BL50+BR50 -> 10147 | BY50: =SUM(BW50:BX50) -> 26147 | BZ50: =+F50+L50+R50+AD50+AJ50+X50+AP50+AV50+BB50+BH50+BN50+BT50 -> 9700 | CA50: =+G50+M50+S50+AE50+AK50+Y50+AQ50+AW50+BC50+BI50+BO50+BU50 -> 2490 | CB50: =SUM(BZ50:CA50) -> 12190
B51: в т.ч. внутрішньогруповий маркетинг та реклама | C51: ='[5]ПП ВДГ'!C51+'[5]Корсак Л.Р.'!C51+'[5]Корсак В.І.'!C51+[5]Конякіна!C51 -> 0 | D51: ='[5]ПП ВДГ'!D51+'[5]Корсак Л.Р.'!D51+'[5]Корсак В.І.'!D51+[5]Конякіна!D51 -> 0 | E51: =SUM(C51:D51) -> 0 | F51: ='Солар Вест'!F51+Будник!F51 -> 0 | G51: ='Солар Вест'!G51+Будник!G51 -> 0 | H51: =SUM(F51:G51) -> 0 | I51: ='[5]ПП ВДГ'!I51+'[5]Корсак Л.Р.'!I51+'[5]Корсак В.І.'!I51+[5]Конякіна!I51 -> 0 | J51: ='[5]ПП ВДГ'!J51+'[5]Корсак Л.Р.'!J51+'[5]Корсак В.І.'!J51+[5]Конякіна!J51 -> 0 | K51: =SUM(I51:J51) -> 0 | L51: ='Солар Вест'!L51+Будник!L51 -> 0 | M51: ='Солар Вест'!M51+Будник!M51 -> 0 | N51: =SUM(L51:M51) -> 0 | O51: ='[5]ПП ВДГ'!O51+'[5]Корсак Л.Р.'!O51+'[5]Корсак В.І.'!O51+[5]Конякіна!O51 -> 0 | P51: ='[5]ПП ВДГ'!P51+'[5]Корсак Л.Р.'!P51+'[5]Корсак В.І.'!P51+[5]Конякіна!P51 -> 0 | Q51: =SUM(O51:P51) -> 0 | R51: ='Солар Вест'!R51+Будник!R51 -> 0 | S51: ='Солар Вест'!S51+Будник!S51 -> 0 | T51: =SUM(R51:S51) -> 0 | U51: ='[5]ПП ВДГ'!U51+'[5]Корсак Л.Р.'!U51+'[5]Корсак В.І.'!U51+[5]Конякіна!U51 -> 0 | V51: ='[5]ПП ВДГ'!V51+'[5]Корсак Л.Р.'!V51+'[5]Корсак В.І.'!V51+[5]Конякіна!V51 -> 0 | W51: =SUM(U51:V51) -> 0 | X51: ='Солар Вест'!X51+Будник!X51 -> 0 | Y51: ='Солар Вест'!Y51+Будник!Y51 -> 0 | Z51: =SUM(X51:Y51) -> 0 | AA51: ='[5]ПП ВДГ'!AA51+'[5]Корсак Л.Р.'!AA51+'[5]Корсак В.І.'!AA51+[5]Конякіна!AA51 -> 0 | AB51: ='[5]ПП ВДГ'!AB51+'[5]Корсак Л.Р.'!AB51+'[5]Корсак В.І.'!AB51+[5]Конякіна!AB51 -> 0 | AC51: =SUM(AA51:AB51) -> 0 | AD51: ='Солар Вест'!AD51+Будник!AD51 -> 0 | AE51: ='Солар Вест'!AE51+Будник!AE51 -> 0 | AF51: =SUM(AD51:AE51) -> 0 | AG51: ='[5]ПП ВДГ'!AG51+'[5]Корсак Л.Р.'!AG51+'[5]Корсак В.І.'!AG51+[5]Конякіна!AG51 -> 0 | AH51: ='[5]ПП ВДГ'!AH51+'[5]Корсак Л.Р.'!AH51+'[5]Корсак В.І.'!AH51+[5]Конякіна!AH51 -> 0 | AI51: =SUM(AG51:AH51) -> 0 | AJ51: ='Солар Вест'!AJ51+Будник!AJ51 -> 0 | AK51: ='Солар Вест'!AK51+Будник!AK51 -> 0 | AL51: =SUM(AJ51:AK51) -> 0 | AM51: ='[5]ПП ВДГ'!AM51+'[5]Корсак Л.Р.'!AM51+'[5]Корсак В.І.'!AM51+[5]Конякіна!AM51 -> 0 | AN51: ='[5]ПП ВДГ'!AN51+'[5]Корсак Л.Р.'!AN51+'[5]Корсак В.І.'!AN51+[5]Конякіна!AN51 -> 0 | AO51: =SUM(AM51:AN51) -> 0 | AP51: ='Солар Вест'!AP51+Будник!AP51 -> 0 | AQ51: ='Солар Вест'!AQ51+Будник!AQ51 -> 0 | AR51: =SUM(AP51:AQ51) -> 0 | AS51: ='[5]ПП ВДГ'!AS51+'[5]Корсак Л.Р.'!AS51+'[5]Корсак В.І.'!AS51+[5]Конякіна!AS51 -> 0 | AT51: ='[5]ПП ВДГ'!AT51+'[5]Корсак Л.Р.'!AT51+'[5]Корсак В.І.'!AT51+[5]Конякіна!AT51 -> 0 | AU51: =SUM(AS51:AT51) -> 0 | AV51: ='Солар Вест'!AV51+Будник!AV51 -> 0 | AW51: ='Солар Вест'!AW51+Будник!AW51 -> 0 | AX51: =SUM(AV51:AW51) -> 0 | AY51: ='[5]ПП ВДГ'!AY51+'[5]Корсак Л.Р.'!AY51+'[5]Корсак В.І.'!AY51+[5]Конякіна!AY51 -> 0 | AZ51: ='[5]ПП ВДГ'!AZ51+'[5]Корсак Л.Р.'!AZ51+'[5]Корсак В.І.'!AZ51+[5]Конякіна!AZ51 -> 0 | BA51: =SUM(AY51:AZ51) -> 0 | BB51: ='Солар Вест'!BB51+Будник!BB51 -> 0 | BC51: ='Солар Вест'!BC51+Будник!BC51 -> 0 | BD51: =SUM(BB51:BC51) -> 0 | BE51: ='Солар Вест'!BE51+Будник!BE51 -> 0 | BF51: ='Солар Вест'!BF51+Будник!BF51 -> 0 | BG51: =SUM(BE51:BF51) -> 0 | BH51: ='Солар Вест'!BH51+Будник!BH51 -> 0 | BI51: ='Солар Вест'!BI51+Будник!BI51 -> 0 | BJ51: =SUM(BH51:BI51) -> 0 | BK51: ='[5]ПП ВДГ'!BK51+'[5]Корсак Л.Р.'!BK51+'[5]Корсак В.І.'!BK51+[5]Конякіна!BK51 -> 0 | BL51: ='[5]ПП ВДГ'!BL51+'[5]Корсак Л.Р.'!BL51+'[5]Корсак В.І.'!BL51+[5]Конякіна!BL51 -> 0 | BM51: =SUM(BK51:BL51) -> 0 | BN51: ='Солар Вест'!BN51+Будник!BN51 -> 0 | BO51: ='Солар Вест'!BO51+Будник!BO51 -> 0 | BP51: =SUM(BN51:BO51) -> 0 | BQ51: ='[5]ПП ВДГ'!BQ51+'[5]Корсак Л.Р.'!BQ51+'[5]Корсак В.І.'!BQ51+[5]Конякіна!BQ51 -> 0 | BR51: ='[5]ПП ВДГ'!BR51+'[5]Корсак Л.Р.'!BR51+'[5]Корсак В.І.'!BR51+[5]Конякіна!BR51 -> 0 | BS51: =SUM(BQ51:BR51) -> 0 | BT51: ='Солар Вест'!BT51+Будник!BT51 -> 0 | BU51: ='Солар Вест'!BU51+Будник!BU51 -> 0 | BV51: =SUM(BT51:BU51) -> 0 | BW51: =+C51+I51+O51+AA51+AG51+U51+AM51+AS51+AY51+BE51+BK51+BQ51 -> 0 | BX51: =+D51+J51+P51+AB51+AH51+V51+AN51+AT51+AZ51+BF51+BL51+BR51 -> 0 | BY51: =SUM(BW51:BX51) -> 0 | BZ51: =+F51+L51+R51+AD51+AJ51+X51+AP51+AV51+BB51+BH51+BN51+BT51 -> 0 | CA51: =+G51+M51+S51+AE51+AK51+Y51+AQ51+AW51+BC51+BI51+BO51+BU51 -> 0 | CB51: =SUM(BZ51:CA51) -> 0
A52: 131 | B52: Утримання автотранспорту (ПММ, ТО, з/ч, страхування, інш.) | C52: ='[5]ПП ВДГ'!C52+'[5]Корсак Л.Р.'!C52+'[5]Корсак В.І.'!C52+[5]Конякіна!C52 -> 0 | D52: ='[5]ПП ВДГ'!D52+'[5]Корсак Л.Р.'!D52+'[5]Корсак В.І.'!D52+[5]Конякіна!D52 -> 0 | E52: =SUM(C52:D52) -> 0 | F52: ='Солар Вест'!F52+Будник!F52 -> 0 | G52: ='Солар Вест'!G52+Будник!G52 -> 0 | H52: =SUM(F52:G52) -> 0 | I52: ='[5]ПП ВДГ'!I52+'[5]Корсак Л.Р.'!I52+'[5]Корсак В.І.'!I52+[5]Конякіна!I52 -> 0 | J52: ='[5]ПП ВДГ'!J52+'[5]Корсак Л.Р.'!J52+'[5]Корсак В.І.'!J52+[5]Конякіна!J52 -> 0 | K52: =SUM(I52:J52) -> 0 | L52: ='Солар Вест'!L52+Будник!L52 -> 0 | M52: ='Солар Вест'!M52+Будник!M52 -> 0 | N52: =SUM(L52:M52) -> 0 | O52: ='[5]ПП ВДГ'!O52+'[5]Корсак Л.Р.'!O52+'[5]Корсак В.І.'!O52+[5]Конякіна!O52 -> 0 | P52: ='[5]ПП ВДГ'!P52+'[5]Корсак Л.Р.'!P52+'[5]Корсак В.І.'!P52+[5]Конякіна!P52 -> 0 | Q52: =SUM(O52:P52) -> 0 | R52: ='Солар Вест'!R52+Будник!R52 -> 0 | S52: ='Солар Вест'!S52+Будник!S52 -> 0 | T52: =SUM(R52:S52) -> 0 | U52: ='[5]ПП ВДГ'!U52+'[5]Корсак Л.Р.'!U52+'[5]Корсак В.І.'!U52+[5]Конякіна!U52 -> 9000 | V52: ='[5]ПП ВДГ'!V52+'[5]Корсак Л.Р.'!V52+'[5]Корсак В.І.'!V52+[5]Конякіна!V52 -> 0 | W52: =SUM(U52:V52) -> 9000 | X52: ='Солар Вест'!X52+Будник!X52 -> 0 | Y52: ='Солар Вест'!Y52+Будник!Y52 -> 2700 | Z52: =SUM(X52:Y52) -> 2700 | AA52: ='[5]ПП ВДГ'!AA52+'[5]Корсак Л.Р.'!AA52+'[5]Корсак В.І.'!AA52+[5]Конякіна!AA52 -> 0 | AB52: ='[5]ПП ВДГ'!AB52+'[5]Корсак Л.Р.'!AB52+'[5]Корсак В.І.'!AB52+[5]Конякіна!AB52 -> 0 | AC52: =SUM(AA52:AB52) -> 0 | AD52: ='Солар Вест'!AD52+Будник!AD52 -> 5400.02 | AE52: ='Солар Вест'!AE52+Будник!AE52 -> 6000 | AF52: =SUM(AD52:AE52) -> 11400.02 | AG52: ='[5]ПП ВДГ'!AG52+'[5]Корсак Л.Р.'!AG52+'[5]Корсак В.І.'!AG52+[5]Конякіна!AG52 -> 8000 | AH52: ='[5]ПП ВДГ'!AH52+'[5]Корсак Л.Р.'!AH52+'[5]Корсак В.І.'!AH52+[5]Конякіна!AH52 -> 0 | AI52: =SUM(AG52:AH52) -> 8000 | AJ52: ='Солар Вест'!AJ52+Будник!AJ52 -> 0 | AK52: ='Солар Вест'!AK52+Будник!AK52 -> 9400 | AL52: =SUM(AJ52:AK52) -> 9400 | AM52: ='[5]ПП ВДГ'!AM52+'[5]Корсак Л.Р.'!AM52+'[5]Корсак В.І.'!AM52+[5]Конякіна!AM52 -> 8000 | AN52: ='[5]ПП ВДГ'!AN52+'[5]Корсак Л.Р.'!AN52+'[5]Корсак В.І.'!AN52+[5]Конякіна!AN52 -> 0 | AO52: =SUM(AM52:AN52) -> 8000 | AP52: ='Солар Вест'!AP52+Будник!AP52 -> 0 | AQ52: ='Солар Вест'!AQ52+Будник!AQ52 -> 10039 | AR52: =SUM(AP52:AQ52) -> 10039 | AS52: ='[5]ПП ВДГ'!AS52+'[5]Корсак Л.Р.'!AS52+'[5]Корсак В.І.'!AS52+[5]Конякіна!AS52 -> 7000 | AT52: ='[5]ПП ВДГ'!AT52+'[5]Корсак Л.Р.'!AT52+'[5]Корсак В.І.'!AT52+[5]Конякіна!AT52 -> 0 | AU52: =SUM(AS52:AT52) -> 7000 | AV52: ='Солар Вест'!AV52+Будник!AV52 -> 0 | AW52: ='Солар Вест'!AW52+Будник!AW52 -> 23959 | AX52: =SUM(AV52:AW52) -> 23959 | AY52: ='[5]ПП ВДГ'!AY52+'[5]Корсак Л.Р.'!AY52+'[5]Корсак В.І.'!AY52+[5]Конякіна!AY52 -> 0 | AZ52: ='[5]ПП ВДГ'!AZ52+'[5]Корсак Л.Р.'!AZ52+'[5]Корсак В.І.'!AZ52+[5]Конякіна!AZ52 -> 0 | BA52: =SUM(AY52:AZ52) -> 0 | BB52: ='Солар Вест'!BB52+Будник!BB52 -> 7740 | BC52: ='Солар Вест'!BC52+Будник!BC52 -> 4410 | BD52: =SUM(BB52:BC52) -> 12150 | BE52: ='Солар Вест'!BE52+Будник!BE52 -> 30532.02 | BF52: ='Солар Вест'!BF52+Будник!BF52 -> 4690 | BG52: =SUM(BE52:BF52) -> 35222.02 | BH52: ='Солар Вест'!BH52+Будник!BH52 -> 0 | BI52: ='Солар Вест'!BI52+Будник!BI52 -> 0 | BJ52: =SUM(BH52:BI52) -> 0 | BK52: ='[5]ПП ВДГ'!BK52+'[5]Корсак Л.Р.'!BK52+'[5]Корсак В.І.'!BK52+[5]Конякіна!BK52 -> 7000 | BL52: ='[5]ПП ВДГ'!BL52+'[5]Корсак Л.Р.'!BL52+'[5]Корсак В.І.'!BL52+[5]Конякіна!BL52 -> 0 | BM52: =SUM(BK52:BL52) -> 7000 | BN52: ='Солар Вест'!BN52+Будник!BN52 -> 0 | BO52: ='Солар Вест'!BO52+Будник!BO52 -> 0 | BP52: =SUM(BN52:BO52) -> 0 | BQ52: ='[5]ПП ВДГ'!BQ52+'[5]Корсак Л.Р.'!BQ52+'[5]Корсак В.І.'!BQ52+[5]Конякіна!BQ52 -> 7500 | BR52: ='[5]ПП ВДГ'!BR52+'[5]Корсак Л.Р.'!BR52+'[5]Корсак В.І.'!BR52+[5]Конякіна!BR52 -> 0 | BS52: =SUM(BQ52:BR52) -> 7500 | BT52: ='Солар Вест'!BT52+Будник!BT52 -> 0 | BU52: ='Солар Вест'!BU52+Будник!BU52 -> 0 | BV52: =SUM(BT52:BU52) -> 0 | BW52: =+C52+I52+O52+AA52+AG52+U52+AM52+AS52+AY52+BE52+BK52+BQ52 -> 77032.02 | BX52: =+D52+J52+P52+AB52+AH52+V52+AN52+AT52+AZ52+BF52+BL52+BR52 -> 4690 | BY52: =SUM(BW52:BX52) -> 81722.02 | BZ52: =+F52+L52+R52+AD52+AJ52+X52+AP52+AV52+BB52+BH52+BN52+BT52 -> 13140.02 | CA52: =+G52+M52+S52+AE52+AK52+Y52+AQ52+AW52+BC52+BI52+BO52+BU52 -> 56508 | CB52: =SUM(BZ52:CA52) -> 69648.02
A53: 132 | B53: Ремонт та утримання ОЗ | C53: ='[5]ПП ВДГ'!C53+'[5]Корсак Л.Р.'!C53+'[5]Корсак В.І.'!C53+[5]Конякіна!C53 -> 3000 | D53: ='[5]ПП ВДГ'!D53+'[5]Корсак Л.Р.'!D53+'[5]Корсак В.І.'!D53+[5]Конякіна!D53 -> 4000 | E53: =SUM(C53:D53) -> 7000 | F53: ='Солар Вест'!F53+Будник!F53 -> 0 | G53: ='Солар Вест'!G53+Будник!G53 -> 0 | H53: =SUM(F53:G53) -> 0 | I53: ='[5]ПП ВДГ'!I53+'[5]Корсак Л.Р.'!I53+'[5]Корсак В.І.'!I53+[5]Конякіна!I53 -> 3000 | J53: ='[5]ПП ВДГ'!J53+'[5]Корсак Л.Р.'!J53+'[5]Корсак В.І.'!J53+[5]Конякіна!J53 -> 4000 | K53: =SUM(I53:J53) -> 7000 | L53: ='Солар Вест'!L53+Будник!L53 -> 0 | M53: ='Солар Вест'!M53+Будник!M53 -> 0 | N53: =SUM(L53:M53) -> 0 | O53: ='[5]ПП ВДГ'!O53+'[5]Корсак Л.Р.'!O53+'[5]Корсак В.І.'!O53+[5]Конякіна!O53 -> 3000 | P53: ='[5]ПП ВДГ'!P53+'[5]Корсак Л.Р.'!P53+'[5]Корсак В.І.'!P53+[5]Конякіна!P53 -> 4000 | Q53: =SUM(O53:P53) -> 7000 | R53: ='Солар Вест'!R53+Будник!R53 -> 0 | S53: ='Солар Вест'!S53+Будник!S53 -> 0 | T53: =SUM(R53:S53) -> 0 | U53: ='[5]ПП ВДГ'!U53+'[5]Корсак Л.Р.'!U53+'[5]Корсак В.І.'!U53+[5]Конякіна!U53 -> 10000 | V53: ='[5]ПП ВДГ'!V53+'[5]Корсак Л.Р.'!V53+'[5]Корсак В.І.'!V53+[5]Конякіна!V53 -> 8000 | W53: =SUM(U53:V53) -> 18000 | X53: ='Солар Вест'!X53+Будник!X53 -> 0 | Y53: ='Солар Вест'!Y53+Будник!Y53 -> 0 | Z53: =SUM(X53:Y53) -> 0 | AA53: ='[5]ПП ВДГ'!AA53+'[5]Корсак Л.Р.'!AA53+'[5]Корсак В.І.'!AA53+[5]Конякіна!AA53 -> 3000 | AB53: ='[5]ПП ВДГ'!AB53+'[5]Корсак Л.Р.'!AB53+'[5]Корсак В.І.'!AB53+[5]Конякіна!AB53 -> 4000 | AC53: =SUM(AA53:AB53) -> 7000 | AD53: ='Солар Вест'!AD53+Будник!AD53 -> 0 | AE53: ='Солар Вест'!AE53+Будник!AE53 -> 0 | AF53: =SUM(AD53:AE53) -> 0 | AG53: ='[5]ПП ВДГ'!AG53+'[5]Корсак Л.Р.'!AG53+'[5]Корсак В.І.'!AG53+[5]Конякіна!AG53 -> 3000 | AH53: ='[5]ПП ВДГ'!AH53+'[5]Корсак Л.Р.'!AH53+'[5]Корсак В.І.'!AH53+[5]Конякіна!AH53 -> 4000 | AI53: =SUM(AG53:AH53) -> 7000 | AJ53: ='Солар Вест'!AJ53+Будник!AJ53 -> 0 | AK53: ='Солар Вест'!AK53+Будник!AK53 -> 3900 | AL53: =SUM(AJ53:AK53) -> 3900 | AM53: ='[5]ПП ВДГ'!AM53+'[5]Корсак Л.Р.'!AM53+'[5]Корсак В.І.'!AM53+[5]Конякіна!AM53 -> 5000 | AN53: ='[5]ПП ВДГ'!AN53+'[5]Корсак Л.Р.'!AN53+'[5]Корсак В.І.'!AN53+[5]Конякіна!AN53 -> 9000 | AO53: =SUM(AM53:AN53) -> 14000 | AP53: ='Солар Вест'!AP53+Будник!AP53 -> 0 | AQ53: ='Солар Вест'!AQ53+Будник!AQ53 -> 7727 | AR53: =SUM(AP53:AQ53) -> 7727 | AS53: ='[5]ПП ВДГ'!AS53+'[5]Корсак Л.Р.'!AS53+'[5]Корсак В.І.'!AS53+[5]Конякіна!AS53 -> 3000 | AT53: ='[5]ПП ВДГ'!AT53+'[5]Корсак Л.Р.'!AT53+'[5]Корсак В.І.'!AT53+[5]Конякіна!AT53 -> 4000 | AU53: =SUM(AS53:AT53) -> 7000 | AV53: ='Солар Вест'!AV53+Будник!AV53 -> 0 | AW53: ='Солар Вест'!AW53+Будник!AW53 -> 10200 | AX53: =SUM(AV53:AW53) -> 10200 | AY53: ='[5]ПП ВДГ'!AY53+'[5]Корсак Л.Р.'!AY53+'[5]Корсак В.І.'!AY53+[5]Конякіна!AY53 -> 3000 | AZ53: ='[5]ПП ВДГ'!AZ53+'[5]Корсак Л.Р.'!AZ53+'[5]Корсак В.І.'!AZ53+[5]Конякіна!AZ53 -> 4000 | BA53: =SUM(AY53:AZ53) -> 7000 | BB53: ='Солар Вест'!BB53+Будник!BB53 -> 0 | BC53: ='Солар Вест'!BC53+Будник!BC53 -> 0 | BD53: =SUM(BB53:BC53) -> 0 | BE53: ='Солар Вест'!BE53+Будник!BE53 -> 0 | BF53: ='Солар Вест'!BF53+Будник!BF53 -> 190 | BG53: =SUM(BE53:BF53) -> 190 | BH53: ='Солар Вест'!BH53+Будник!BH53 -> 0 | BI53: ='Солар Вест'!BI53+Будник!BI53 -> 0 | BJ53: =SUM(BH53:BI53) -> 0 | BK53: ='[5]ПП ВДГ'!BK53+'[5]Корсак Л.Р.'!BK53+'[5]Корсак В.І.'!BK53+[5]Конякіна!BK53 -> 3000 | BL53: ='[5]ПП ВДГ'!BL53+'[5]Корсак Л.Р.'!BL53+'[5]Корсак В.І.'!BL53+[5]Конякіна!BL53 -> 4000 | BM53: =SUM(BK53:BL53) -> 7000 | BN53: ='Солар Вест'!BN53+Будник!BN53 -> 0 | BO53: ='Солар Вест'!BO53+Будник!BO53 -> 0 | BP53: =SUM(BN53:BO53) -> 0 | BQ53: ='[5]ПП ВДГ'!BQ53+'[5]Корсак Л.Р.'!BQ53+'[5]Корсак В.І.'!BQ53+[5]Конякіна!BQ53 -> 4000 | BR53: ='[5]ПП ВДГ'!BR53+'[5]Корсак Л.Р.'!BR53+'[5]Корсак В.І.'!BR53+[5]Конякіна!BR53 -> 4000 | BS53: =SUM(BQ53:BR53) -> 8000 | BT53: ='Солар Вест'!BT53+Будник!BT53 -> 0 | BU53: ='Солар Вест'!BU53+Будник!BU53 -> 0 | BV53: =SUM(BT53:BU53) -> 0 | BW53: =+C53+I53+O53+AA53+AG53+U53+AM53+AS53+AY53+BE53+BK53+BQ53 -> 43000 | BX53: =+D53+J53+P53+AB53+AH53+V53+AN53+AT53+AZ53+BF53+BL53+BR53 -> 53190 | BY53: =SUM(BW53:BX53) -> 96190 | BZ53: =+F53+L53+R53+AD53+AJ53+X53+AP53+AV53+BB53+BH53+BN53+BT53 -> 0 | CA53: =+G53+M53+S53+AE53+AK53+Y53+AQ53+AW53+BC53+BI53+BO53+BU53 -> 21827 | CB53: =SUM(BZ53:CA53) -> 21827
A54: 133 | B54: Банківські послуги | C54: ='[5]ПП ВДГ'!C54+'[5]Корсак Л.Р.'!C54+'[5]Корсак В.І.'!C54+[5]Конякіна!C54 -> 885 | D54: ='[5]ПП ВДГ'!D54+'[5]Корсак Л.Р.'!D54+'[5]Корсак В.І.'!D54+[5]Конякіна!D54 -> 305 | E54: =SUM(C54:D54) -> 1190 | F54: ='Солар Вест'!F54+Будник!F54 -> 467.45 | G54: ='Солар Вест'!G54+Будник!G54 -> 0 | H54: =SUM(F54:G54) -> 467.45 | I54: ='[5]ПП ВДГ'!I54+'[5]Корсак Л.Р.'!I54+'[5]Корсак В.І.'!I54+[5]Конякіна!I54 -> 885 | J54: ='[5]ПП ВДГ'!J54+'[5]Корсак Л.Р.'!J54+'[5]Корсак В.І.'!J54+[5]Конякіна!J54 -> 305 | K54: =SUM(I54:J54) -> 1190 | L54: ='Солар Вест'!L54+Будник!L54 -> 600.45 | M54: ='Солар Вест'!M54+Будник!M54 -> 0 | N54: =SUM(L54:M54) -> 600.45 | O54: ='[5]ПП ВДГ'!O54+'[5]Корсак Л.Р.'!O54+'[5]Корсак В.І.'!O54+[5]Конякіна!O54 -> 885 | P54: ='[5]ПП ВДГ'!P54+'[5]Корсак Л.Р.'!P54+'[5]Корсак В.І.'!P54+[5]Конякіна!P54 -> 305 | Q54: =SUM(O54:P54) -> 1190 | R54: ='Солар Вест'!R54+Будник!R54 -> 2245.08 | S54: ='Солар Вест'!S54+Будник!S54 -> 0 | T54: =SUM(R54:S54) -> 2245.08 | U54: ='[5]ПП ВДГ'!U54+'[5]Корсак Л.Р.'!U54+'[5]Корсак В.І.'!U54+[5]Конякіна!U54 -> 450 | V54: ='[5]ПП ВДГ'!V54+'[5]Корсак Л.Р.'!V54+'[5]Корсак В.І.'!V54+[5]Конякіна!V54 -> 568 | W54: =SUM(U54:V54) -> 1018 | X54: ='Солар Вест'!X54+Будник!X54 -> 1239.99 | Y54: ='Солар Вест'!Y54+Будник!Y54 -> 0 | Z54: =SUM(X54:Y54) -> 1239.99 | AA54: ='[5]ПП ВДГ'!AA54+'[5]Корсак Л.Р.'!AA54+'[5]Корсак В.І.'!AA54+[5]Конякіна!AA54 -> 885 | AB54: ='[5]ПП ВДГ'!AB54+'[5]Корсак Л.Р.'!AB54+'[5]Корсак В.І.'!AB54+[5]Конякіна!AB54 -> 305 | AC54: =SUM(AA54:AB54) -> 1190 | AD54: ='Солар Вест'!AD54+Будник!AD54 -> 2563.94 | AE54: ='Солар Вест'!AE54+Будник!AE54 -> 0 | AF54: =SUM(AD54:AE54) -> 2563.94 | AG54: ='[5]ПП ВДГ'!AG54+'[5]Корсак Л.Р.'!AG54+'[5]Корсак В.І.'!AG54+[5]Конякіна!AG54 -> 885 | AH54: ='[5]ПП ВДГ'!AH54+'[5]Корсак Л.Р.'!AH54+'[5]Корсак В.І.'!AH54+[5]Конякіна!AH54 -> 232 | AI54: =SUM(AG54:AH54) -> 1117 | AJ54: ='Солар Вест'!AJ54+Будник!AJ54 -> 3561.35 | AK54: ='Солар Вест'!AK54+Будник!AK54 -> 1003 | AL54: =SUM(AJ54:AK54) -> 4564.35 | AM54: ='[5]ПП ВДГ'!AM54+'[5]Корсак Л.Р.'!AM54+'[5]Корсак В.І.'!AM54+[5]Конякіна!AM54 -> 885 | AN54: ='[5]ПП ВДГ'!AN54+'[5]Корсак Л.Р.'!AN54+'[5]Корсак В.І.'!AN54+[5]Конякіна!AN54 -> 235 | AO54: =SUM(AM54:AN54) -> 1120 | AP54: ='Солар Вест'!AP54+Будник!AP54 -> 1292 | AQ54: ='Солар Вест'!AQ54+Будник!AQ54 -> 0 | AR54: =SUM(AP54:AQ54) -> 1292 | AS54: ='[5]ПП ВДГ'!AS54+'[5]Корсак Л.Р.'!AS54+'[5]Корсак В.І.'!AS54+[5]Конякіна!AS54 -> 1085 | AT54: ='[5]ПП ВДГ'!AT54+'[5]Корсак Л.Р.'!AT54+'[5]Корсак В.І.'!AT54+[5]Конякіна!AT54 -> 235 | AU54: =SUM(AS54:AT54) -> 1320 | AV54: ='Солар Вест'!AV54+Будник!AV54 -> 1755.82 | AW54: ='Солар Вест'!AW54+Будник!AW54 -> 0 | AX54: =SUM(AV54:AW54) -> 1755.82 | AY54: ='[5]ПП ВДГ'!AY54+'[5]Корсак Л.Р.'!AY54+'[5]Корсак В.І.'!AY54+[5]Конякіна!AY54 -> 885 | AZ54: ='[5]ПП ВДГ'!AZ54+'[5]Корсак Л.Р.'!AZ54+'[5]Корсак В.І.'!AZ54+[5]Конякіна!AZ54 -> 305 | BA54: =SUM(AY54:AZ54) -> 1190 | BB54: ='Солар Вест'!BB54+Будник!BB54 -> 1649.45 | BC54: ='Солар Вест'!BC54+Будник!BC54 -> 0 | BD54: =SUM(BB54:BC54) -> 1649.45 | BE54: ='Солар Вест'!BE54+Будник!BE54 -> 1320.77 | BF54: ='Солар Вест'!BF54+Будник!BF54 -> 0 | BG54: =SUM(BE54:BF54) -> 1320.77 | BH54: ='Солар Вест'!BH54+Будник!BH54 -> 0 | BI54: ='Солар Вест'!BI54+Будник!BI54 -> 0 | BJ54: =SUM(BH54:BI54) -> 0 | BK54: ='[5]ПП ВДГ'!BK54+'[5]Корсак Л.Р.'!BK54+'[5]Корсак В.І.'!BK54+[5]Конякіна!BK54 -> 835 | BL54: ='[5]ПП ВДГ'!BL54+'[5]Корсак Л.Р.'!BL54+'[5]Корсак В.І.'!BL54+[5]Конякіна!BL54 -> 232 | BM54: =SUM(BK54:BL54) -> 1067 | BN54: ='Солар Вест'!BN54+Будник!BN54 -> 0 | BO54: ='Солар Вест'!BO54+Будник!BO54 -> 0 | BP54: =SUM(BN54:BO54) -> 0 | BQ54: ='[5]ПП ВДГ'!BQ54+'[5]Корсак Л.Р.'!BQ54+'[5]Корсак В.І.'!BQ54+[5]Конякіна!BQ54 -> 800 | BR54: ='[5]ПП ВДГ'!BR54+'[5]Корсак Л.Р.'!BR54+'[5]Корсак В.І.'!BR54+[5]Конякіна!BR54 -> 330 | BS54: =SUM(BQ54:BR54) -> 1130 | BT54: ='Солар Вест'!BT54+Будник!BT54 -> 0 | BU54: ='Солар Вест'!BU54+Будник!BU54 -> 0 | BV54: =SUM(BT54:BU54) -> 0 | BW54: =+C54+I54+O54+AA54+AG54+U54+AM54+AS54+AY54+BE54+BK54+BQ54 -> 10685.77 | BX54: =+D54+J54+P54+AB54+AH54+V54+AN54+AT54+AZ54+BF54+BL54+BR54 -> 3357 | BY54: =SUM(BW54:BX54) -> 14042.77 | BZ54: =+F54+L54+R54+AD54+AJ54+X54+AP54+AV54+BB54+BH54+BN54+BT54 -> 15375.53 | CA54: =+G54+M54+S54+AE54+AK54+Y54+AQ54+AW54+BC54+BI54+BO54+BU54 -> 1003 | CB54: =SUM(BZ54:CA54) -> 16378.53
A55: 134 | B55: Поточні офісні витрати (зв'язок, ІТ, періодика, інш) | C55: ='[5]ПП ВДГ'!C55+'[5]Корсак Л.Р.'!C55+'[5]Корсак В.І.'!C55+[5]Конякіна!C55 -> 2610 | D55: ='[5]ПП ВДГ'!D55+'[5]Корсак Л.Р.'!D55+'[5]Корсак В.І.'!D55+[5]Конякіна!D55 -> 0 | E55: =SUM(C55:D55) -> 2610 | F55: ='Солар Вест'!F55+Будник!F55 -> 0 | G55: ='Солар Вест'!G55+Будник!G55 -> 385 | H55: =SUM(F55:G55) -> 385 | I55: ='[5]ПП ВДГ'!I55+'[5]Корсак Л.Р.'!I55+'[5]Корсак В.І.'!I55+[5]Конякіна!I55 -> 2610 | J55: ='[5]ПП ВДГ'!J55+'[5]Корсак Л.Р.'!J55+'[5]Корсак В.І.'!J55+[5]Конякіна!J55 -> 0 | K55: =SUM(I55:J55) -> 2610 | L55: ='Солар Вест'!L55+Будник!L55 -> 0 | M55: ='Солар Вест'!M55+Будник!M55 -> 750 | N55: =SUM(L55:M55) -> 750 | O55: ='[5]ПП ВДГ'!O55+'[5]Корсак Л.Р.'!O55+'[5]Корсак В.І.'!O55+[5]Конякіна!O55 -> 2610 | P55: ='[5]ПП ВДГ'!P55+'[5]Корсак Л.Р.'!P55+'[5]Корсак В.І.'!P55+[5]Конякіна!P55 -> 0 | Q55: =SUM(O55:P55) -> 2610 | R55: ='Солар Вест'!R55+Будник!R55 -> 0 | S55: ='Солар Вест'!S55+Будник!S55 -> 0 | T55: =SUM(R55:S55) -> 0 | U55: ='[5]ПП ВДГ'!U55+'[5]Корсак Л.Р.'!U55+'[5]Корсак В.І.'!U55+[5]Конякіна!U55 -> 4000 | V55: ='[5]ПП ВДГ'!V55+'[5]Корсак Л.Р.'!V55+'[5]Корсак В.І.'!V55+[5]Конякіна!V55 -> 0 | W55: =SUM(U55:V55) -> 4000 | X55: ='Солар Вест'!X55+Будник!X55 -> 0 | Y55: ='Солар Вест'!Y55+Будник!Y55 -> 0 | Z55: =SUM(X55:Y55) -> 0 | AA55: ='[5]ПП ВДГ'!AA55+'[5]Корсак Л.Р.'!AA55+'[5]Корсак В.І.'!AA55+[5]Конякіна!AA55 -> 2610 | AB55: ='[5]ПП ВДГ'!AB55+'[5]Корсак Л.Р.'!AB55+'[5]Корсак В.І.'!AB55+[5]Конякіна!AB55 -> 0 | AC55: =SUM(AA55:AB55) -> 2610 | AD55: ='Солар Вест'!AD55+Будник!AD55 -> 0 | AE55: ='Солар Вест'!AE55+Будник!AE55 -> 0 | AF55: =SUM(AD55:AE55) -> 0 | AG55: ='[5]ПП ВДГ'!AG55+'[5]Корсак Л.Р.'!AG55+'[5]Корсак В.І.'!AG55+[5]Конякіна!AG55 -> 2610 | AH55: ='[5]ПП ВДГ'!AH55+'[5]Корсак Л.Р.'!AH55+'[5]Корсак В.І.'!AH55+[5]Конякіна!AH55 -> 0 | AI55: =SUM(AG55:AH55) -> 2610 | AJ55: ='Солар Вест'!AJ55+Будник!AJ55 -> 0 | AK55: ='Солар Вест'!AK55+Будник!AK55 -> 347 | AL55: =SUM(AJ55:AK55) -> 347 | AM55: ='[5]ПП ВДГ'!AM55+'[5]Корсак Л.Р.'!AM55+'[5]Корсак В.І.'!AM55+[5]Конякіна!AM55 -> 3410 | AN55: ='[5]ПП ВДГ'!AN55+'[5]Корсак Л.Р.'!AN55+'[5]Корсак В.І.'!AN55+[5]Конякіна!AN55 -> 0 | AO55: =SUM(AM55:AN55) -> 3410 | AP55: ='Солар Вест'!AP55+Будник!AP55 -> 0 | AQ55: ='Солар Вест'!AQ55+Будник!AQ55 -> 0 | AR55: =SUM(AP55:AQ55) -> 0 | AS55: ='[5]ПП ВДГ'!AS55+'[5]Корсак Л.Р.'!AS55+'[5]Корсак В.І.'!AS55+[5]Конякіна!AS55 -> 3310 | AT55: ='[5]ПП ВДГ'!AT55+'[5]Корсак Л.Р.'!AT55+'[5]Корсак В.І.'!AT55+[5]Конякіна!AT55 -> 0 | AU55: =SUM(AS55:AT55) -> 3310 | AV55: ='Солар Вест'!AV55+Будник!AV55 -> 0 | AW55: ='Солар Вест'!AW55+Будник!AW55 -> 0 | AX55: =SUM(AV55:AW55) -> 0 | AY55: ='[5]ПП ВДГ'!AY55+'[5]Корсак Л.Р.'!AY55+'[5]Корсак В.І.'!AY55+[5]Конякіна!AY55 -> 2610 | AZ55: ='[5]ПП ВДГ'!AZ55+'[5]Корсак Л.Р.'!AZ55+'[5]Корсак В.І.'!AZ55+[5]Конякіна!AZ55 -> 0 | BA55: =SUM(AY55:AZ55) -> 2610 | BB55: ='Солар Вест'!BB55+Будник!BB55 -> 0 | BC55: ='Солар Вест'!BC55+Будник!BC55 -> 6165 | BD55: =SUM(BB55:BC55) -> 6165 | BE55: ='Солар Вест'!BE55+Будник!BE55 -> 0 | BF55: ='Солар Вест'!BF55+Будник!BF55 -> 14700 | BG55: =SUM(BE55:BF55) -> 14700 | BH55: ='Солар Вест'!BH55+Будник!BH55 -> 0 | BI55: ='Солар Вест'!BI55+Будник!BI55 -> 0 | BJ55: =SUM(BH55:BI55) -> 0 | BK55: ='[5]ПП ВДГ'!BK55+'[5]Корсак Л.Р.'!BK55+'[5]Корсак В.І.'!BK55+[5]Конякіна!BK55 -> 6010 | BL55: ='[5]ПП ВДГ'!BL55+'[5]Корсак Л.Р.'!BL55+'[5]Корсак В.І.'!BL55+[5]Конякіна!BL55 -> 0 | BM55: =SUM(BK55:BL55) -> 6010 | BN55: ='Солар Вест'!BN55+Будник!BN55 -> 0 | BO55: ='Солар Вест'!BO55+Будник!BO55 -> 0 | BP55: =SUM(BN55:BO55) -> 0 | BQ55: ='[5]ПП ВДГ'!BQ55+'[5]Корсак Л.Р.'!BQ55+'[5]Корсак В.І.'!BQ55+[5]Конякіна!BQ55 -> 6010 | BR55: ='[5]ПП ВДГ'!BR55+'[5]Корсак Л.Р.'!BR55+'[5]Корсак В.І.'!BR55+[5]Конякіна!BR55 -> 0 | BS55: =SUM(BQ55:BR55) -> 6010 | BT55: ='Солар Вест'!BT55+Будник!BT55 -> 0 | BU55: ='Солар Вест'!BU55+Будник!BU55 -> 0 | BV55: =SUM(BT55:BU55) -> 0 | BW55: =+C55+I55+O55+AA55+AG55+U55+AM55+AS55+AY55+BE55+BK55+BQ55 -> 38400 | BX55: =+D55+J55+P55+AB55+AH55+V55+AN55+AT55+AZ55+BF55+BL55+BR55 -> 14700 | BY55: =SUM(BW55:BX55) -> 53100 | BZ55: =+F55+L55+R55+AD55+AJ55+X55+AP55+AV55+BB55+BH55+BN55+BT55 -> 0 | CA55: =+G55+M55+S55+AE55+AK55+Y55+AQ55+AW55+BC55+BI55+BO55+BU55 -> 7647 | CB55: =SUM(BZ55:CA55) -> 7647
A56: 135 | B56: Податки і збори | C56: ='[5]ПП ВДГ'!C56+'[5]Корсак Л.Р.'!C56+'[5]Корсак В.І.'!C56+[5]Конякіна!C56 -> 40020 | D56: ='[5]ПП ВДГ'!D56+'[5]Корсак Л.Р.'!D56+'[5]Корсак В.І.'!D56+[5]Конякіна!D56 -> 23300 | E56: =SUM(C56:D56) -> 63320 | F56: ='Солар Вест'!F56+Будник!F56 -> 0 | G56: ='Солар Вест'!G56+Будник!G56 -> 0 | H56: =SUM(F56:G56) -> 0 | I56: ='[5]ПП ВДГ'!I56+'[5]Корсак Л.Р.'!I56+'[5]Корсак В.І.'!I56+[5]Конякіна!I56 -> 40020 | J56: ='[5]ПП ВДГ'!J56+'[5]Корсак Л.Р.'!J56+'[5]Корсак В.І.'!J56+[5]Конякіна!J56 -> 23300 | K56: =SUM(I56:J56) -> 63320 | L56: ='Солар Вест'!L56+Будник!L56 -> 0 | M56: ='Солар Вест'!M56+Будник!M56 -> 0 | N56: =SUM(L56:M56) -> 0 | O56: ='[5]ПП ВДГ'!O56+'[5]Корсак Л.Р.'!O56+'[5]Корсак В.І.'!O56+[5]Конякіна!O56 -> 40020 | P56: ='[5]ПП ВДГ'!P56+'[5]Корсак Л.Р.'!P56+'[5]Корсак В.І.'!P56+[5]Конякіна!P56 -> 23300 | Q56: =SUM(O56:P56) -> 63320 | R56: ='Солар Вест'!R56+Будник!R56 -> 6322 | S56: ='Солар Вест'!S56+Будник!S56 -> 0 | T56: =SUM(R56:S56) -> 6322 | U56: ='[5]ПП ВДГ'!U56+'[5]Корсак Л.Р.'!U56+'[5]Корсак В.І.'!U56+[5]Конякіна!U56 -> 50000 | V56: ='[5]ПП ВДГ'!V56+'[5]Корсак Л.Р.'!V56+'[5]Корсак В.І.'!V56+[5]Конякіна!V56 -> 27491 | W56: =SUM(U56:V56) -> 77491 | X56: ='Солар Вест'!X56+Будник!X56 -> 2400 | Y56: ='Солар Вест'!Y56+Будник!Y56 -> 0 | Z56: =SUM(X56:Y56) -> 2400 | AA56: ='[5]ПП ВДГ'!AA56+'[5]Корсак Л.Р.'!AA56+'[5]Корсак В.І.'!AA56+[5]Конякіна!AA56 -> 40020 | AB56: ='[5]ПП ВДГ'!AB56+'[5]Корсак Л.Р.'!AB56+'[5]Корсак В.І.'!AB56+[5]Конякіна!AB56 -> 22550 | AC56: =SUM(AA56:AB56) -> 62570 | AD56: ='Солар Вест'!AD56+Будник!AD56 -> 2400 | AE56: ='Солар Вест'!AE56+Будник!AE56 -> 0 | AF56: =SUM(AD56:AE56) -> 2400 | AG56: ='[5]ПП ВДГ'!AG56+'[5]Корсак Л.Р.'!AG56+'[5]Корсак В.І.'!AG56+[5]Конякіна!AG56 -> 40000 | AH56: ='[5]ПП ВДГ'!AH56+'[5]Корсак Л.Р.'!AH56+'[5]Корсак В.І.'!AH56+[5]Конякіна!AH56 -> 22530 | AI56: =SUM(AG56:AH56) -> 62530 | AJ56: ='Солар Вест'!AJ56+Будник!AJ56 -> 2400 | AK56: ='Солар Вест'!AK56+Будник!AK56 -> 0 | AL56: =SUM(AJ56:AK56) -> 2400 | AM56: ='[5]ПП ВДГ'!AM56+'[5]Корсак Л.Р.'!AM56+'[5]Корсак В.І.'!AM56+[5]Конякіна!AM56 -> 40000 | AN56: ='[5]ПП ВДГ'!AN56+'[5]Корсак Л.Р.'!AN56+'[5]Корсак В.І.'!AN56+[5]Конякіна!AN56 -> 22542 | AO56: =SUM(AM56:AN56) -> 62542 | AP56: ='Солар Вест'!AP56+Будник!AP56 -> 146356 | AQ56: ='Солар Вест'!AQ56+Будник!AQ56 -> 0 | AR56: =SUM(AP56:AQ56) -> 146356 | AS56: ='[5]ПП ВДГ'!AS56+'[5]Корсак Л.Р.'!AS56+'[5]Корсак В.І.'!AS56+[5]Конякіна!AS56 -> 39020 | AT56: ='[5]ПП ВДГ'!AT56+'[5]Корсак Л.Р.'!AT56+'[5]Корсак В.І.'!AT56+[5]Конякіна!AT56 -> 22527 | AU56: =SUM(AS56:AT56) -> 61547 | AV56: ='Солар Вест'!AV56+Будник!AV56 -> 43300 | AW56: ='Солар Вест'!AW56+Будник!AW56 -> 0 | AX56: =SUM(AV56:AW56) -> 43300 | AY56: ='[5]ПП ВДГ'!AY56+'[5]Корсак Л.Р.'!AY56+'[5]Корсак В.І.'!AY56+[5]Конякіна!AY56 -> 40020 | AZ56: ='[5]ПП ВДГ'!AZ56+'[5]Корсак Л.Р.'!AZ56+'[5]Корсак В.І.'!AZ56+[5]Конякіна!AZ56 -> 23300 | BA56: =SUM(AY56:AZ56) -> 63320 | BB56: ='Солар Вест'!BB56+Будник!BB56 -> 10437 | BC56: ='Солар Вест'!BC56+Будник!BC56 -> 0 | BD56: =SUM(BB56:BC56) -> 10437 | BE56: ='Солар Вест'!BE56+Будник!BE56 -> 12615 | BF56: ='Солар Вест'!BF56+Будник!BF56 -> 0 | BG56: =SUM(BE56:BF56) -> 12615 | BH56: ='Солар Вест'!BH56+Будник!BH56 -> 0 | BI56: ='Солар Вест'!BI56+Будник!BI56 -> 0 | BJ56: =SUM(BH56:BI56) -> 0 | BK56: ='[5]ПП ВДГ'!BK56+'[5]Корсак Л.Р.'!BK56+'[5]Корсак В.І.'!BK56+[5]Конякіна!BK56 -> 40020 | BL56: ='[5]ПП ВДГ'!BL56+'[5]Корсак Л.Р.'!BL56+'[5]Корсак В.І.'!BL56+[5]Конякіна!BL56 -> 22527 | BM56: =SUM(BK56:BL56) -> 62547 | BN56: ='Солар Вест'!BN56+Будник!BN56 -> 0 | BO56: ='Солар Вест'!BO56+Будник!BO56 -> 0 | BP56: =SUM(BN56:BO56) -> 0 | BQ56: ='[5]ПП ВДГ'!BQ56+'[5]Корсак Л.Р.'!BQ56+'[5]Корсак В.І.'!BQ56+[5]Конякіна!BQ56 -> 40020 | BR56: ='[5]ПП ВДГ'!BR56+'[5]Корсак Л.Р.'!BR56+'[5]Корсак В.І.'!BR56+[5]Конякіна!BR56 -> 22541 | BS56: =SUM(BQ56:BR56) -> 62561 | BT56: ='Солар Вест'!BT56+Будник!BT56 -> 0 | BU56: ='Солар Вест'!BU56+Будник!BU56 -> 0 | BV56: =SUM(BT56:BU56) -> 0 | BW56: =+C56+I56+O56+AA56+AG56+U56+AM56+AS56+AY56+BE56+BK56+BQ56 -> 461775 | BX56: =+D56+J56+P56+AB56+AH56+V56+AN56+AT56+AZ56+BF56+BL56+BR56 -> 255908 | BY56: =SUM(BW56:BX56) -> 717683 | BZ56: =+F56+L56+R56+AD56+AJ56+X56+AP56+AV56+BB56+BH56+BN56+BT56 -> 213615 | CA56: =+G56+M56+S56+AE56+AK56+Y56+AQ56+AW56+BC56+BI56+BO56+BU56 -> 0 | CB56: =SUM(BZ56:CA56) -> 213615
A57: 136 | B57: Інші операційні витрати | C57: ='[5]ПП ВДГ'!C57+'[5]Корсак Л.Р.'!C57+'[5]Корсак В.І.'!C57+[5]Конякіна!C57 -> 0 | D57: ='[5]ПП ВДГ'!D57+'[5]Корсак Л.Р.'!D57+'[5]Корсак В.І.'!D57+[5]Конякіна!D57 -> 0 | E57: =SUM(C57:D57) -> 0 | F57: ='Солар Вест'!F57+Будник!F57 -> 0 | G57: ='Солар Вест'!G57+Будник!G57 -> 17397 | H57: =SUM(F57:G57) -> 17397 | I57: ='[5]ПП ВДГ'!I57+'[5]Корсак Л.Р.'!I57+'[5]Корсак В.І.'!I57+[5]Конякіна!I57 -> 0 | J57: ='[5]ПП ВДГ'!J57+'[5]Корсак Л.Р.'!J57+'[5]Корсак В.І.'!J57+[5]Конякіна!J57 -> 0 | K57: =SUM(I57:J57) -> 0 | L57: ='Солар Вест'!L57+Будник!L57 -> 0 | M57: ='Солар Вест'!M57+Будник!M57 -> 1440 | N57: =SUM(L57:M57) -> 1440 | O57: ='[5]ПП ВДГ'!O57+'[5]Корсак Л.Р.'!O57+'[5]Корсак В.І.'!O57+[5]Конякіна!O57 -> 0 | P57: ='[5]ПП ВДГ'!P57+'[5]Корсак Л.Р.'!P57+'[5]Корсак В.І.'!P57+[5]Конякіна!P57 -> 0 | Q57: =SUM(O57:P57) -> 0 | R57: ='Солар Вест'!R57+Будник!R57 -> 0 | S57: ='Солар Вест'!S57+Будник!S57 -> 120 | T57: =SUM(R57:S57) -> 120 | U57: ='[5]ПП ВДГ'!U57+'[5]Корсак Л.Р.'!U57+'[5]Корсак В.І.'!U57+[5]Конякіна!U57 -> 0 | V57: ='[5]ПП ВДГ'!V57+'[5]Корсак Л.Р.'!V57+'[5]Корсак В.І.'!V57+[5]Конякіна!V57 -> 200 | W57: =SUM(U57:V57) -> 200 | X57: ='Солар Вест'!X57+Будник!X57 -> 0 | Y57: ='Солар Вест'!Y57+Будник!Y57 -> 272 | Z57: =SUM(X57:Y57) -> 272 | AA57: ='[5]ПП ВДГ'!AA57+'[5]Корсак Л.Р.'!AA57+'[5]Корсак В.І.'!AA57+[5]Конякіна!AA57 -> 0 | AB57: ='[5]ПП ВДГ'!AB57+'[5]Корсак Л.Р.'!AB57+'[5]Корсак В.І.'!AB57+[5]Конякіна!AB57 -> 0 | AC57: =SUM(AA57:AB57) -> 0 | AD57: ='Солар Вест'!AD57+Будник!AD57 -> 0 | AE57: ='Солар Вест'!AE57+Будник!AE57 -> 0 | AF57: =SUM(AD57:AE57) -> 0 | AG57: ='[5]ПП ВДГ'!AG57+'[5]Корсак Л.Р.'!AG57+'[5]Корсак В.І.'!AG57+[5]Конякіна!AG57 -> 0 | AH57: ='[5]ПП ВДГ'!AH57+'[5]Корсак Л.Р.'!AH57+'[5]Корсак В.І.'!AH57+[5]Конякіна!AH57 -> 250 | AI57: =SUM(AG57:AH57) -> 250 | AJ57: ='Солар Вест'!AJ57+Будник!AJ57 -> 0 | AK57: ='Солар Вест'!AK57+Будник!AK57 -> 12100 | AL57: =SUM(AJ57:AK57) -> 12100 | AM57: ='[5]ПП ВДГ'!AM57+'[5]Корсак Л.Р.'!AM57+'[5]Корсак В.І.'!AM57+[5]Конякіна!AM57 -> 0 | AN57: ='[5]ПП ВДГ'!AN57+'[5]Корсак Л.Р.'!AN57+'[5]Корсак В.І.'!AN57+[5]Конякіна!AN57 -> 225 | AO57: =SUM(AM57:AN57) -> 225 | AP57: ='Солар Вест'!AP57+Будник!AP57 -> 0 | AQ57: ='Солар Вест'!AQ57+Будник!AQ57 -> 9940 | AR57: =SUM(AP57:AQ57) -> 9940 | AS57: ='[5]ПП ВДГ'!AS57+'[5]Корсак Л.Р.'!AS57+'[5]Корсак В.І.'!AS57+[5]Конякіна!AS57 -> 0 | AT57: ='[5]ПП ВДГ'!AT57+'[5]Корсак Л.Р.'!AT57+'[5]Корсак В.І.'!AT57+[5]Конякіна!AT57 -> 250 | AU57: =SUM(AS57:AT57) -> 250 | AV57: ='Солар Вест'!AV57+Будник!AV57 -> 0 | AW57: ='Солар Вест'!AW57+Будник!AW57 -> 4245 | AX57: =SUM(AV57:AW57) -> 4245 | AY57: ='[5]ПП ВДГ'!AY57+'[5]Корсак Л.Р.'!AY57+'[5]Корсак В.І.'!AY57+[5]Конякіна!AY57 -> 0 | AZ57: ='[5]ПП ВДГ'!AZ57+'[5]Корсак Л.Р.'!AZ57+'[5]Корсак В.І.'!AZ57+[5]Конякіна!AZ57 -> 0 | BA57: =SUM(AY57:AZ57) -> 0 | BB57: ='Солар Вест'!BB57+Будник!BB57 -> 0 | BC57: ='Солар Вест'!BC57+Будник!BC57 -> 850 | BD57: =SUM(BB57:BC57) -> 850 | BE57: ='Солар Вест'!BE57+Будник!BE57 -> 0 | BF57: ='Солар Вест'!BF57+Будник!BF57 -> 0 | BG57: =SUM(BE57:BF57) -> 0 | BH57: ='Солар Вест'!BH57+Будник!BH57 -> 0 | BI57: ='Солар Вест'!BI57+Будник!BI57 -> 0 | BJ57: =SUM(BH57:BI57) -> 0 | BK57: ='[5]ПП ВДГ'!BK57+'[5]Корсак Л.Р.'!BK57+'[5]Корсак В.І.'!BK57+[5]Конякіна!BK57 -> 0 | BL57: ='[5]ПП ВДГ'!BL57+'[5]Корсак Л.Р.'!BL57+'[5]Корсак В.І.'!BL57+[5]Конякіна!BL57 -> 500 | BM57: =SUM(BK57:BL57) -> 500 | BN57: ='Солар Вест'!BN57+Будник!BN57 -> 0 | BO57: ='Солар Вест'!BO57+Будник!BO57 -> 0 | BP57: =SUM(BN57:BO57) -> 0 | BQ57: ='[5]ПП ВДГ'!BQ57+'[5]Корсак Л.Р.'!BQ57+'[5]Корсак В.І.'!BQ57+[5]Конякіна!BQ57 -> 0 | BR57: ='[5]ПП ВДГ'!BR57+'[5]Корсак Л.Р.'!BR57+'[5]Корсак В.І.'!BR57+[5]Конякіна!BR57 -> 500 | BS57: =SUM(BQ57:BR57) -> 500 | BT57: ='Солар Вест'!BT57+Будник!BT57 -> 0 | BU57: ='Солар Вест'!BU57+Будник!BU57 -> 0 | BV57: =SUM(BT57:BU57) -> 0 | BW57: =+C57+I57+O57+AA57+AG57+U57+AM57+AS57+AY57+BE57+BK57+BQ57 -> 0 | BX57: =+D57+J57+P57+AB57+AH57+V57+AN57+AT57+AZ57+BF57+BL57+BR57 -> 1925 | BY57: =SUM(BW57:BX57) -> 1925 | BZ57: =+F57+L57+R57+AD57+AJ57+X57+AP57+AV57+BB57+BH57+BN57+BT57 -> 0 | CA57: =+G57+M57+S57+AE57+AK57+Y57+AQ57+AW57+BC57+BI57+BO57+BU57 -> 46364 | CB57: =SUM(BZ57:CA57) -> 46364
A58: 221 | B58: Повернення кредитів та позик | C58: ='[5]ПП ВДГ'!C58+'[5]Корсак Л.Р.'!C58+'[5]Корсак В.І.'!C58+[5]Конякіна!C58 -> 0 | D58: ='[5]ПП ВДГ'!D58+'[5]Корсак Л.Р.'!D58+'[5]Корсак В.І.'!D58+[5]Конякіна!D58 -> 0 | E58: =SUM(C58:D58) -> 0 | F58: ='Солар Вест'!F58+Будник!F58 -> 0 | G58: ='Солар Вест'!G58+Будник!G58 -> 0 | H58: =SUM(F58:G58) -> 0 | I58: ='[5]ПП ВДГ'!I58+'[5]Корсак Л.Р.'!I58+'[5]Корсак В.І.'!I58+[5]Конякіна!I58 -> 0 | J58: ='[5]ПП ВДГ'!J58+'[5]Корсак Л.Р.'!J58+'[5]Корсак В.І.'!J58+[5]Конякіна!J58 -> 0 | K58: =SUM(I58:J58) -> 0 | L58: ='Солар Вест'!L58+Будник!L58 -> 0 | M58: ='Солар Вест'!M58+Будник!M58 -> 0 | N58: =SUM(L58:M58) -> 0 | O58: ='[5]ПП ВДГ'!O58+'[5]Корсак Л.Р.'!O58+'[5]Корсак В.І.'!O58+[5]Конякіна!O58 -> 0 | P58: ='[5]ПП ВДГ'!P58+'[5]Корсак Л.Р.'!P58+'[5]Корсак В.І.'!P58+[5]Конякіна!P58 -> 0 | Q58: =SUM(O58:P58) -> 0 | R58: ='Солар Вест'!R58+Будник!R58 -> 0 | S58: ='Солар Вест'!S58+Будник!S58 -> 0 | T58: =SUM(R58:S58) -> 0 | U58: ='[5]ПП ВДГ'!U58+'[5]Корсак Л.Р.'!U58+'[5]Корсак В.І.'!U58+[5]Конякіна!U58 -> 27757 | V58: ='[5]ПП ВДГ'!V58+'[5]Корсак Л.Р.'!V58+'[5]Корсак В.І.'!V58+[5]Конякіна!V58 -> 0 | W58: =SUM(U58:V58) -> 27757 | X58: ='Солар Вест'!X58+Будник!X58 -> 0 | Y58: ='Солар Вест'!Y58+Будник!Y58 -> 0 | Z58: =SUM(X58:Y58) -> 0 | AA58: ='[5]ПП ВДГ'!AA58+'[5]Корсак Л.Р.'!AA58+'[5]Корсак В.І.'!AA58+[5]Конякіна!AA58 -> 0 | AB58: ='[5]ПП ВДГ'!AB58+'[5]Корсак Л.Р.'!AB58+'[5]Корсак В.І.'!AB58+[5]Конякіна!AB58 -> 0 | AC58: =SUM(AA58:AB58) -> 0 | AD58: ='Солар Вест'!AD58+Будник!AD58 -> 0 | AE58: ='Солар Вест'!AE58+Будник!AE58 -> 0 | AF58: =SUM(AD58:AE58) -> 0 | AG58: ='[5]ПП ВДГ'!AG58+'[5]Корсак Л.Р.'!AG58+'[5]Корсак В.І.'!AG58+[5]Конякіна!AG58 -> 5407 | AH58: ='[5]ПП ВДГ'!AH58+'[5]Корсак Л.Р.'!AH58+'[5]Корсак В.І.'!AH58+[5]Конякіна!AH58 -> 0 | AI58: =SUM(AG58:AH58) -> 5407 | AJ58: ='Солар Вест'!AJ58+Будник!AJ58 -> 0 | AK58: ='Солар Вест'!AK58+Будник!AK58 -> 0 | AL58: =SUM(AJ58:AK58) -> 0 | AM58: ='[5]ПП ВДГ'!AM58+'[5]Корсак Л.Р.'!AM58+'[5]Корсак В.І.'!AM58+[5]Конякіна!AM58 -> 5202 | AN58: ='[5]ПП ВДГ'!AN58+'[5]Корсак Л.Р.'!AN58+'[5]Корсак В.І.'!AN58+[5]Конякіна!AN58 -> 0 | AO58: =SUM(AM58:AN58) -> 5202 | AP58: ='Солар Вест'!AP58+Будник!AP58 -> 0 | AQ58: ='Солар Вест'!AQ58+Будник!AQ58 -> 0 | AR58: =SUM(AP58:AQ58) -> 0 | AS58: ='[5]ПП ВДГ'!AS58+'[5]Корсак Л.Р.'!AS58+'[5]Корсак В.І.'!AS58+[5]Конякіна!AS58 -> 5006 | AT58: ='[5]ПП ВДГ'!AT58+'[5]Корсак Л.Р.'!AT58+'[5]Корсак В.І.'!AT58+[5]Конякіна!AT58 -> 0 | AU58: =SUM(AS58:AT58) -> 5006 | AV58: ='Солар Вест'!AV58+Будник!AV58 -> 0 | AW58: ='Солар Вест'!AW58+Будник!AW58 -> 0 | AX58: =SUM(AV58:AW58) -> 0 | AY58: ='[5]ПП ВДГ'!AY58+'[5]Корсак Л.Р.'!AY58+'[5]Корсак В.І.'!AY58+[5]Конякіна!AY58 -> 0 | AZ58: ='[5]ПП ВДГ'!AZ58+'[5]Корсак Л.Р.'!AZ58+'[5]Корсак В.І.'!AZ58+[5]Конякіна!AZ58 -> 0 | BA58: =SUM(AY58:AZ58) -> 0 | BB58: ='Солар Вест'!BB58+Будник!BB58 -> 0 | BC58: ='Солар Вест'!BC58+Будник!BC58 -> 0 | BD58: =SUM(BB58:BC58) -> 0 | BE58: ='Солар Вест'!BE58+Будник!BE58 -> 0 | BF58: ='Солар Вест'!BF58+Будник!BF58 -> 0 | BG58: =SUM(BE58:BF58) -> 0 | BH58: ='Солар Вест'!BH58+Будник!BH58 -> 0 | BI58: ='Солар Вест'!BI58+Будник!BI58 -> 0 | BJ58: =SUM(BH58:BI58) -> 0 | BK58: ='[5]ПП ВДГ'!BK58+'[5]Корсак Л.Р.'!BK58+'[5]Корсак В.І.'!BK58+[5]Конякіна!BK58 -> 0 | BL58: ='[5]ПП ВДГ'!BL58+'[5]Корсак Л.Р.'!BL58+'[5]Корсак В.І.'!BL58+[5]Конякіна!BL58 -> 0 | BM58: =SUM(BK58:BL58) -> 0 | BN58: ='Солар Вест'!BN58+Будник!BN58 -> 0 | BO58: ='Солар Вест'!BO58+Будник!BO58 -> 0 | BP58: =SUM(BN58:BO58) -> 0 | BQ58: ='[5]ПП ВДГ'!BQ58+'[5]Корсак Л.Р.'!BQ58+'[5]Корсак В.І.'!BQ58+[5]Конякіна!BQ58 -> 0 | BR58: ='[5]ПП ВДГ'!BR58+'[5]Корсак Л.Р.'!BR58+'[5]Корсак В.І.'!BR58+[5]Конякіна!BR58 -> 0 | BS58: =SUM(BQ58:BR58) -> 0 | BT58: ='Солар Вест'!BT58+Будник!BT58 -> 0 | BU58: ='Солар Вест'!BU58+Будник!BU58 -> 0 | BV58: =SUM(BT58:BU58) -> 0 | BW58: =+C58+I58+O58+AA58+AG58+U58+AM58+AS58+AY58+BE58+BK58+BQ58 -> 43372 | BX58: =+D58+J58+P58+AB58+AH58+V58+AN58+AT58+AZ58+BF58+BL58+BR58 -> 0 | BY58: =SUM(BW58:BX58) -> 43372 | BZ58: =+F58+L58+R58+AD58+AJ58+X58+AP58+AV58+BB58+BH58+BN58+BT58 -> 0 | CA58: =+G58+M58+S58+AE58+AK58+Y58+AQ58+AW58+BC58+BI58+BO58+BU58 -> 0 | CB58: =SUM(BZ58:CA58) -> 0
